Workbook
Name _aliq_irap: [1]Tax!$D$61
Name _aliq_ires: [1]Tax!$D$60
Name _capitale_iniziale: #REF!
Name _company: [2]COVER!$B$3
Name _data_fin: #REF!
Name _data_inizio: #REF!
Name _durata_anni: #REF!
Name _inflazione: [3]cover!$B$11
Name _inflazione_mese: '[1]3.sensitivity'!$D$10
Name _intervallo_mese: #REF!
Name _newbond: [1]cover!$E$37
Name _num_rate: #REF!
Name _periodicita: #REF!
Name _rata: #REF!
Name _Scala: [2]COVER!$B$4
Name _spese_extra: #REF!
Name _tab_periodi: #REF!
Name _tablePU: [1]PU!$A$1:$B$18
Name _tasso_annuale: #REF!
Name _tasso_mutuo: #REF!
Name _tasso_VAN: #REF!
Name _tipo_periodo: #REF!
Name Altezza: #REF!
Name ArticoloFornitore: #REF!
Name CampoEX: #REF!
Name CampoEx1: #REF!
Name CampoEx2: #REF!
Name Codice: #REF!
Name ColFornitore1: #REF!
Name ColFornitore10: #REF!
Name ColFornitore11: #REF!
Name ColFornitore12: #REF!
Name ColFornitore13: #REF!
Name ColFornitore14: #REF!
Name ColFornitore15: #REF!
Name ColFornitore16: #REF!
Name ColFornitore17: #REF!
Name ColFornitore18: #REF!
Name ColFornitore19: #REF!
Name ColFornitore2: #REF!
Name ColFornitore20: #REF!
Name ColFornitore3: #REF!
Name ColFornitore4: #REF!
Name ColFornitore5: #REF!
Name ColFornitore6: #REF!
Name ColFornitore7: #REF!
Name ColFornitore8: #REF!
Name ColFornitore9: #REF!
Name Colore1: #REF!
Name Colore10: #REF!
Name Colore11: #REF!
Name Colore12: #REF!
Name Colore13: #REF!
Name Colore14: #REF!
Name Colore15: #REF!
Name Colore16: #REF!
Name Colore17: #REF!
Name Colore18: #REF!
Name Colore19: #REF!
Name Colore2: #REF!

Sheet INDICE
A2: Mese di Analisi | B2: 45838
A6: Ripartizione Manodopera Diretta
A7: Manodopera diretta di produzione | B7: PERDI | C7: 0.7
A8: Costi del personale diretto improduttivo | B8: PERIM | C8: 0.3

Sheet FOGLI PER REPORT -->

Sheet Grafici
A1: SEZIONE 1
A77: SEZIONE 2
K96: Breakdown MdC | L96: Act 12.2020 | M96: Act 12.2021 | N96: Act 12.2022 | O96: Act 12.2023 | P96: Act 12.2024 | Q96: Fct 12.2025
K97: Ricavi Totali | L97: =DB_Grafici!B64 -> 13187.454 | M97: =DB_Grafici!C64 -> 6668.3968 | N97: =DB_Grafici!D64 -> 5925.2624 | O97: =DB_Grafici!E64 -> 6006.0651 | P97: =DB_Grafici!F64 -> 7209.174 | Q97: =DB_Grafici!G64 -> 7625.0438
K98: Costi Variabili | L98: =SUM(CE_Sintetico!J9:J11)*-1 -> 8423.951 | M98: =SUM(CE_Sintetico!K9:K11)*-1 -> 3558.3326 | N98: =SUM(CE_Sintetico!L9:L11)*-1 -> 2105.6039 | O98: =SUM(CE_Sintetico!M9:M11)*-1 -> 3589.3427 | P98: =SUM(CE_Sintetico!N9:N11)*-1 -> 2635.8387 | Q98: =+SUM(CE_Esteso!K8:K11)*-1 -> 3311.4536
K99: di cui Consumi MP/SL | L99: =CE_Sintetico!J9 -> -1825.4343 | M99: =CE_Sintetico!K9 -> -1182.6431 | N99: =CE_Sintetico!L9 -> -340.13104 | O99: =CE_Sintetico!M9 -> -1092.4301 | P99: =CE_Sintetico!N9 -> -527.36397 | Q99: =+SUM(CE_Esteso!K8:K9) -> -633.54427
K100: di cui Lavorazioni Esterne | L100: =CE_Sintetico!J10 -> -4793.8641 | M100: =CE_Sintetico!K10 -> -458.0877 | N100: =CE_Sintetico!L10 -> -890.82406 | O100: =CE_Sintetico!M10 -> -1345.237 | P100: =CE_Sintetico!N10 -> -839.90733 | Q100: =+CE_Esteso!K10 -> -1102.4473
K101: di cui Manodopera Diretta | L101: =CE_Sintetico!J11 -> -1804.6526 | M101: =CE_Sintetico!K11 -> -1917.6018 | N101: =CE_Sintetico!L11 -> -874.64877 | O101: =CE_Sintetico!M11 -> -1151.6756 | P101: =CE_Sintetico!N11 -> -1268.5674 | Q101: =+CE_Esteso!K11 -> -1575.462
K102: Margine di Contribuzione | L102: =L97-L98 -> 4763.5035 | M102: =M97-M98 -> 3110.0641 | N102: =N97-N98 -> 3819.6586 | O102: =O97-O98 -> 2416.7225 | P102: =P97-P98 -> 4573.3352 | Q102: =Q97-Q98 -> 4313.5902
K103: MdC (%) | L103: =L102/L97 -> 0.36121478 | M103: =M102/M97 -> 0.46638858 | N103: =N102/N97 -> 0.64463956 | O103: =O102/O97 -> 0.40238033 | P103: =P102/P97 -> 0.63437715 | Q103: =Q102/Q97 -> 0.5657135
K115: Composizione Ricavi Commerciali | L115: ="Bdg 0"&MONTH(INDICE!$B$2)&"."&YEAR(INDICE!$B$2) -> Bdg 06.2025 | M115: ="Act 0"&MONTH(INDICE!$B$2)&"."&YEAR(INDICE!$B$2) -> Act 06.2025 | N115: Scostam. | O115: Scost (%)
J116: 07011200 | K116: =PROPER(LOWER(INDEX(Mappatura_PdC!C:C,MATCH(J116,Mappatura_PdC!B:B,0)))) -> Incassi Per Corrispettivi | L116: =-SUMIFS(DB_Complessivo!$E:$E,DB_Complessivo!$A:$A,"BDG",DB_Complessivo!$C:$C,$J116,DB_Complessivo!$B:$B,INDICE!$B$2)/1000 -> 96 | M116: =-SUMIFS(DB_Complessivo!$E:$E,DB_Complessivo!$A:$A,"ACT",DB_Complessivo!$C:$C,$J116,DB_Complessivo!$B:$B,INDICE!$B$2)/1000 -> 145.43466 | N116: =M116-L116 -> 49.43466 | O116: =IFERROR(N116/L116,"") -> 0.51494438
K117: Ricavi Netti di Vendita | L117: =+SUM(L118:L126) -> 3116 | M117: =+SUM(M118:M126) -> 3278.7257 | N117: =M117-L117 -> 162.72568 | O117: =IFERROR(N117/L117,"") -> 0.052222619
J118: 07011001 | K118: ="Di cui "&PROPER(LOWER(INDEX(Mappatura_PdC!C:C,MATCH(J118,Mappatura_PdC!B:B,0)))) -> Di cui Vendite B2B | L118: =-SUMIFS(DB_Complessivo!$E:$E,DB_Complessivo!$A:$A,"BDG",DB_Complessivo!$C:$C,$J118,DB_Complessivo!$B:$B,INDICE!$B$2)/1000 -> 3016 | M118: =-SUMIFS(DB_Complessivo!$E:$E,DB_Complessivo!$A:$A,"ACT",DB_Complessivo!$C:$C,$J118,DB_Complessivo!$B:$B,INDICE!$B$2)/1000 -> 3060.2934 | N118: =M118-L118 -> 44.29339 | O118: =IFERROR(N118/L118,"") -> 0.014686137
J119: 07011003 | K119: ="Di cui "&PROPER(LOWER(INDEX(Mappatura_PdC!C:C,MATCH(J119,Mappatura_PdC!B:B,0)))) -> Di cui Vendite Botteghe Altromercato | L119: =-SUMIFS(DB_Complessivo!$E:$E,DB_Complessivo!$A:$A,"BDG",DB_Complessivo!$C:$C,$J119,DB_Complessivo!$B:$B,INDICE!$B$2)/1000 -> 0 | M119: =-SUMIFS(DB_Complessivo!$E:$E,DB_Complessivo!$A:$A,"ACT",DB_Complessivo!$C:$C,$J119,DB_Complessivo!$B:$B,INDICE!$B$2)/1000 -> -1.03832 | N119: =M119-L119 -> -1.03832 | O119: =IFERROR(N119/L119,"")
J120: 07011004 | K120: ="Di cui "&PROPER(LOWER(INDEX(Mappatura_PdC!C:C,MATCH(J120,Mappatura_PdC!B:B,0)))) -> Di cui Ricavi Delle Vendite Altri | L120: =-SUMIFS(DB_Complessivo!$E:$E,DB_Complessivo!$A:$A,"BDG",DB_Complessivo!$C:$C,$J120,DB_Complessivo!$B:$B,INDICE!$B$2)/1000 -> 0 | M120: =-SUMIFS(DB_Complessivo!$E:$E,DB_Complessivo!$A:$A,"ACT",DB_Complessivo!$C:$C,$J120,DB_Complessivo!$B:$B,INDICE!$B$2)/1000 -> 2.40877 | N120: =M120-L120 -> 2.40877 | O120: =IFERROR(N120/L120,"")
J121: 07011007 | K121: ="Di cui "&PROPER(LOWER(INDEX(Mappatura_PdC!C:C,MATCH(J121,Mappatura_PdC!B:B,0)))) -> Di cui Vendita Tessuti | L121: =-SUMIFS(DB_Complessivo!$E:$E,DB_Complessivo!$A:$A,"BDG",DB_Complessivo!$C:$C,$J121,DB_Complessivo!$B:$B,INDICE!$B$2)/1000 -> 0 | M121: =-SUMIFS(DB_Complessivo!$E:$E,DB_Complessivo!$A:$A,"ACT",DB_Complessivo!$C:$C,$J121,DB_Complessivo!$B:$B,INDICE!$B$2)/1000 -> 2.0568 | N121: =M121-L121 -> 2.0568 | O121: =IFERROR(N121/L121,"")
J122: 07011008 | K122: ="Di cui "&PROPER(LOWER(INDEX(Mappatura_PdC!C:C,MATCH(J122,Mappatura_PdC!B:B,0)))) -> Di cui Servizi B2B | L122: =-SUMIFS(DB_Complessivo!$E:$E,DB_Complessivo!$A:$A,"BDG",DB_Complessivo!$C:$C,$J122,DB_Complessivo!$B:$B,INDICE!$B$2)/1000 -> 0 | M122: =-SUMIFS(DB_Complessivo!$E:$E,DB_Complessivo!$A:$A,"ACT",DB_Complessivo!$C:$C,$J122,DB_Complessivo!$B:$B,INDICE!$B$2)/1000 -> 12.006 | N122: =M122-L122 -> 12.006 | O122: =IFERROR(N122/L122,"")
J123: 07011009 | K123: ="Di cui "&PROPER(LOWER(INDEX(Mappatura_PdC!C:C,MATCH(J123,Mappatura_PdC!B:B,0)))) -> Di cui Ricavi Da Eventi Istituzionali | L123: =-SUMIFS(DB_Complessivo!$E:$E,DB_Complessivo!$A:$A,"BDG",DB_Complessivo!$C:$C,$J123,DB_Complessivo!$B:$B,INDICE!$B$2)/1000 -> 95 | M123: =-SUMIFS(DB_Complessivo!$E:$E,DB_Complessivo!$A:$A,"ACT",DB_Complessivo!$C:$C,$J123,DB_Complessivo!$B:$B,INDICE!$B$2)/1000 -> 59.7512 | N123: =M123-L123 -> -35.2488 | O123: =IFERROR(N123/L123,"") -> -0.37104
J124: 07011100 | K124: ="Di cui "&PROPER(LOWER(INDEX(Mappatura_PdC!C:C,MATCH(J124,Mappatura_PdC!B:B,0)))) -> Di cui Ricavi Da Prestazione Servizi | L124: =-SUMIFS(DB_Complessivo!$E:$E,DB_Complessivo!$A:$A,"BDG",DB_Complessivo!$C:$C,$J124,DB_Complessivo!$B:$B,INDICE!$B$2)/1000 -> 5 | M124: =-SUMIFS(DB_Complessivo!$E:$E,DB_Complessivo!$A:$A,"ACT",DB_Complessivo!$C:$C,$J124,DB_Complessivo!$B:$B,INDICE!$B$2)/1000 -> 0 | N124: =M124-L124 -> -5 | O124: =IFERROR(N124/L124,"") -> -1
J125: 07011101 | K125: ="Di cui "&PROPER(LOWER(INDEX(Mappatura_PdC!C:C,MATCH(J125,Mappatura_PdC!B:B,0)))) -> Di cui Prestazioni Di Servizi Yeah | L125: =-SUMIFS(DB_Complessivo!$E:$E,DB_Complessivo!$A:$A,"BDG",DB_Complessivo!$C:$C,$J125,DB_Complessivo!$B:$B,INDICE!$B$2)/1000 -> 0 | M125: =-SUMIFS(DB_Complessivo!$E:$E,DB_Complessivo!$A:$A,"ACT",DB_Complessivo!$C:$C,$J125,DB_Complessivo!$B:$B,INDICE!$B$2)/1000 -> 143.962 | N125: =M125-L125 -> 143.962 | O125: =IFERROR(N125/L125,"")
J126: 07051004 | K126: ="Di cui "&PROPER(LOWER(INDEX(Mappatura_PdC!C:C,MATCH(J126,Mappatura_PdC!B:B,0)))) -> Di cui Resi Su Vendite | L126: =-SUMIFS(DB_Complessivo!$E:$E,DB_Complessivo!$A:$A,"BDG",DB_Complessivo!$C:$C,$J126,DB_Complessivo!$B:$B,INDICE!$B$2)/1000 -> 0 | M126: =-SUMIFS(DB_Complessivo!$E:$E,DB_Complessivo!$A:$A,"ACT",DB_Complessivo!$C:$C,$J126,DB_Complessivo!$B:$B,INDICE!$B$2)/1000 -> -0.71416 | N126: =M126-L126 -> -0.71416 | O126: =IFERROR(N126/L126,"")
A147: SEZIONE 3
A203: SEZIONE 4
A236: GRAFICO FATTURATO

Sheet DB_Grafici
A1: SEZIONE 1
B3: ="Act 0"&MONTH(INDICE!$B$2)&"."&YEAR(INDICE!$B$2) -> Act 06.2025 | C3: ="Bdg 0"&MONTH(INDICE!$B$2)&"."&YEAR(INDICE!$B$2) -> Bdg 06.2025
A4: Ricavi | B4: =CE_Esteso!G7 -> 3842.6868 | C4: =+CE_Esteso!F7 -> 3543.5453
A5: MdC | B5: =+CE_Esteso!G12 -> 2178.0042 | C5: =+CE_Esteso!F12 -> 1876.9617
A6: Ebitda | B6: =+CE_Esteso!G27-SUM(CE_Esteso!G18,CE_Esteso!G25:G26) -> 93.7272 | C6: =+CE_Esteso!F27-SUM(CE_Esteso!F18,CE_Esteso!F25:F26) -> 30.758895
A7: Ebit | B7: =+CE_Esteso!G27 -> 26.51475 | C7: =+CE_Esteso!F27 -> -36.453645
B10: ="Act 0"&MONTH(INDICE!$B$2)&"."&YEAR(INDICE!B2)-1 -> Act 06.2024 | C10: ="Act 0"&MONTH(INDICE!$B$2)&"."&YEAR(INDICE!B2) -> Act 06.2025 | D10: ="Bdg 0"&MONTH(INDICE!$B$2)&"."&YEAR(INDICE!B2) -> Bdg 06.2025
A11: Ricavi | B11: =CE_Esteso!$D$7 -> 3718.5335 | C11: =CE_Esteso!$G$7 -> 3842.6868 | D11: =CE_Esteso!$F$7 -> 3543.5453
A12: MdC | B12: =+CE_Esteso!$D$12 -> 2711.8762 | C12: =+CE_Esteso!$G$12 -> 2178.0042 | D12: =+CE_Esteso!$F$12 -> 1876.9617
A13: Ebitda | B13: =+CE_Esteso!$D$27-SUM(CE_Esteso!$D$18,CE_Esteso!$D$25:$D$26) -> 957.31622 | C13: =+CE_Esteso!$G$27-SUM(CE_Esteso!$G$18,CE_Esteso!$G$25:$G$26) -> 93.7272 | D13: =+CE_Esteso!$F$27-SUM(CE_Esteso!$F$18,CE_Esteso!$F$25:$F$26) -> 30.758895
A14: Ebit | B14: =+CE_Esteso!$D$27 -> 901.13017 | C14: =+CE_Esteso!$G$27 -> 26.51475 | D14: =+CE_Esteso!$F$27 -> -36.453645
A16: Conto | B16: Descr. Conto | C16: Ricl | D16: Saldo | F16: Componenti Positive PFN
A17: 00031302 | B17: PARTECIPAZIONE IN BANCA POPOLARE DI SONDRIO | C17: C | D17: =SUMIFS(DB_Complessivo!E:E,DB_Complessivo!B:B,INDICE!$B$2,DB_Complessivo!C:C,$A17,DB_Complessivo!A:A,"ACT") -> 340 | F17: D | G17: Liquidità | H17: =SUMIFS($D$17:$D$43,$C$17:$C$43,$F17)/1000 -> 1102.995
A18: 00031303 | B18: PARTECIPAZIONE IN CGM FINANCE | C18: C | D18: =SUMIFS(DB_Complessivo!E:E,DB_Complessivo!B:B,INDICE!$B$2,DB_Complessivo!C:C,$A18,DB_Complessivo!A:A,"ACT") -> 2500 | F18: A | G18: Deposito CGM | H18: =SUMIFS($D$17:$D$43,$C$17:$C$43,$F18)/1000 -> 1898.8734
A19: 00031304 | B19: PARTECIPAZIONE IN COOPERFIDI ITALIA | C19: C | D19: =SUMIFS(DB_Complessivo!E:E,DB_Complessivo!B:B,INDICE!$B$2,DB_Complessivo!C:C,$A19,DB_Complessivo!A:A,"ACT") -> 250 | F19: B | G19: Polizze | H19: =SUMIFS($D$17:$D$43,$C$17:$C$43,$F19)/1000 -> 1055.0231
A20: 00032300 | B20: CREDITI VERSO ALTRI - POLIZZA ASSIC. INTESA | C20: B | D20: =SUMIFS(DB_Complessivo!E:E,DB_Complessivo!B:B,INDICE!$B$2,DB_Complessivo!C:C,$A20,DB_Complessivo!A:A,"ACT") -> 997500 | F20: C | G20: Altre Imm. Finanz. | H20: =SUMIFS($D$17:$D$43,$C$17:$C$43,$F20)/1000 -> 63.78852
A21: 00032301 | B21: CREDITI VERSO ALTRI - INT.POLIZZA ASS. INTESA | C21: B | D21: =SUMIFS(DB_Complessivo!E:E,DB_Complessivo!B:B,INDICE!$B$2,DB_Complessivo!C:C,$A21,DB_Complessivo!A:A,"ACT") -> 57523.07
A22: 00035000 | B22: STRUMENTI FINANZIARI DERIVATI ATTIVI | C22: C | D22: =SUMIFS(DB_Complessivo!E:E,DB_Complessivo!B:B,INDICE!$B$2,DB_Complessivo!C:C,$A22,DB_Complessivo!A:A,"ACT") -> 60698.52
A23: 02011001 | B23: CASSA | C23: D | D23: =SUMIFS(DB_Complessivo!E:E,DB_Complessivo!B:B,INDICE!$B$2,DB_Complessivo!C:C,$A23,DB_Complessivo!A:A,"ACT") -> 7314.83
A24: 02011002 | B24: CASSA CORRISPETTIVI | C24: D | D24: =SUMIFS(DB_Complessivo!E:E,DB_Complessivo!B:B,INDICE!$B$2,DB_Complessivo!C:C,$A24,DB_Complessivo!A:A,"ACT") -> 24179.808
A25: 02011003 | B25: CASSA NEGOZI | C25: D | D25: =SUMIFS(DB_Complessivo!E:E,DB_Complessivo!B:B,INDICE!$B$2,DB_Complessivo!C:C,$A25,DB_Complessivo!A:A,"ACT") -> 2408.05
A26: 02011004 | B26: CARTA PREPAGATA 5088 MAESTRELLO | C26: D | D26: =SUMIFS(DB_Complessivo!E:E,DB_Complessivo!B:B,INDICE!$B$2,DB_Complessivo!C:C,$A26,DB_Complessivo!A:A,"ACT") -> 1951.57
A27: 02011005 | B27: CARTA PREPAGATA 5062 CROIN | C27: D | D27: =SUMIFS(DB_Complessivo!E:E,DB_Complessivo!B:B,INDICE!$B$2,DB_Complessivo!C:C,$A27,DB_Complessivo!A:A,"ACT") -> 0
A28: 02020001 | B28: UNICREDIT C/C | C28: D | D28: =SUMIFS(DB_Complessivo!E:E,DB_Complessivo!B:B,INDICE!$B$2,DB_Complessivo!C:C,$A28,DB_Complessivo!A:A,"ACT") -> 334360.54
A29: 02020002 | B29: BANCA POP. SONDRIO C/C | C29: D | D29: =SUMIFS(DB_Complessivo!E:E,DB_Complessivo!B:B,INDICE!$B$2,DB_Complessivo!C:C,$A29,DB_Complessivo!A:A,"ACT") -> 158.54
A30: 02020005 | B30: CREVAL C/C | C30: D | D30: =SUMIFS(DB_Complessivo!E:E,DB_Complessivo!B:B,INDICE!$B$2,DB_Complessivo!C:C,$A30,DB_Complessivo!A:A,"ACT") -> 0
A31: 02020006 | B31: BPM C/C | C31: D | D31: =SUMIFS(DB_Complessivo!E:E,DB_Complessivo!B:B,INDICE!$B$2,DB_Complessivo!C:C,$A31,DB_Complessivo!A:A,"ACT") -> 35631.34
A32: 02020007 | B32: BANCA POP. SONDRIO YEAH C/C | C32: D | D32: =SUMIFS(DB_Complessivo!E:E,DB_Complessivo!B:B,INDICE!$B$2,DB_Complessivo!C:C,$A32,DB_Complessivo!A:A,"ACT") -> 225538.55
... A43: 02020031 | B43: DEPOSITO 2115 CGM FINANCE | C43: A | D43: =SUMIFS(DB_Complessivo!E:E,DB_Complessivo!B:B,INDICE!$B$2,DB_Complessivo!C:C,$A43,DB_Complessivo!A:A,"ACT") -> 898810
A45: Conto | B45: Descr. Conto | C45: Saldo
A46: 05011206 | B46: UBI Ponte | C46: =-SUMIFS(DB_Complessivo!E:E,DB_Complessivo!B:B,INDICE!$B$2,DB_Complessivo!C:C,$A46,DB_Complessivo!A:A,"ACT")/1000 -> 135.17967 | G46: Componenti Positive PFN | H46: =SUM(H17:H20) -> 4120.68
A47: 05011210 | B47: Credit Agricole | C47: =-SUMIFS(DB_Complessivo!E:E,DB_Complessivo!B:B,INDICE!$B$2,DB_Complessivo!C:C,$A47,DB_Complessivo!A:A,"ACT")/1000 -> 201.99893 | G47: Componenti Negative PFN | H47: =SUM(C46:C52) -> 2062.2307
A48: 05011212 | B48: UBI B/76180/1 | C48: =-SUMIFS(DB_Complessivo!E:E,DB_Complessivo!B:B,INDICE!$B$2,DB_Complessivo!C:C,$A48,DB_Complessivo!A:A,"ACT")/1000 -> 158.61724
A49: 05011213 | B49: BPM 04878755 | C49: =-SUMIFS(DB_Complessivo!E:E,DB_Complessivo!B:B,INDICE!$B$2,DB_Complessivo!C:C,$A49,DB_Complessivo!A:A,"ACT")/1000 -> 29.2961 | H49: =SUM(M16:M53) -> 0
A50: 05011216 | B50: UBI 76180/00 | C50: =-SUMIFS(DB_Complessivo!E:E,DB_Complessivo!B:B,INDICE!$B$2,DB_Complessivo!C:C,$A50,DB_Complessivo!A:A,"ACT")/1000 -> 101.70099 | H50: =+(H46-H47)*1000 -> 2058449.3
A51: 05011217 | B51: UNICREDIT 8931002 | C51: =-SUMIFS(DB_Complessivo!E:E,DB_Complessivo!B:B,INDICE!$B$2,DB_Complessivo!C:C,$A51,DB_Complessivo!A:A,"ACT")/1000 -> 1419.6158 | H51: =+H49-H50 -> -2058449.3
A52: 05011304 | B52: SIMEST 51339/EC/FP | C52: =-SUMIFS(DB_Complessivo!E:E,DB_Complessivo!B:B,INDICE!$B$2,DB_Complessivo!C:C,$A52,DB_Complessivo!A:A,"ACT")/1000 -> 15.822
A56: SEZIONE 2
B59: ="Act 0"&MONTH(INDICE!$B$2)&"."&YEAR(INDICE!$B$2)-1 -> Act 06.2024 | C59: ="Bdg 0"&MONTH(INDICE!$B$2)&"."&YEAR(INDICE!$B$2) -> Bdg 06.2025 | D59: ="Act 0"&MONTH(INDICE!$B$2)&"."&YEAR(INDICE!$B$2) -> Act 06.2025
A60: Ricavi | B60: =CE_Sintetico!D8 -> 3718.5335 | C60: =CE_Sintetico!E8 -> 3543.5453 | D60: =CE_Sintetico!F8 -> 3842.6868
A61: Ebitda (%) | B61: =CE_Sintetico!D19 -> 0.25744456 | C61: =CE_Sintetico!E19 -> 0.0086802601 | D61: =CE_Sintetico!F19 -> 0.024391059
B63: Act 12.2020 | C63: Act 12.2021 | D63: Act 12.2022 | E63: Act 12.2023 | F63: Act 12.2024 | G63: Fct 12.2025
A64: Ricavi | B64: =CE_Sintetico!J8 -> 13187.454 | C64: =CE_Sintetico!K8 -> 6668.3968 | D64: =CE_Sintetico!L8 -> 5925.2624 | E64: =CE_Sintetico!M8 -> 6006.0651 | F64: =CE_Sintetico!N8 -> 7209.174 | G64: =CE_Esteso!K7 -> 7625.0438
A65: Ebitda (%) | B65: =CE_Sintetico!J19 -> 0.1929494 | C65: =CE_Sintetico!K19 -> 0.13539061 | D65: =CE_Sintetico!L19 -> -0.022778542 | E65: =CE_Sintetico!M19 -> -0.26941934 | F65: =CE_Sintetico!N19 -> 0.12197366 | G65: =(CE_Esteso!K27-SUM(CE_Esteso!K18,CE_Esteso!K25:K26))/CE_Esteso!K3 -> 0.082290335
A69: Breakdown Personale | B69: ="Act 0"&MONTH(INDICE!$B$2)&"."&YEAR(INDICE!$B$2) -> Act 06.2025
A70: Manodopera diretta di produzione | B70: =-CE_Esteso!G11 -> 780.02684
A71: Costi del personale diretto improduttivo | B71: =-CE_Esteso!G15 -> 334.29722
A72: Costi del Personale indiretto di fabbrica | B72: =-CE_Esteso!G16 -> 406.57358
A73: Costi del personale di struttura | B73: =-CE_Esteso!G21 -> 630.26133
A76: Ebit Waterfall | B76: ="Act 0"&MONTH(INDICE!$B$2)&"."&YEAR(INDICE!$B$2) -> Act 06.2025
A77: Ricavi | B77: =SUM(CE_Esteso!G3:G6) -> 3842.6868
A78: Costi Industriali Diretti | B78: =SUM(CE_Esteso!G8:G11) -> -1664.6826
A79: Costi Industriali Indiretti | B79: =SUM(CE_Esteso!G14:G18) -> -891.39369
A80: Costi di Struttura | B80: =SUM(CE_Esteso!G21:G26) -> -1260.0957
A81: Risultato Operativo | B81: =SUM(B77:B80) -> 26.51475
A84: SEZIONE 3
A87: CCN Caratteristico | B87: Act 12.2023 | C87: ="Act 0"&MONTH(INDICE!$B$2)&"."&YEAR(INDICE!$B$2) -> Act 06.2025
A88: Crediti vs Clienti | B88: =SP_CIN!D11 -> 1965.6162 | C88: =SP_CIN!E11 -> 1353.2129
A89: Rimanenze | B89: =SP_CIN!D10 -> 573.3745 | C89: =SP_CIN!E10 -> 491.05785
A90: Debiti vs Fornitori | B90: =-SP_CIN!D12 -> 786.79147 | C90: =-SP_CIN!E12 -> 827.84899
B93: Breakdown Rimanenze | C93: ="Act 0"&MONTH(INDICE!$B$2)&"."&YEAR(INDICE!$B$2) -> Act 06.2025
A94: 00041000 | B94: Materie Prime, Sussidiarie e Consumo | C94: =SUMIFS(DB_Complessivo!E:E,DB_Complessivo!A:A,"ACT",DB_Complessivo!C:C,A94,DB_Complessivo!B:B,INDICE!$B$2)/1000 -> 398.48487
A95: 04021501 | B95: Fondo Svalutazione Magazzino MP | C95: =SUMIFS(DB_Complessivo!E:E,DB_Complessivo!A:A,"ACT",DB_Complessivo!C:C,A95,DB_Complessivo!B:B,INDICE!$B$2)/1000 -> -51.95858
A96: 00041300 | B96: Prodotti Finiti e Merci | C96: =SUMIFS(DB_Complessivo!E:E,DB_Complessivo!A:A,"ACT",DB_Complessivo!C:C,A96,DB_Complessivo!B:B,INDICE!$B$2)/1000 -> 244.53156
A97: 04021500 | B97: Fondo Svalutazione Magazzino PF | C97: =SUMIFS(DB_Complessivo!E:E,DB_Complessivo!A:A,"ACT",DB_Complessivo!C:C,A97,DB_Complessivo!B:B,INDICE!$B$2)/1000 -> -100
A100: Breakdown PFN | B100: Act 12.2023 | C100: ="Act 0"&MONTH(INDICE!$B$2)&"."&YEAR(INDICE!$B$2) -> Act 06.2025
A101: PFN a BT | B101: =SP_CIN!H6 -> -2263.2018 | C101: =SP_CIN!I6 -> -3001.8684
A102: PFN a MLT | B102: =SP_CIN!H10 -> 1204.9326 | C102: =SP_CIN!I10 -> 943.41911
A109: SEZIONE 4
A111: Cash Flow Waterfall | B111: ="Act 0"&MONTH(INDICE!$B$2)&"."&YEAR(INDICE!$B$2) -> Act 06.2025
A112: Autofinanziamento Operativo Netto | B112: =INDEX(RF_YtD!10:10,MATCH(INDICE!$B$2,RF_YtD!$1:$1,0)) -> 230.74304
A113: Variazione CCN | B113: =INDEX(RF_YtD!25:25,MATCH(INDICE!$B$2,RF_YtD!$1:$1,0))-B112 -> 418.69244
A114: Flusso Investimenti | B114: =INDEX(RF_YtD!30:30,MATCH(INDICE!$B$2,RF_YtD!$1:$1,0))-SUM(B112:B113) -> -8.1353776
A115: Rimborso Finanziamenti MLT | B115: =INDEX(RF_YtD!33:33,MATCH(INDICE!$B$2,RF_YtD!$1:$1,0))-SUM(B112:B114) -> -271.2532
A116: Aumenti/Decrementi Patrim. Netto | B116: =INDEX(RF_YtD!36:36,MATCH(INDICE!$B$2,RF_YtD!$1:$1,0))-SUM(B112:B115) -> -103.51785
A117: Accenzione Finanziamenti MLT | B117: =INDEX(RF_YtD!38:38,MATCH(INDICE!$B$2,RF_YtD!$1:$1,0))-SUM(B112:B116) -> 0
A118: Cash Flow Totale | B118: =SUM(B112:B117) -> 266.52905
A122: GRAFICO CLIENTI
A125: Cliente | B125: Fatturato | C125: Inc. (%) | D125: Distribuzione
A126: Calzedonia Spa | B126: 1779.4349 | C126: =B126/SUM($B$126:$B$199) -> 0.57918668 | D126: =C126 -> 0.57918668 | F126: Calzedonia Spa | G126: =+B126 -> 1779.4349
A127: Guess Europe Sagl | B127: 162.83175 | C127: =B127/SUM($B$126:$B$199) -> 0.052999962 | D127: =C127+D126 -> 0.63218664 | F127: Guess Europe Sagl | G127: =+B127 -> 162.83175
A128: Ikea Italia Retail Srl | B128: 114.32895 | C128: =B128/SUM($B$126:$B$199) -> 0.037212828 | D128: =C128+D127 -> 0.66939947 | F128: Ikea Italia Retail Srl | G128: =+B128 -> 114.32895
A129: A.I.A. Spa | B129: 112.409 | C129: =B129/SUM($B$126:$B$199) -> 0.036587906 | D129: =C129+D128 -> 0.70598738 | F129: A.I.A. Spa | G129: =+B129 -> 112.409
A130: OVS Spa | B130: 103.2708 | C130: =B130/SUM($B$126:$B$199) -> 0.033613521 | D130: =C130+D129 -> 0.7396009 | F130: OVS Spa | G130: =+B130 -> 103.2708
A131: DOLCE & GABBANA SRL | B131: 88.49596 | C131: =B131/SUM($B$126:$B$199) -> 0.028804471 | D131: =C131+D130 -> 0.76840537 | F131: Altri | G131: =ROUND(SUM(B131:B199),2) -> 800.02
A132: KERING ITALIA S.P.A. | B132: 69.2413 | C132: =B132/SUM($B$126:$B$199) -> 0.022537289 | D132: =C132+D131 -> 0.79094266
A133: Luxury Trains Servizi Srl | B133: 58.5439 | C133: =B133/SUM($B$126:$B$199) -> 0.019055402 | D133: =C133+D132 -> 0.80999806
A134: GOLDEN POINT S.P.A. | B134: 54.81775 | C134: =B134/SUM($B$126:$B$199) -> 0.017842581 | D134: =C134+D133 -> 0.82784064
A135: ATELIER EME' SRL | B135: 46.877 | C135: =B135/SUM($B$126:$B$199) -> 0.015257953 | D135: =C135+D134 -> 0.8430986
A136: MONDE SRL | B136: 35.108 | C136: =B136/SUM($B$126:$B$199) -> 0.011427272 | D136: =C136+D135 -> 0.85452587
A137: FEDRIGONI SpA | B137: 35.07656 | C137: =B137/SUM($B$126:$B$199) -> 0.011417038 | D137: =C137+D136 -> 0.86594291
A138: DATACOL S.R.L. | B138: 34.7897 | C138: =B138/SUM($B$126:$B$199) -> 0.011323669 | D138: =C138+D137 -> 0.87726657
A139: Davines S.p.A. | B139: 31.9355 | C139: =B139/SUM($B$126:$B$199) -> 0.010394658 | D139: =C139+D138 -> 0.88766123
A140: GENERALI ITALIA SPA | B140: 30.7916 | C140: =B140/SUM($B$126:$B$199) -> 0.010022331 | D140: =C140+D139 -> 0.89768356
A141: SONEPAR ITALIA SPA | B141: 27.8922 | C141: =B141/SUM($B$126:$B$199) -> 0.0090786074 | D141: =C141+D140 -> 0.90676217
A142: WE EXHIBIT SRL | B142: 25.4408 | C142: =B142/SUM($B$126:$B$199) -> 0.0082807034 | D142: =C142+D141 -> 0.91504287
A143: PETTENON COSMETICS S.p. A. Società soggetta a direzione e coordinamento di AGF88 Holding S.r.l | B143: 23.2168 | C143: =B143/SUM($B$126:$B$199) -> 0.0075568156 | D143: =C143+D142 -> 0.92259969
... A199: CHIARINI LORENZA | B199: 0.0245 | C199: =B199/SUM($B$126:$B$199) -> 7.9744832e-06 | D199: =C199+D198 -> 1

Sheet CE_Sintetico
C2: Conto Economico "Sintetico" | D2: PY | E2: REV_BDG | F2: ACT
C3: EUR/000 | D3: =EOMONTH(INDICE!B2,-12) -> 45473 | E3: =EOMONTH(INDICE!B2,0) -> 45838 | F3: =EOMONTH(INDICE!B2,0) -> 45838 | J3: 44196 | K3: 44561 | L3: 44926 | M3: 45291 | N3: 45657
A4: RIC | C4: Ricavi Netti di Vendita | D4: =-SUMIFS(DB_Complessivo!$E:$E,DB_Complessivo!$A:$A,"ACT",DB_Complessivo!$J:$J,$A4,DB_Complessivo!$B:$B,D$3)/1000 -> 3007.6994 | E4: =-SUMIFS(DB_Complessivo!$E:$E,DB_Complessivo!$A:$A,$E$2,DB_Complessivo!$J:$J,$A4,DB_Complessivo!$B:$B,E$3)/1000 -> 3057.6796 | F4: =-SUMIFS(DB_Complessivo!$E:$E,DB_Complessivo!$A:$A,"ACT",DB_Complessivo!$J:$J,$A4,DB_Complessivo!$B:$B,F$3)/1000 -> 3134.7637 | J4: =-SUMIFS(DB_Complessivo!$E:$E,DB_Complessivo!$A:$A,"ACT",DB_Complessivo!$J:$J,$A4,DB_Complessivo!$B:$B,J$3)/1000 -> 7370.1443 | K4: =-SUMIFS(DB_Complessivo!$E:$E,DB_Complessivo!$A:$A,"ACT",DB_Complessivo!$J:$J,$A4,DB_Complessivo!$B:$B,K$3)/1000 -> 3089.6107 | L4: =-SUMIFS(DB_Complessivo!$E:$E,DB_Complessivo!$A:$A,"ACT",DB_Complessivo!$J:$J,$A4,DB_Complessivo!$B:$B,L$3)/1000 -> 4290.7315 | M4: =-SUMIFS(DB_Complessivo!$E:$E,DB_Complessivo!$A:$A,"ACT",DB_Complessivo!$J:$J,$A4,DB_Complessivo!$B:$B,M$3)/1000 -> 3828.3514 | N4: =-SUMIFS(DB_Complessivo!$E:$E,DB_Complessivo!$A:$A,"ACT",DB_Complessivo!$J:$J,$A4,DB_Complessivo!$B:$B,N$3)/1000 -> 5644.8126
A5: CORR | C5: Corrispettivi | D5: =-SUMIFS(DB_Complessivo!$E:$E,DB_Complessivo!$A:$A,"ACT",DB_Complessivo!$J:$J,$A5,DB_Complessivo!$B:$B,D$3)/1000 -> 583.8182 | E5: =-SUMIFS(DB_Complessivo!$E:$E,DB_Complessivo!$A:$A,$E$2,DB_Complessivo!$J:$J,$A5,DB_Complessivo!$B:$B,E$3)/1000 -> 145.36444 | F5: =-SUMIFS(DB_Complessivo!$E:$E,DB_Complessivo!$A:$A,"ACT",DB_Complessivo!$J:$J,$A5,DB_Complessivo!$B:$B,F$3)/1000 -> 145.43466 | J5: =-SUMIFS(DB_Complessivo!$E:$E,DB_Complessivo!$A:$A,"ACT",DB_Complessivo!$J:$J,$A5,DB_Complessivo!$B:$B,J$3)/1000 -> 1321.2355 | K5: =-SUMIFS(DB_Complessivo!$E:$E,DB_Complessivo!$A:$A,"ACT",DB_Complessivo!$J:$J,$A5,DB_Complessivo!$B:$B,K$3)/1000 -> 1480.6083 | L5: =-SUMIFS(DB_Complessivo!$E:$E,DB_Complessivo!$A:$A,"ACT",DB_Complessivo!$J:$J,$A5,DB_Complessivo!$B:$B,L$3)/1000 -> 1720.3795 | M5: =-SUMIFS(DB_Complessivo!$E:$E,DB_Complessivo!$A:$A,"ACT",DB_Complessivo!$J:$J,$A5,DB_Complessivo!$B:$B,M$3)/1000 -> 1701.8199 | N5: =-SUMIFS(DB_Complessivo!$E:$E,DB_Complessivo!$A:$A,"ACT",DB_Complessivo!$J:$J,$A5,DB_Complessivo!$B:$B,N$3)/1000 -> 825.32082
A6: VARPF | C6: Variazione magazzino PF | D6: =-SUMIFS(DB_Complessivo!$E:$E,DB_Complessivo!$A:$A,"ACT",DB_Complessivo!$J:$J,$A6,DB_Complessivo!$B:$B,D$3)/1000 -> -378.34423 | E6: =-SUMIFS(DB_Complessivo!$E:$E,DB_Complessivo!$A:$A,$E$2,DB_Complessivo!$J:$J,$A6,DB_Complessivo!$B:$B,E$3)/1000 -> 50.48681 | F6: =-SUMIFS(DB_Complessivo!$E:$E,DB_Complessivo!$A:$A,"ACT",DB_Complessivo!$J:$J,$A6,DB_Complessivo!$B:$B,F$3)/1000 -> -30.72334 | J6: =-SUMIFS(DB_Complessivo!$E:$E,DB_Complessivo!$A:$A,"ACT",DB_Complessivo!$J:$J,$A6,DB_Complessivo!$B:$B,J$3)/1000 -> 2698.6681 | K6: =-SUMIFS(DB_Complessivo!$E:$E,DB_Complessivo!$A:$A,"ACT",DB_Complessivo!$J:$J,$A6,DB_Complessivo!$B:$B,K$3)/1000 -> -2428.6984 | L6: =-SUMIFS(DB_Complessivo!$E:$E,DB_Complessivo!$A:$A,"ACT",DB_Complessivo!$J:$J,$A6,DB_Complessivo!$B:$B,L$3)/1000 -> -675.3404 | M6: =-SUMIFS(DB_Complessivo!$E:$E,DB_Complessivo!$A:$A,"ACT",DB_Complessivo!$J:$J,$A6,DB_Complessivo!$B:$B,M$3)/1000 -> -56.15042 | N6: =-SUMIFS(DB_Complessivo!$E:$E,DB_Complessivo!$A:$A,"ACT",DB_Complessivo!$J:$J,$A6,DB_Complessivo!$B:$B,N$3)/1000 -> -113.78036
A7: ALTRI | C7: Altri Ricavi | D7: =-SUMIFS(DB_Complessivo!$E:$E,DB_Complessivo!$A:$A,"ACT",DB_Complessivo!$J:$J,$A7,DB_Complessivo!$B:$B,D$3)/1000 -> 505.36009 | E7: =-SUMIFS(DB_Complessivo!$E:$E,DB_Complessivo!$A:$A,$E$2,DB_Complessivo!$J:$J,$A7,DB_Complessivo!$B:$B,E$3)/1000 -> 290.01446 | F7: =-SUMIFS(DB_Complessivo!$E:$E,DB_Complessivo!$A:$A,"ACT",DB_Complessivo!$J:$J,$A7,DB_Complessivo!$B:$B,F$3)/1000 -> 593.21178 | J7: =-SUMIFS(DB_Complessivo!$E:$E,DB_Complessivo!$A:$A,"ACT",DB_Complessivo!$J:$J,$A7,DB_Complessivo!$B:$B,J$3)/1000 -> 1797.4066 | K7: =-SUMIFS(DB_Complessivo!$E:$E,DB_Complessivo!$A:$A,"ACT",DB_Complessivo!$J:$J,$A7,DB_Complessivo!$B:$B,K$3)/1000 -> 4526.8762 | L7: =-SUMIFS(DB_Complessivo!$E:$E,DB_Complessivo!$A:$A,"ACT",DB_Complessivo!$J:$J,$A7,DB_Complessivo!$B:$B,L$3)/1000 -> 589.49188 | M7: =-SUMIFS(DB_Complessivo!$E:$E,DB_Complessivo!$A:$A,"ACT",DB_Complessivo!$J:$J,$A7,DB_Complessivo!$B:$B,M$3)/1000 -> 532.04425 | N7: =-SUMIFS(DB_Complessivo!$E:$E,DB_Complessivo!$A:$A,"ACT",DB_Complessivo!$J:$J,$A7,DB_Complessivo!$B:$B,N$3)/1000 -> 852.82091
C8: Ricavi Tot | D8: =SUM(D4:D7) -> 3718.5335 | E8: =SUM(E4:E7) -> 3543.5453 | F8: =SUM(F4:F7) -> 3842.6868 | J8: =SUM(J4:J7) -> 13187.454 | K8: =SUM(K4:K7) -> 6668.3968 | L8: =SUM(L4:L7) -> 5925.2624 | M8: =SUM(M4:M7) -> 6006.0651 | N8: =SUM(N4:N7) -> 7209.174
A9: ACQ | C9: Consumi | D9: =-SUMIFS(DB_Complessivo!$E:$E,DB_Complessivo!$A:$A,"ACT",DB_Complessivo!$J:$J,$A9,DB_Complessivo!$B:$B,D$3)/1000 -> -8.29416 | E9: =-SUMIFS(DB_Complessivo!$E:$E,DB_Complessivo!$A:$A,$E$2,DB_Complessivo!$J:$J,$A9,DB_Complessivo!$B:$B,E$3)/1000 -> -304.70786 | F9: =-SUMIFS(DB_Complessivo!$E:$E,DB_Complessivo!$A:$A,"ACT",DB_Complessivo!$J:$J,$A9,DB_Complessivo!$B:$B,F$3)/1000 -> -365.43326 | J9: =-SUMIFS(DB_Complessivo!$E:$E,DB_Complessivo!$A:$A,"ACT",DB_Complessivo!$J:$J,$A9,DB_Complessivo!$B:$B,J$3)/1000 -> -1825.4343 | K9: =-SUMIFS(DB_Complessivo!$E:$E,DB_Complessivo!$A:$A,"ACT",DB_Complessivo!$J:$J,$A9,DB_Complessivo!$B:$B,K$3)/1000 -> -1182.6431 | L9: =-SUMIFS(DB_Complessivo!$E:$E,DB_Complessivo!$A:$A,"ACT",DB_Complessivo!$J:$J,$A9,DB_Complessivo!$B:$B,L$3)/1000 -> -340.13104 | M9: =-SUMIFS(DB_Complessivo!$E:$E,DB_Complessivo!$A:$A,"ACT",DB_Complessivo!$J:$J,$A9,DB_Complessivo!$B:$B,M$3)/1000 -> -1092.4301 | N9: =-SUMIFS(DB_Complessivo!$E:$E,DB_Complessivo!$A:$A,"ACT",DB_Complessivo!$J:$J,$A9,DB_Complessivo!$B:$B,N$3)/1000 -> -527.36397
A10: LAV | C10: Lavorazioni esterne | D10: =-SUMIFS(DB_Complessivo!$E:$E,DB_Complessivo!$A:$A,"ACT",DB_Complessivo!$J:$J,$A10,DB_Complessivo!$B:$B,D$3)/1000 -> -354.46345 | E10: =-SUMIFS(DB_Complessivo!$E:$E,DB_Complessivo!$A:$A,$E$2,DB_Complessivo!$J:$J,$A10,DB_Complessivo!$B:$B,E$3)/1000 -> -566.4114 | F10: =-SUMIFS(DB_Complessivo!$E:$E,DB_Complessivo!$A:$A,"ACT",DB_Complessivo!$J:$J,$A10,DB_Complessivo!$B:$B,F$3)/1000 -> -519.22252 | J10: =-SUMIFS(DB_Complessivo!$E:$E,DB_Complessivo!$A:$A,"ACT",DB_Complessivo!$J:$J,$A10,DB_Complessivo!$B:$B,J$3)/1000 -> -4793.8641 | K10: =-SUMIFS(DB_Complessivo!$E:$E,DB_Complessivo!$A:$A,"ACT",DB_Complessivo!$J:$J,$A10,DB_Complessivo!$B:$B,K$3)/1000 -> -458.0877 | L10: =-SUMIFS(DB_Complessivo!$E:$E,DB_Complessivo!$A:$A,"ACT",DB_Complessivo!$J:$J,$A10,DB_Complessivo!$B:$B,L$3)/1000 -> -890.82406 | M10: =-SUMIFS(DB_Complessivo!$E:$E,DB_Complessivo!$A:$A,"ACT",DB_Complessivo!$J:$J,$A10,DB_Complessivo!$B:$B,M$3)/1000 -> -1345.237 | N10: =-SUMIFS(DB_Complessivo!$E:$E,DB_Complessivo!$A:$A,"ACT",DB_Complessivo!$J:$J,$A10,DB_Complessivo!$B:$B,N$3)/1000 -> -839.90733
A11: dir | C11: Costo del personale diretto | D11: =-SUMIFS(DB_Complessivo!$E:$E,DB_Complessivo!$A:$A,"ACT",DB_Complessivo!$J:$J,$A11,DB_Complessivo!$B:$B,D$3)/1000 -> -643.8996 | E11: =-SUMIFS(DB_Complessivo!$E:$E,DB_Complessivo!$A:$A,$E$2,DB_Complessivo!$J:$J,$A11,DB_Complessivo!$B:$B,E$3)/1000*70% -> -556.82503 | F11: =-SUMIFS(DB_Complessivo!$E:$E,DB_Complessivo!$A:$A,"ACT",DB_Complessivo!$J:$J,$A11,DB_Complessivo!$B:$B,F$3)/1000 -> -780.02684 | J11: =-SUMIFS(DB_Complessivo!$E:$E,DB_Complessivo!$A:$A,"ACT",DB_Complessivo!$J:$J,$A11,DB_Complessivo!$B:$B,J$3)/1000 -> -1804.6526 | K11: =-SUMIFS(DB_Complessivo!$E:$E,DB_Complessivo!$A:$A,"ACT",DB_Complessivo!$J:$J,$A11,DB_Complessivo!$B:$B,K$3)/1000 -> -1917.6018 | L11: =-SUMIFS(DB_Complessivo!$E:$E,DB_Complessivo!$A:$A,"ACT",DB_Complessivo!$J:$J,$A11,DB_Complessivo!$B:$B,L$3)/1000 -> -874.64877 | M11: =-SUMIFS(DB_Complessivo!$E:$E,DB_Complessivo!$A:$A,"ACT",DB_Complessivo!$J:$J,$A11,DB_Complessivo!$B:$B,M$3)/1000 -> -1151.6756 | N11: =-SUMIFS(DB_Complessivo!$E:$E,DB_Complessivo!$A:$A,"ACT",DB_Complessivo!$J:$J,$A11,DB_Complessivo!$B:$B,N$3)/1000 -> -1268.5674
C12: Margine di Contribuzione | D12: =SUM(D8:D11) -> 2711.8762 | E12: =SUM(E8:E11) -> 2115.601 | F12: =SUM(F8:F11) -> 2178.0042 | J12: =SUM(J8:J11) -> 4763.5035 | K12: =SUM(K8:K11) -> 3110.0641 | L12: =SUM(L8:L11) -> 3819.6586 | M12: =SUM(M8:M11) -> 2416.7225 | N12: =SUM(N8:N11) -> 4573.3352
C13: % Margine di Contribuzione | D13: =D12/D$8 -> 0.7292865 | E13: =E12/E$8 -> 0.59702948 | F13: =F12/F$8 -> 0.56679201 | J13: =J12/J$8 -> 0.36121478 | K13: =K12/K$8 -> 0.46638858 | L13: =L12/L$8 -> 0.64463956 | M13: =M12/M$8 -> 0.40238033 | N13: =N12/N$8 -> 0.63437715
A14: PRD | C14: Altri costi di produzione | D14: =-SUMIFS(DB_Complessivo!$E:$E,DB_Complessivo!$A:$A,"ACT",DB_Complessivo!$J:$J,$A14,DB_Complessivo!$B:$B,D$3)/1000 -> -81.11524 | E14: =-SUMIFS(DB_Complessivo!$E:$E,DB_Complessivo!$A:$A,$E$2,DB_Complessivo!$J:$J,$A14,DB_Complessivo!$B:$B,E$3)/1000 -> -103.07902 | F14: =-SUMIFS(DB_Complessivo!$E:$E,DB_Complessivo!$A:$A,"ACT",DB_Complessivo!$J:$J,$A14,DB_Complessivo!$B:$B,F$3)/1000 -> -106.59596 | J14: =-SUMIFS(DB_Complessivo!$E:$E,DB_Complessivo!$A:$A,"ACT",DB_Complessivo!$J:$J,$A14,DB_Complessivo!$B:$B,J$3)/1000 -> -228.3328 | K14: =-SUMIFS(DB_Complessivo!$E:$E,DB_Complessivo!$A:$A,"ACT",DB_Complessivo!$J:$J,$A14,DB_Complessivo!$B:$B,K$3)/1000 -> -192.74006 | L14: =-SUMIFS(DB_Complessivo!$E:$E,DB_Complessivo!$A:$A,"ACT",DB_Complessivo!$J:$J,$A14,DB_Complessivo!$B:$B,L$3)/1000 -> -255.39126 | M14: =-SUMIFS(DB_Complessivo!$E:$E,DB_Complessivo!$A:$A,"ACT",DB_Complessivo!$J:$J,$A14,DB_Complessivo!$B:$B,M$3)/1000 -> -292.18367 | N14: =-SUMIFS(DB_Complessivo!$E:$E,DB_Complessivo!$A:$A,"ACT",DB_Complessivo!$J:$J,$A14,DB_Complessivo!$B:$B,N$3)/1000 -> -180.57237
A15: PAY | C15: Costo del personale indiretto | D15: =-SUMIFS(DB_Complessivo!$E:$E,DB_Complessivo!$A:$A,"ACT",DB_Complessivo!$J:$J,$A15,DB_Complessivo!$B:$B,D$3)/1000 -> -1163.1673 | E15: =-SUMIFS(DB_Complessivo!$E:$E,DB_Complessivo!$A:$A,$E$2,DB_Complessivo!$J:$J,$A15,DB_Complessivo!$B:$B,E$3)/1000-SUMIFS(DB_Complessivo!$E:$E,DB_Complessivo!$A:$A,$E$2,DB_Complessivo!$J:$J,$A11,DB_Complessivo!$B:$B,E$3)/1000*30% -> -1487.85 | F15: =-SUMIFS(DB_Complessivo!$E:$E,DB_Complessivo!$A:$A,"ACT",DB_Complessivo!$J:$J,$A15,DB_Complessivo!$B:$B,F$3)/1000 -> -1371.1321 | J15: =-SUMIFS(DB_Complessivo!$E:$E,DB_Complessivo!$A:$A,"ACT",DB_Complessivo!$J:$J,$A15,DB_Complessivo!$B:$B,J$3)/1000 -> -773.42256 | K15: =-SUMIFS(DB_Complessivo!$E:$E,DB_Complessivo!$A:$A,"ACT",DB_Complessivo!$J:$J,$A15,DB_Complessivo!$B:$B,K$3)/1000 -> -821.82934 | L15: =-SUMIFS(DB_Complessivo!$E:$E,DB_Complessivo!$A:$A,"ACT",DB_Complessivo!$J:$J,$A15,DB_Complessivo!$B:$B,L$3)/1000 -> -2271.9612 | M15: =-SUMIFS(DB_Complessivo!$E:$E,DB_Complessivo!$A:$A,"ACT",DB_Complessivo!$J:$J,$A15,DB_Complessivo!$B:$B,M$3)/1000 -> -2336.1136 | N15: =-SUMIFS(DB_Complessivo!$E:$E,DB_Complessivo!$A:$A,"ACT",DB_Complessivo!$J:$J,$A15,DB_Complessivo!$B:$B,N$3)/1000 -> -2291.1535
A16: AFF | C16: Affitti | D16: =-SUMIFS(DB_Complessivo!$E:$E,DB_Complessivo!$A:$A,"ACT",DB_Complessivo!$J:$J,$A16,DB_Complessivo!$B:$B,D$3)/1000 -> -85.26118 | E16: =-SUMIFS(DB_Complessivo!$E:$E,DB_Complessivo!$A:$A,$E$2,DB_Complessivo!$J:$J,$A16,DB_Complessivo!$B:$B,E$3)/1000 -> -38.6754 | F16: =-SUMIFS(DB_Complessivo!$E:$E,DB_Complessivo!$A:$A,"ACT",DB_Complessivo!$J:$J,$A16,DB_Complessivo!$B:$B,F$3)/1000 -> -46.5754 | J16: =-SUMIFS(DB_Complessivo!$E:$E,DB_Complessivo!$A:$A,"ACT",DB_Complessivo!$J:$J,$A16,DB_Complessivo!$B:$B,J$3)/1000 -> -168.45069 | K16: =-SUMIFS(DB_Complessivo!$E:$E,DB_Complessivo!$A:$A,"ACT",DB_Complessivo!$J:$J,$A16,DB_Complessivo!$B:$B,K$3)/1000 -> -186.66432 | L16: =-SUMIFS(DB_Complessivo!$E:$E,DB_Complessivo!$A:$A,"ACT",DB_Complessivo!$J:$J,$A16,DB_Complessivo!$B:$B,L$3)/1000 -> -205.82747 | M16: =-SUMIFS(DB_Complessivo!$E:$E,DB_Complessivo!$A:$A,"ACT",DB_Complessivo!$J:$J,$A16,DB_Complessivo!$B:$B,M$3)/1000 -> -249.02661 | N16: =-SUMIFS(DB_Complessivo!$E:$E,DB_Complessivo!$A:$A,"ACT",DB_Complessivo!$J:$J,$A16,DB_Complessivo!$B:$B,N$3)/1000 -> -125.09451
A17: COSTI | C17: Costi generali, commerciali ed amm. | D17: =-SUMIFS(DB_Complessivo!$E:$E,DB_Complessivo!$A:$A,"ACT",DB_Complessivo!$J:$J,$A17,DB_Complessivo!$B:$B,D$3)/1000 -> -425.01635 | E17: =-SUMIFS(DB_Complessivo!$E:$E,DB_Complessivo!$A:$A,$E$2,DB_Complessivo!$J:$J,$A17,DB_Complessivo!$B:$B,E$3)/1000 -> -455.23768 | F17: =-SUMIFS(DB_Complessivo!$E:$E,DB_Complessivo!$A:$A,"ACT",DB_Complessivo!$J:$J,$A17,DB_Complessivo!$B:$B,F$3)/1000 -> -559.97346 | J17: =-SUMIFS(DB_Complessivo!$E:$E,DB_Complessivo!$A:$A,"ACT",DB_Complessivo!$J:$J,$A17,DB_Complessivo!$B:$B,J$3)/1000 -> -1048.786 | K17: =-SUMIFS(DB_Complessivo!$E:$E,DB_Complessivo!$A:$A,"ACT",DB_Complessivo!$J:$J,$A17,DB_Complessivo!$B:$B,K$3)/1000 -> -1005.9921 | L17: =-SUMIFS(DB_Complessivo!$E:$E,DB_Complessivo!$A:$A,"ACT",DB_Complessivo!$J:$J,$A17,DB_Complessivo!$B:$B,L$3)/1000 -> -1221.4475 | M17: =-SUMIFS(DB_Complessivo!$E:$E,DB_Complessivo!$A:$A,"ACT",DB_Complessivo!$J:$J,$A17,DB_Complessivo!$B:$B,M$3)/1000 -> -1157.5486 | N17: =-SUMIFS(DB_Complessivo!$E:$E,DB_Complessivo!$A:$A,"ACT",DB_Complessivo!$J:$J,$A17,DB_Complessivo!$B:$B,N$3)/1000 -> -1097.1855
C18: EBITDA | D18: =SUM(D12,D14:D17) -> 957.31622 | E18: =SUM(E12,E14:E17) -> 30.758895 | F18: =SUM(F12,F14:F17) -> 93.7272 | J18: =SUM(J12,J14:J17) -> 2544.5114 | K18: =SUM(K12,K14:K17) -> 902.83833 | L18: =SUM(L12,L14:L17) -> -134.96884 | M18: =SUM(M12,M14:M17) -> -1618.1501 | N18: =SUM(N12,N14:N17) -> 879.32932
C19: % EBITDA | D19: =D18/D$8 -> 0.25744456 | E19: =E18/E$8 -> 0.0086802601 | F19: =F18/F$8 -> 0.024391059 | J19: =J18/J$8 -> 0.1929494 | K19: =K18/K$8 -> 0.13539061 | L19: =L18/L$8 -> -0.022778542 | M19: =M18/M$8 -> -0.26941934 | N19: =N18/N$8 -> 0.12197366
A20: AMM | C20: Ammortamenti | D20: =-SUMIFS(DB_Complessivo!$E:$E,DB_Complessivo!$A:$A,"ACT",DB_Complessivo!$J:$J,$A20,DB_Complessivo!$B:$B,D$3)/1000 -> -56.186048 | E20: =-SUMIFS(DB_Complessivo!$E:$E,DB_Complessivo!$A:$A,$E$2,DB_Complessivo!$J:$J,$A20,DB_Complessivo!$B:$B,E$3)/1000 -> -67.21254 | F20: =-SUMIFS(DB_Complessivo!$E:$E,DB_Complessivo!$A:$A,"ACT",DB_Complessivo!$J:$J,$A20,DB_Complessivo!$B:$B,F$3)/1000 -> -67.21245 | J20: =-SUMIFS(DB_Complessivo!$E:$E,DB_Complessivo!$A:$A,"ACT",DB_Complessivo!$J:$J,$A20,DB_Complessivo!$B:$B,J$3)/1000 -> -164.51532 | K20: =-SUMIFS(DB_Complessivo!$E:$E,DB_Complessivo!$A:$A,"ACT",DB_Complessivo!$J:$J,$A20,DB_Complessivo!$B:$B,K$3)/1000 -> -198.29228 | L20: =-SUMIFS(DB_Complessivo!$E:$E,DB_Complessivo!$A:$A,"ACT",DB_Complessivo!$J:$J,$A20,DB_Complessivo!$B:$B,L$3)/1000 -> -157.96159 | M20: =-SUMIFS(DB_Complessivo!$E:$E,DB_Complessivo!$A:$A,"ACT",DB_Complessivo!$J:$J,$A20,DB_Complessivo!$B:$B,M$3)/1000 -> -130.40508 | N20: =-SUMIFS(DB_Complessivo!$E:$E,DB_Complessivo!$A:$A,"ACT",DB_Complessivo!$J:$J,$A20,DB_Complessivo!$B:$B,N$3)/1000 -> -122.444
A21: ACC | C21: Accantonamenti | D21: =-SUMIFS(DB_Complessivo!$E:$E,DB_Complessivo!$A:$A,"ACT",DB_Complessivo!$J:$J,$A21,DB_Complessivo!$B:$B,D$3)/1000 -> 0 | E21: =-SUMIFS(DB_Complessivo!$E:$E,DB_Complessivo!$A:$A,$E$2,DB_Complessivo!$J:$J,$A21,DB_Complessivo!$B:$B,E$3)/1000 -> 0 | F21: =-SUMIFS(DB_Complessivo!$E:$E,DB_Complessivo!$A:$A,"ACT",DB_Complessivo!$J:$J,$A21,DB_Complessivo!$B:$B,F$3)/1000 -> 0 | J21: =-SUMIFS(DB_Complessivo!$E:$E,DB_Complessivo!$A:$A,"ACT",DB_Complessivo!$J:$J,$A21,DB_Complessivo!$B:$B,J$3)/1000 -> -2427 | K21: =-SUMIFS(DB_Complessivo!$E:$E,DB_Complessivo!$A:$A,"ACT",DB_Complessivo!$J:$J,$A21,DB_Complessivo!$B:$B,K$3)/1000 -> -808.99081 | L21: =-SUMIFS(DB_Complessivo!$E:$E,DB_Complessivo!$A:$A,"ACT",DB_Complessivo!$J:$J,$A21,DB_Complessivo!$B:$B,L$3)/1000 -> -2016.5399 | M21: =-SUMIFS(DB_Complessivo!$E:$E,DB_Complessivo!$A:$A,"ACT",DB_Complessivo!$J:$J,$A21,DB_Complessivo!$B:$B,M$3)/1000 -> 0 | N21: =-SUMIFS(DB_Complessivo!$E:$E,DB_Complessivo!$A:$A,"ACT",DB_Complessivo!$J:$J,$A21,DB_Complessivo!$B:$B,N$3)/1000 -> 0
C22: EBIT | D22: =SUM(D18,D20:D21) -> 901.13017 | E22: =SUM(E18,E20:E21) -> -36.453645 | F22: =SUM(F18,F20:F21) -> 26.51475 | J22: =SUM(J18,J20:J21) -> -47.00393 | K22: =SUM(K18,K20:K21) -> -104.44476 | L22: =SUM(L18,L20:L21) -> -2309.4704 | M22: =SUM(M18,M20:M21) -> -1748.5552 | N22: =SUM(N18,N20:N21) -> 756.88532
C23: % EBIT | D23: =D22/D$8 -> 0.24233483 | E23: =E22/E$8 -> -0.010287337 | F23: =F22/F$8 -> 0.006900055 | J23: =J22/J$8 -> -0.0035642914 | K23: =K22/K$8 -> -0.01566265 | L23: =L22/L$8 -> -0.38976676 | M23: =M22/M$8 -> -0.29113157 | N23: =N22/N$8 -> 0.10498919
A24: FIN | C24: Gestione Finanziaria | D24: =-SUMIFS(DB_Complessivo!$E:$E,DB_Complessivo!$A:$A,"ACT",DB_Complessivo!$J:$J,$A24,DB_Complessivo!$B:$B,D$3)/1000 -> -44.34164 | E24: =-SUMIFS(DB_Complessivo!$E:$E,DB_Complessivo!$A:$A,$E$2,DB_Complessivo!$J:$J,$A24,DB_Complessivo!$B:$B,E$3)/1000 -> 0 | F24: =-SUMIFS(DB_Complessivo!$E:$E,DB_Complessivo!$A:$A,"ACT",DB_Complessivo!$J:$J,$A24,DB_Complessivo!$B:$B,F$3)/1000 -> 11.67779 | J24: =-SUMIFS(DB_Complessivo!$E:$E,DB_Complessivo!$A:$A,"ACT",DB_Complessivo!$J:$J,$A24,DB_Complessivo!$B:$B,J$3)/1000 -> -18.59043 | K24: =-SUMIFS(DB_Complessivo!$E:$E,DB_Complessivo!$A:$A,"ACT",DB_Complessivo!$J:$J,$A24,DB_Complessivo!$B:$B,K$3)/1000 -> -24.9416 | L24: =-SUMIFS(DB_Complessivo!$E:$E,DB_Complessivo!$A:$A,"ACT",DB_Complessivo!$J:$J,$A24,DB_Complessivo!$B:$B,L$3)/1000 -> -14.27967 | M24: =-SUMIFS(DB_Complessivo!$E:$E,DB_Complessivo!$A:$A,"ACT",DB_Complessivo!$J:$J,$A24,DB_Complessivo!$B:$B,M$3)/1000 -> 69.02285 | N24: =-SUMIFS(DB_Complessivo!$E:$E,DB_Complessivo!$A:$A,"ACT",DB_Complessivo!$J:$J,$A24,DB_Complessivo!$B:$B,N$3)/1000 -> 44.33652
A25: EXT | C25: Gestione Straordinaria | D25: =-SUMIFS(DB_Complessivo!$E:$E,DB_Complessivo!$A:$A,"ACT",DB_Complessivo!$J:$J,$A25,DB_Complessivo!$B:$B,D$3)/1000 -> 33.568 | E25: =-SUMIFS(DB_Complessivo!$E:$E,DB_Complessivo!$A:$A,$E$2,DB_Complessivo!$J:$J,$A25,DB_Complessivo!$B:$B,E$3)/1000 -> -49.87874 | F25: =-SUMIFS(DB_Complessivo!$E:$E,DB_Complessivo!$A:$A,"ACT",DB_Complessivo!$J:$J,$A25,DB_Complessivo!$B:$B,F$3)/1000 -> 37.29463 | J25: =-SUMIFS(DB_Complessivo!$E:$E,DB_Complessivo!$A:$A,"ACT",DB_Complessivo!$J:$J,$A25,DB_Complessivo!$B:$B,J$3)/1000 -> 98.74265 | K25: =-SUMIFS(DB_Complessivo!$E:$E,DB_Complessivo!$A:$A,"ACT",DB_Complessivo!$J:$J,$A25,DB_Complessivo!$B:$B,K$3)/1000 -> 180.1279 | L25: =-SUMIFS(DB_Complessivo!$E:$E,DB_Complessivo!$A:$A,"ACT",DB_Complessivo!$J:$J,$A25,DB_Complessivo!$B:$B,L$3)/1000 -> 2393.0702 | M25: =-SUMIFS(DB_Complessivo!$E:$E,DB_Complessivo!$A:$A,"ACT",DB_Complessivo!$J:$J,$A25,DB_Complessivo!$B:$B,M$3)/1000 -> 1732.986 | N25: =-SUMIFS(DB_Complessivo!$E:$E,DB_Complessivo!$A:$A,"ACT",DB_Complessivo!$J:$J,$A25,DB_Complessivo!$B:$B,N$3)/1000 -> 139.317
C26: EBT | D26: =SUM(D22,D24:D25) -> 890.35653 | E26: =SUM(E22,E24:E25) -> -86.332385 | F26: =SUM(F22,F24:F25) -> 75.48717 | J26: =SUM(J22,J24:J25) -> 33.14829 | K26: =SUM(K22,K24:K25) -> 50.741535 | L26: =SUM(L22,L24:L25) -> 69.32017 | M26: =SUM(M22,M24:M25) -> 53.453745 | N26: =SUM(N22,N24:N25) -> 940.53884
A27: TAX | C27: Imposte | D27: =-SUMIFS(DB_Complessivo!$E:$E,DB_Complessivo!$A:$A,"ACT",DB_Complessivo!$J:$J,$A27,DB_Complessivo!$B:$B,D$3)/1000 -> 0 | E27: =-SUMIFS(DB_Complessivo!$E:$E,DB_Complessivo!$A:$A,$E$2,DB_Complessivo!$J:$J,$A27,DB_Complessivo!$B:$B,E$3)/1000 -> 0 | F27: =-SUMIFS(DB_Complessivo!$E:$E,DB_Complessivo!$A:$A,"ACT",DB_Complessivo!$J:$J,$A27,DB_Complessivo!$B:$B,F$3)/1000 -> 0 | J27: =-SUMIFS(DB_Complessivo!$E:$E,DB_Complessivo!$A:$A,"ACT",DB_Complessivo!$J:$J,$A27,DB_Complessivo!$B:$B,J$3)/1000 -> 0 | K27: =-SUMIFS(DB_Complessivo!$E:$E,DB_Complessivo!$A:$A,"ACT",DB_Complessivo!$J:$J,$A27,DB_Complessivo!$B:$B,K$3)/1000 -> 0 | L27: =-SUMIFS(DB_Complessivo!$E:$E,DB_Complessivo!$A:$A,"ACT",DB_Complessivo!$J:$J,$A27,DB_Complessivo!$B:$B,L$3)/1000 -> -0.948 | M27: =-SUMIFS(DB_Complessivo!$E:$E,DB_Complessivo!$A:$A,"ACT",DB_Complessivo!$J:$J,$A27,DB_Complessivo!$B:$B,M$3)/1000 -> 0 | N27: =-SUMIFS(DB_Complessivo!$E:$E,DB_Complessivo!$A:$A,"ACT",DB_Complessivo!$J:$J,$A27,DB_Complessivo!$B:$B,N$3)/1000 -> 0
C28: Risultato d'esercizio | D28: =SUM(D26:D27) -> 890.35653 | E28: =SUM(E26:E27) -> -86.332385 | F28: =SUM(F26:F27) -> 75.48717 | J28: =SUM(J26:J27) -> 33.14829 | K28: =SUM(K26:K27) -> 50.741535 | L28: =SUM(L26:L27) -> 68.37217 | M28: =SUM(M26:M27) -> 53.453745 | N28: =SUM(N26:N27) -> 940.53884

Sheet CE_Esteso
C1: CONTO ECONOMICO di PROGETTO QUID | D1: PY | F1: REV_BDG | G1: ACT | H1: DELTA | I1: DELTA (%) | K1: PJ 2025
C2: EUR/000 | D2: =EOMONTH(INDICE!$B$2,-12) -> 45473 | F2: =EOMONTH(INDICE!$B$2,0) -> 45838 | G2: =EOMONTH(INDICE!$B$2,0) -> 45838 | H2: ACT vs BDG | I2: ACT vs BDG | K2: FCT 2025
A3: RICOP | C3: Ricavi Netti di Vendita | D3: =-SUMIFS(DB_Complessivo!$E:$E,DB_Complessivo!$A:$A,"ACT",DB_Complessivo!$B:$B,D$2,DB_Complessivo!$H:$H,$A3)/1000 -> 3007.6994 | F3: =-SUMIFS(DB_Complessivo!$E:$E,DB_Complessivo!$A:$A,$F$1,DB_Complessivo!$B:$B,F$2,DB_Complessivo!$H:$H,$A3)/1000 -> 3057.6796 | G3: =-SUMIFS(DB_Complessivo!$E:$E,DB_Complessivo!$A:$A,"ACT",DB_Complessivo!$B:$B,G$2,DB_Complessivo!$H:$H,$A3)/1000 -> 3134.7637 | H3: =G3-F3 -> 77.084109 | I3: =IFERROR((G3-F3)/ABS(F3),"") -> 0.025210002 | K3: =+SUM(FCT!D3:O3) -> 6180.0423 | L3: x
A4: CORR | C4: Corrispettivi | D4: =-SUMIFS(DB_Complessivo!$E:$E,DB_Complessivo!$A:$A,"ACT",DB_Complessivo!$B:$B,D$2,DB_Complessivo!$H:$H,$A4)/1000 -> 583.8182 | F4: =-SUMIFS(DB_Complessivo!$E:$E,DB_Complessivo!$A:$A,$F$1,DB_Complessivo!$B:$B,F$2,DB_Complessivo!$H:$H,$A4)/1000 -> 145.36444 | G4: =-SUMIFS(DB_Complessivo!$E:$E,DB_Complessivo!$A:$A,"ACT",DB_Complessivo!$B:$B,G$2,DB_Complessivo!$H:$H,$A4)/1000 -> 145.43466 | H4: =G4-F4 -> 0.07022 | I4: =IFERROR((G4-F4)/ABS(F4),"") -> 0.00048306174 | K4: =+SUM(FCT!D4:O4) -> 216.43466 | L4: x
A5: VARPF | C5: Variazione magazzino PF | D5: =-SUMIFS(DB_Complessivo!$E:$E,DB_Complessivo!$A:$A,"ACT",DB_Complessivo!$B:$B,D$2,DB_Complessivo!$H:$H,$A5)/1000 -> -378.34423 | F5: =-SUMIFS(DB_Complessivo!$E:$E,DB_Complessivo!$A:$A,$F$1,DB_Complessivo!$B:$B,F$2,DB_Complessivo!$H:$H,$A5)/1000 -> 50.48681 | G5: =-SUMIFS(DB_Complessivo!$E:$E,DB_Complessivo!$A:$A,"ACT",DB_Complessivo!$B:$B,G$2,DB_Complessivo!$H:$H,$A5)/1000 -> -30.72334 | H5: =G5-F5 -> -81.21015 | I5: =IFERROR((G5-F5)/ABS(F5),"") -> -1.6085419 | K5: =+SUM(FCT!D5:O5) -> -30.72334 | L5: x
A6: ALTRI | C6: Altri Ricavi | D6: =-SUMIFS(DB_Complessivo!$E:$E,DB_Complessivo!$A:$A,"ACT",DB_Complessivo!$B:$B,D$2,DB_Complessivo!$H:$H,$A6)/1000 -> 505.36009 | F6: =-SUMIFS(DB_Complessivo!$E:$E,DB_Complessivo!$A:$A,$F$1,DB_Complessivo!$B:$B,F$2,DB_Complessivo!$H:$H,$A6)/1000 -> 290.01446 | G6: =-SUMIFS(DB_Complessivo!$E:$E,DB_Complessivo!$A:$A,"ACT",DB_Complessivo!$B:$B,G$2,DB_Complessivo!$H:$H,$A6)/1000 -> 593.21178 | H6: =G6-F6 -> 303.19732 | I6: =IFERROR((G6-F6)/ABS(F6),"") -> 1.0454559 | K6: =+SUM(FCT!D6:O6) -> 1259.2901 | L6: x
A7: SUBTOTALE | C7: Ricavi | D7: =SUM(D3:D6) -> 3718.5335 | F7: =SUM(F3:F6) -> 3543.5453 | G7: =SUM(G3:G6) -> 3842.6868 | H7: =G7-F7 -> 299.1415 | I7: =IFERROR((G7-F7)/ABS(F7),"") -> 0.084418704 | K7: =SUM(K3:K6) -> 7625.0438
A8: ACQDI | C8: Acquisti diretti di produzione | D8: =-SUMIFS(DB_Complessivo!$E:$E,DB_Complessivo!$A:$A,"ACT",DB_Complessivo!$B:$B,D$2,DB_Complessivo!$H:$H,$A8)/1000 -> -262.589 | F8: =-SUMIFS(DB_Complessivo!$E:$E,DB_Complessivo!$A:$A,$F$1,DB_Complessivo!$B:$B,F$2,DB_Complessivo!$H:$H,$A8)/1000 -> -254.76535 | G8: =-SUMIFS(DB_Complessivo!$E:$E,DB_Complessivo!$A:$A,"ACT",DB_Complessivo!$B:$B,G$2,DB_Complessivo!$H:$H,$A8)/1000 -> -313.83995 | H8: =G8-F8 -> -59.074598 | I8: =IFERROR((G8-F8)/ABS(F8),"") -> -0.23187846 | K8: =+SUM(FCT!D8:O8) -> -581.95096 | L8: x
A9: VARMP | C9: Variazioni magazzino MP / SL | D9: =-SUMIFS(DB_Complessivo!$E:$E,DB_Complessivo!$A:$A,"ACT",DB_Complessivo!$B:$B,D$2,DB_Complessivo!$H:$H,$A9)/1000 -> 254.29484 | F9: =-SUMIFS(DB_Complessivo!$E:$E,DB_Complessivo!$A:$A,$F$1,DB_Complessivo!$B:$B,F$2,DB_Complessivo!$H:$H,$A9)/1000 -> -49.94251 | G9: =-SUMIFS(DB_Complessivo!$E:$E,DB_Complessivo!$A:$A,"ACT",DB_Complessivo!$B:$B,G$2,DB_Complessivo!$H:$H,$A9)/1000 -> -51.59331 | H9: =G9-F9 -> -1.6508 | I9: =IFERROR((G9-F9)/ABS(F9),"") -> -0.033054005 | K9: =+SUM(FCT!D9:O9) -> -51.59331 | L9: x
A10: SERDI | C10: Lavorazioni esterne | D10: =-SUMIFS(DB_Complessivo!$E:$E,DB_Complessivo!$A:$A,"ACT",DB_Complessivo!$B:$B,D$2,DB_Complessivo!$H:$H,$A10)/1000 -> -354.46345 | F10: =-SUMIFS(DB_Complessivo!$E:$E,DB_Complessivo!$A:$A,$F$1,DB_Complessivo!$B:$B,F$2,DB_Complessivo!$H:$H,$A10)/1000 -> -566.4114 | G10: =-SUMIFS(DB_Complessivo!$E:$E,DB_Complessivo!$A:$A,"ACT",DB_Complessivo!$B:$B,G$2,DB_Complessivo!$H:$H,$A10)/1000 -> -519.22252 | H10: =G10-F10 -> 47.18888 | I10: =IFERROR((G10-F10)/ABS(F10),"") -> 0.083312024 | K10: =+SUM(FCT!D10:O10) -> -1102.4473 | L10: x
A11: PERDI | C11: Manodopera diretta di produzione | D11: =-SUMIFS(DB_Complessivo!$E:$E,DB_Complessivo!$A:$A,"ACT",DB_Complessivo!$B:$B,D$2,DB_Complessivo!$H:$H,$A11)/1000 -> -643.8996 | F11: =-SUMIFS(DB_Complessivo!$E:$E,DB_Complessivo!$A:$A,$F$1,DB_Complessivo!$B:$B,F$2,DB_Complessivo!$H:$H,$A11)/1000 -> -795.46433 | G11: =-SUMIFS(DB_Complessivo!$E:$E,DB_Complessivo!$A:$A,"ACT",DB_Complessivo!$B:$B,G$2,DB_Complessivo!$H:$H,$A11)/1000 -> -780.02684 | H11: =G11-F11 -> 15.437484 | I11: =IFERROR((G11-F11)/ABS(F11),"") -> 0.019406884 | K11: =+SUM(FCT!D11:O11) -> -1575.462 | L11: x
A12: SUBTOTALE | C12: Margine Diretto di Produzione | D12: =SUM(D7:D11) -> 2711.8762 | F12: =SUM(F7:F11) -> 1876.9617 | G12: =SUM(G7:G11) -> 2178.0042 | H12: =G12-F12 -> 301.04247 | I12: =IFERROR((G12-F12)/ABS(F12),"") -> 0.16038818 | K12: =SUM(K7:K11) -> 4313.5902
A13: SUBTOTALE | C13: Margine diretto di produzione (%) | D13: =IFERROR(D12/D$7,"") -> 0.7292865 | F13: =IFERROR(F12/F$7,"") -> 0.52968469 | G13: =IFERROR(G12/G$7,"") -> 0.56679201 | H13: =G13-F13 -> 0.037107316 | I13: =IFERROR((G13-F13)/ABS(F13),"") -> 0.070055481 | K13: =IFERROR(K12/K$7,"") -> 0.5657135
A14: ACQIN | C14: Acquisti indiretti di fabbrica | D14: =-SUMIFS(DB_Complessivo!$E:$E,DB_Complessivo!$A:$A,"ACT",DB_Complessivo!$B:$B,D$2,DB_Complessivo!$H:$H,$A14)/1000 -> -10.14771 | F14: =-SUMIFS(DB_Complessivo!$E:$E,DB_Complessivo!$A:$A,$F$1,DB_Complessivo!$B:$B,F$2,DB_Complessivo!$H:$H,$A14)/1000 -> -8.958456 | G14: =-SUMIFS(DB_Complessivo!$E:$E,DB_Complessivo!$A:$A,"ACT",DB_Complessivo!$B:$B,G$2,DB_Complessivo!$H:$H,$A14)/1000 -> -9.83135 | H14: =G14-F14 -> -0.872894 | I14: =IFERROR((G14-F14)/ABS(F14),"") -> -0.097437996 | K14: =+SUM(FCT!D14:O14) -> -14.875142 | L14: x
A15: PERIM | C15: Costi del personale diretto improduttivo | D15: =-SUMIFS(DB_Complessivo!$E:$E,DB_Complessivo!$A:$A,"ACT",DB_Complessivo!$B:$B,D$2,DB_Complessivo!$H:$H,$A15)/1000 -> -275.95697 | F15: =-SUMIFS(DB_Complessivo!$E:$E,DB_Complessivo!$A:$A,$F$1,DB_Complessivo!$B:$B,F$2,DB_Complessivo!$H:$H,$A15)/1000 -> -340.91328 | G15: =-SUMIFS(DB_Complessivo!$E:$E,DB_Complessivo!$A:$A,"ACT",DB_Complessivo!$B:$B,G$2,DB_Complessivo!$H:$H,$A15)/1000 -> -334.29722 | H15: =G15-F15 -> 6.6160645 | I15: =IFERROR((G15-F15)/ABS(F15),"") -> 0.019406884 | K15: =+SUM(FCT!D15:O15) -> -675.19799
A16: PERIN | C16: Costi del Personale indiretto di fabbrica | D16: =-SUMIFS(DB_Complessivo!$E:$E,DB_Complessivo!$A:$A,"ACT",DB_Complessivo!$B:$B,D$2,DB_Complessivo!$H:$H,$A16)/1000 -> -278.62387 | F16: =-SUMIFS(DB_Complessivo!$E:$E,DB_Complessivo!$A:$A,$F$1,DB_Complessivo!$B:$B,F$2,DB_Complessivo!$H:$H,$A16)/1000 -> -411.44048 | G16: =-SUMIFS(DB_Complessivo!$E:$E,DB_Complessivo!$A:$A,"ACT",DB_Complessivo!$B:$B,G$2,DB_Complessivo!$H:$H,$A16)/1000 -> -406.57358 | H16: =G16-F16 -> 4.8668985 | I16: =IFERROR((G16-F16)/ABS(F16),"") -> 0.011828925 | K16: =+SUM(FCT!D16:O16) -> -786.76095
A17: SERIN | C17: Servizi indiretti di fabbrica | D17: =-SUMIFS(DB_Complessivo!$E:$E,DB_Complessivo!$A:$A,"ACT",DB_Complessivo!$B:$B,D$2,DB_Complessivo!$H:$H,$A17)/1000 -> -70.96753 | F17: =-SUMIFS(DB_Complessivo!$E:$E,DB_Complessivo!$A:$A,$F$1,DB_Complessivo!$B:$B,F$2,DB_Complessivo!$H:$H,$A17)/1000 -> -94.120566 | G17: =-SUMIFS(DB_Complessivo!$E:$E,DB_Complessivo!$A:$A,"ACT",DB_Complessivo!$B:$B,G$2,DB_Complessivo!$H:$H,$A17)/1000 -> -96.76461 | H17: =G17-F17 -> -2.644044 | I17: =IFERROR((G17-F17)/ABS(F17),"") -> -0.028092096 | K17: =+SUM(FCT!D17:O17) -> -222.74969 | L17: x
A18: AMMIN | C18: Ammortamenti indiretti di fabbrica | D18: =-SUMIFS(DB_Complessivo!$E:$E,DB_Complessivo!$A:$A,"ACT",DB_Complessivo!$B:$B,D$2,DB_Complessivo!$H:$H,$A18)/1000 -> -39.921 | F18: =-SUMIFS(DB_Complessivo!$E:$E,DB_Complessivo!$A:$A,$F$1,DB_Complessivo!$B:$B,F$2,DB_Complessivo!$H:$H,$A18)/1000 -> -43.92702 | G18: =-SUMIFS(DB_Complessivo!$E:$E,DB_Complessivo!$A:$A,"ACT",DB_Complessivo!$B:$B,G$2,DB_Complessivo!$H:$H,$A18)/1000 -> -43.92693 | H18: =G18-F18 -> 9e-05 | I18: =IFERROR((G18-F18)/ABS(F18),"") -> 2.0488528e-06 | K18: =+SUM(FCT!D18:O18) -> -87.85395 | L18: x
A19: SUBTOTALE | C19: Margine Indiretto di Fabbrica | D19: =SUM(D12,D14:D18) -> 2036.2592 | F19: =SUM(F12,F14:F18) -> 977.60188 | G19: =SUM(G12,G14:G18) -> 1286.6105 | H19: =G19-F19 -> 309.00858 | I19: =IFERROR((G19-F19)/ABS(F19),"") -> 0.31608836 | K19: =SUM(K12,K14:K18) -> 2526.1525
A20: SUBTOTALE | C20: Margine indiretto di fabbrica (%) | D20: =IFERROR(D19/D$7,"") -> 0.54759737 | F20: =IFERROR(F19/F$7,"") -> 0.27588243 | G20: =IFERROR(G19/G$7,"") -> 0.33482054 | H20: =G20-F20 -> 0.05893811 | I20: =IFERROR((G20-F20)/ABS(F20),"") -> 0.21363488 | K20: =IFERROR(K19/K$7,"") -> 0.33129679
A21: PERST | C21: Costi del personale di struttura | D21: =-SUMIFS(DB_Complessivo!$E:$E,DB_Complessivo!$A:$A,"ACT",DB_Complessivo!$B:$B,D$2,DB_Complessivo!$H:$H,$A21)/1000 -> -608.58641 | F21: =-SUMIFS(DB_Complessivo!$E:$E,DB_Complessivo!$A:$A,$F$1,DB_Complessivo!$B:$B,F$2,DB_Complessivo!$H:$H,$A21)/1000 -> -496.85693 | G21: =-SUMIFS(DB_Complessivo!$E:$E,DB_Complessivo!$A:$A,"ACT",DB_Complessivo!$B:$B,G$2,DB_Complessivo!$H:$H,$A21)/1000 -> -630.26133 | H21: =G21-F21 -> -133.4044 | I21: =IFERROR((G21-F21)/ABS(F21),"") -> -0.26849661 | K21: =+SUM(FCT!D21:O21) -> -1098.8008
A22: SERST | C22: Servizi di struttura | D22: =-SUMIFS(DB_Complessivo!$E:$E,DB_Complessivo!$A:$A,"ACT",DB_Complessivo!$B:$B,D$2,DB_Complessivo!$H:$H,$A22)/1000 -> -279.21442 | F22: =-SUMIFS(DB_Complessivo!$E:$E,DB_Complessivo!$A:$A,$F$1,DB_Complessivo!$B:$B,F$2,DB_Complessivo!$H:$H,$A22)/1000 -> -311.56084 | G22: =-SUMIFS(DB_Complessivo!$E:$E,DB_Complessivo!$A:$A,"ACT",DB_Complessivo!$B:$B,G$2,DB_Complessivo!$H:$H,$A22)/1000 -> -385.23776 | H22: =G22-F22 -> -73.676923 | I22: =IFERROR((G22-F22)/ABS(F22),"") -> -0.23647684 | K22: =+SUM(FCT!D22:O22) -> -619.7632 | L22: x
A23: AFFIT | C23: Affitti | D23: =-SUMIFS(DB_Complessivo!$E:$E,DB_Complessivo!$A:$A,"ACT",DB_Complessivo!$B:$B,D$2,DB_Complessivo!$H:$H,$A23)/1000 -> -85.26118 | F23: =-SUMIFS(DB_Complessivo!$E:$E,DB_Complessivo!$A:$A,$F$1,DB_Complessivo!$B:$B,F$2,DB_Complessivo!$H:$H,$A23)/1000 -> -38.6754 | G23: =-SUMIFS(DB_Complessivo!$E:$E,DB_Complessivo!$A:$A,"ACT",DB_Complessivo!$B:$B,G$2,DB_Complessivo!$H:$H,$A23)/1000 -> -46.5754 | H23: =G23-F23 -> -7.9 | I23: =IFERROR((G23-F23)/ABS(F23),"") -> -0.20426421 | K23: =+SUM(FCT!D23:O23) -> -88.7008 | L23: x
A24: COSGS | C24: Costi generali di struttura | D24: =-SUMIFS(DB_Complessivo!$E:$E,DB_Complessivo!$A:$A,"ACT",DB_Complessivo!$B:$B,D$2,DB_Complessivo!$H:$H,$A24)/1000 -> -145.80193 | F24: =-SUMIFS(DB_Complessivo!$E:$E,DB_Complessivo!$A:$A,$F$1,DB_Complessivo!$B:$B,F$2,DB_Complessivo!$H:$H,$A24)/1000 -> -143.67684 | G24: =-SUMIFS(DB_Complessivo!$E:$E,DB_Complessivo!$A:$A,"ACT",DB_Complessivo!$B:$B,G$2,DB_Complessivo!$H:$H,$A24)/1000 -> -174.7357 | H24: =G24-F24 -> -31.058861 | I24: =IFERROR((G24-F24)/ABS(F24),"") -> -0.21617166 | K24: =+SUM(FCT!D24:O24) -> -298.18387 | L24: x
A25: AMMST | C25: Ammortamenti di struttura | D25: =-SUMIFS(DB_Complessivo!$E:$E,DB_Complessivo!$A:$A,"ACT",DB_Complessivo!$B:$B,D$2,DB_Complessivo!$H:$H,$A25)/1000 -> -16.265048 | F25: =-SUMIFS(DB_Complessivo!$E:$E,DB_Complessivo!$A:$A,$F$1,DB_Complessivo!$B:$B,F$2,DB_Complessivo!$H:$H,$A25)/1000 -> -23.28552 | G25: =-SUMIFS(DB_Complessivo!$E:$E,DB_Complessivo!$A:$A,"ACT",DB_Complessivo!$B:$B,G$2,DB_Complessivo!$H:$H,$A25)/1000 -> -23.28552 | H25: =G25-F25 -> 0 | I25: =IFERROR((G25-F25)/ABS(F25),"") -> 0 | K25: =+SUM(FCT!D25:O25) -> -46.57104 | L25: x
A26: ACC | C26: Accantonamenti | D26: =-SUMIFS(DB_Complessivo!$E:$E,DB_Complessivo!$A:$A,"ACT",DB_Complessivo!$B:$B,D$2,DB_Complessivo!$H:$H,$A26)/1000 -> 0 | F26: =-SUMIFS(DB_Complessivo!$E:$E,DB_Complessivo!$A:$A,$F$1,DB_Complessivo!$B:$B,F$2,DB_Complessivo!$H:$H,$A26)/1000 -> 0 | G26: =-SUMIFS(DB_Complessivo!$E:$E,DB_Complessivo!$A:$A,"ACT",DB_Complessivo!$B:$B,G$2,DB_Complessivo!$H:$H,$A26)/1000 -> 0 | H26: =G26-F26 -> 0 | I26: =IFERROR((G26-F26)/ABS(F26),"") | K26: =+SUM(FCT!D26:O26) -> 0
A27: SUBTOTALE | C27: Risultato Operativo | D27: =SUM(D19,D21:D26) -> 901.13017 | F27: =SUM(F19,F21:F26) -> -36.453645 | G27: =SUM(G19,G21:G26) -> 26.51475 | H27: =G27-F27 -> 62.968395 | I27: =IFERROR((G27-F27)/ABS(F27),"") -> 1.7273552 | K27: =SUM(K19,K21:K26) -> 374.13276
A28: SUBTOTALE | C28: EBIT (%) | D28: =IFERROR(D27/D$7,"") -> 0.24233483 | F28: =IFERROR(F27/F$7,"") -> -0.010287337 | G28: =IFERROR(G27/G$7,"") -> 0.006900055 | H28: =G28-F28 -> 0.017187392 | I28: =IFERROR((G28-F28)/ABS(F28),"") -> 1.6707328 | K28: =IFERROR(K27/K$7,"") -> 0.04906631
A29: ONFIN | C29: Gestione Finanziaria | D29: =-SUMIFS(DB_Complessivo!$E:$E,DB_Complessivo!$A:$A,"ACT",DB_Complessivo!$B:$B,D$2,DB_Complessivo!$H:$H,$A29)/1000 -> -44.34164 | F29: =-SUMIFS(DB_Complessivo!$E:$E,DB_Complessivo!$A:$A,$F$1,DB_Complessivo!$B:$B,F$2,DB_Complessivo!$H:$H,$A29)/1000 -> 0 | G29: =-SUMIFS(DB_Complessivo!$E:$E,DB_Complessivo!$A:$A,"ACT",DB_Complessivo!$B:$B,G$2,DB_Complessivo!$H:$H,$A29)/1000 -> 11.67779 | H29: =G29-F29 -> 11.67779 | I29: =IFERROR((G29-F29)/ABS(F29),"") | K29: =+SUM(FCT!D29:O29) -> 11.67779
A30: ONSTR | C30: Gestione Straordinaria e Non Core | D30: =-SUMIFS(DB_Complessivo!$E:$E,DB_Complessivo!$A:$A,"ACT",DB_Complessivo!$B:$B,D$2,DB_Complessivo!$H:$H,$A30)/1000 -> 33.568 | F30: =-SUMIFS(DB_Complessivo!$E:$E,DB_Complessivo!$A:$A,$F$1,DB_Complessivo!$B:$B,F$2,DB_Complessivo!$H:$H,$A30)/1000 -> -49.87874 | G30: =-SUMIFS(DB_Complessivo!$E:$E,DB_Complessivo!$A:$A,"ACT",DB_Complessivo!$B:$B,G$2,DB_Complessivo!$H:$H,$A30)/1000 -> 37.29463 | H30: =G30-F30 -> 87.17337 | I30: =IFERROR((G30-F30)/ABS(F30),"") -> 1.7477059 | K30: =+SUM(FCT!D30:O30) -> 37.29463
A31: SUBTOTALE | C31: EBT | D31: =SUM(D27,D29:D30) -> 890.35653 | F31: =SUM(F27,F29:F30) -> -86.332385 | G31: =SUM(G27,G29:G30) -> 75.48717 | H31: =G31-F31 -> 161.81956 | I31: =IFERROR((G31-F31)/ABS(F31),"") -> 1.8743784 | K31: =SUM(K27,K29:K30) -> 423.10518
A32: TAX | C32: - Imposte | D32: =-SUMIFS(DB_Complessivo!$E:$E,DB_Complessivo!$A:$A,"ACT",DB_Complessivo!$B:$B,D$2,DB_Complessivo!$H:$H,$A32)/1000 -> 0 | F32: =-SUMIFS(DB_Complessivo!$E:$E,DB_Complessivo!$A:$A,$F$1,DB_Complessivo!$B:$B,F$2,DB_Complessivo!$H:$H,$A32)/1000 -> 0 | G32: =-SUMIFS(DB_Complessivo!$E:$E,DB_Complessivo!$A:$A,"ACT",DB_Complessivo!$B:$B,G$2,DB_Complessivo!$H:$H,$A32)/1000 -> 0 | H32: =G32-F32 -> 0 | I32: =IFERROR((G32-F32)/ABS(F32),"") | K32: 0
A33: SUBTOTALE | C33: Utile/perdita di esercizio | D33: =SUM(D31:D32) -> 890.35653 | F33: =SUM(F31:F32) -> -86.332385 | G33: =SUM(G31:G32) -> 75.48717 | H33: =G33-F33 -> 161.81956 | I33: =IFERROR((G33-F33)/ABS(F33),"") -> 1.8743784 | K33: =SUM(K31:K32) -> 423.10518

Sheet SP_CIN
C1: STATO PATRIMONIALE di PROGETTO QUID
C2: EUR/000 | D2: 45657 | E2: =INDICE!B2 -> 45838 | H2: 45657 | I2: =E2 -> 45838
C4: Immobilizzazioni Immateriali Nette | D4: =INDEX(SP!4:4,MATCH(D2,SP!2:2,0)) -> 83.93744 | E4: =INDEX(SP!4:4,MATCH(E2,SP!2:2,0)) -> 71.35754 | G4: Debiti a Breve (Liquidità) | H4: =-SUMIFS(DB_Complessivo!$E:$E,DB_Complessivo!$A:$A,"ACT",DB_Complessivo!$H:$H,$K4,DB_Complessivo!$B:$B,D$2)/1000 -> -2755.6611 | I4: =-SUMIFS(DB_Complessivo!$E:$E,DB_Complessivo!$A:$A,"ACT",DB_Complessivo!$H:$H,$K4,DB_Complessivo!$B:$B,E$2)/1000 -> -3022.1902 | K4: 36.LIQ
C5: Immobilizzazioni Materiali Nette | D5: =INDEX(SP!7:7,MATCH(D2,SP!2:2,0)) -> 1007.7579 | E5: =INDEX(SP!7:7,MATCH(E2,SP!2:2,0)) -> 993.70459 | G5: Utilizzo Linee Anticipo Fatture | H5: =-SUMIFS(DB_Complessivo!$E:$E,DB_Complessivo!$A:$A,"ACT",DB_Complessivo!$H:$H,$K5,DB_Complessivo!$B:$B,D$2)/1000 -> 492.45933 | I5: =-SUMIFS(DB_Complessivo!$E:$E,DB_Complessivo!$A:$A,"ACT",DB_Complessivo!$H:$H,$K5,DB_Complessivo!$B:$B,E$2)/1000 -> 20.32174 | K5: 36.ANT
A6: 38.TFR | C6: Fondo TFR | D6: =SUMIFS(DB_Complessivo!$E:$E,DB_Complessivo!$A:$A,"ACT",DB_Complessivo!$H:$H,$A6,DB_Complessivo!$B:$B,D$2)/1000 -> -674.25167 | E6: =SUMIFS(DB_Complessivo!$E:$E,DB_Complessivo!$A:$A,"ACT",DB_Complessivo!$H:$H,$A6,DB_Complessivo!$B:$B,E$2)/1000 -> -733.2327 | G6: PFN a Breve Termine | H6: =+SUM(H4:H5) -> -2263.2018 | I6: =+SUM(I4:I5) -> -3001.8684
A7: 33.PROV | C7: Altri Fondi | D7: =SUMIFS(DB_Complessivo!$E:$E,DB_Complessivo!$A:$A,"ACT",DB_Complessivo!$H:$H,$A7,DB_Complessivo!$B:$B,D$2)/1000 -> -518.56361 | E7: =SUMIFS(DB_Complessivo!$E:$E,DB_Complessivo!$A:$A,"ACT",DB_Complessivo!$H:$H,$A7,DB_Complessivo!$B:$B,E$2)/1000 -> -574.2685 | K7: 37.DFIN
C8: ATTIVO FISSO NETTO | D8: =SUM(D4:D7) -> -101.11996 | E8: =SUM(E4:E7) -> -242.43907 | G8: Debiti Finanziari (MLT) | H8: =-SUMIFS(DB_Complessivo!$E:$E,DB_Complessivo!$A:$A,"ACT",DB_Complessivo!$H:$H,$K7,DB_Complessivo!$B:$B,D$2)/1000 -> 2345.1617 | I8: =-SUMIFS(DB_Complessivo!$E:$E,DB_Complessivo!$A:$A,"ACT",DB_Complessivo!$H:$H,$K7,DB_Complessivo!$B:$B,E$2)/1000 -> 2062.2307 | K8: 25.I.FIN
G9: Immobilizzazioni Finanziarie | H9: =-SUMIFS(DB_Complessivo!$E:$E,DB_Complessivo!$A:$A,"ACT",DB_Complessivo!$H:$H,$K8,DB_Complessivo!$B:$B,D$2)/1000 -> -1140.2291 | I9: =-SUMIFS(DB_Complessivo!$E:$E,DB_Complessivo!$A:$A,"ACT",DB_Complessivo!$H:$H,$K8,DB_Complessivo!$B:$B,E$2)/1000 -> -1118.8116
A10: 26.MAG | C10: Rimanenze | D10: =SUMIFS(DB_Complessivo!$E:$E,DB_Complessivo!$A:$A,"ACT",DB_Complessivo!$H:$H,$A10,DB_Complessivo!$B:$B,D$2)/1000 -> 573.3745 | E10: =SUMIFS(DB_Complessivo!$E:$E,DB_Complessivo!$A:$A,"ACT",DB_Complessivo!$H:$H,$A10,DB_Complessivo!$B:$B,E$2)/1000 -> 491.05785 | G10: PFN a ML Termine | H10: =SUM(H8:H9) -> 1204.9326 | I10: =SUM(I8:I9) -> 943.41911
A11: 27.CLI | C11: Crediti Commerciali | D11: =SUMIFS(DB_Complessivo!$E:$E,DB_Complessivo!$A:$A,"ACT",DB_Complessivo!$H:$H,$A11,DB_Complessivo!$B:$B,D$2)/1000 -> 1965.6162 | E11: =SUMIFS(DB_Complessivo!$E:$E,DB_Complessivo!$A:$A,"ACT",DB_Complessivo!$H:$H,$A11,DB_Complessivo!$B:$B,E$2)/1000 -> 1353.2129
A12: 28.FOR | C12: Debiti Commerciali | D12: =SUMIFS(DB_Complessivo!$E:$E,DB_Complessivo!$A:$A,"ACT",DB_Complessivo!$H:$H,$A12,DB_Complessivo!$B:$B,D$2)/1000 -> -786.79147 | E12: =SUMIFS(DB_Complessivo!$E:$E,DB_Complessivo!$A:$A,"ACT",DB_Complessivo!$H:$H,$A12,DB_Complessivo!$B:$B,E$2)/1000 -> -827.84899 | G12: POSIZIONE FINANZIARIA NETTA | H12: =H6+H10 -> -1058.2692 | I12: =I6+I10 -> -2058.4493
A13: 29.AC | C13: Altri Crediti | D13: =SUMIFS(DB_Complessivo!$E:$E,DB_Complessivo!$A:$A,"ACT",DB_Complessivo!$H:$H,$A13,DB_Complessivo!$B:$B,D$2)/1000 -> 270.18941 | E13: =SUMIFS(DB_Complessivo!$E:$E,DB_Complessivo!$A:$A,"ACT",DB_Complessivo!$H:$H,$A13,DB_Complessivo!$B:$B,E$2)/1000 -> 374.77313 | K13: 34.CS
A14: 30.AD | C14: Altri Debiti | D14: =SUMIFS(DB_Complessivo!$E:$E,DB_Complessivo!$A:$A,"ACT",DB_Complessivo!$H:$H,$A14,DB_Complessivo!$B:$B,D$2)/1000 -> -648.42184 | E14: =SUMIFS(DB_Complessivo!$E:$E,DB_Complessivo!$A:$A,"ACT",DB_Complessivo!$H:$H,$A14,DB_Complessivo!$B:$B,E$2)/1000 -> -701.66725 | G14: Capitale | H14: =-SUMIFS(DB_Complessivo!$E:$E,DB_Complessivo!$A:$A,"ACT",DB_Complessivo!$H:$H,$K13,DB_Complessivo!$B:$B,D$2)/1000 -> 907.3 | I14: =-SUMIFS(DB_Complessivo!$E:$E,DB_Complessivo!$A:$A,"ACT",DB_Complessivo!$H:$H,$K13,DB_Complessivo!$B:$B,E$2)/1000 -> 951.3 | K14: 35.RIS
A15: 55.DIP | C15: Debiti verso Dipendenti | D15: =SUMIFS(DB_Complessivo!$E:$E,DB_Complessivo!$A:$A,"ACT",DB_Complessivo!$H:$H,$A15,DB_Complessivo!$B:$B,D$2)/1000 -> -244.82115 | E15: =SUMIFS(DB_Complessivo!$E:$E,DB_Complessivo!$A:$A,"ACT",DB_Complessivo!$H:$H,$A15,DB_Complessivo!$B:$B,E$2)/1000 -> -435.97225 | G15: Riserve | H15: =-SUMIFS(DB_Complessivo!$E:$E,DB_Complessivo!$A:$A,"ACT",DB_Complessivo!$H:$H,$K14,DB_Complessivo!$B:$B,D$2)/1000 -> 282.49888 | I15: =-SUMIFS(DB_Complessivo!$E:$E,DB_Complessivo!$A:$A,"ACT",DB_Complessivo!$H:$H,$K14,DB_Complessivo!$B:$B,E$2)/1000 -> 1075.5199
A16: 31.PTN | C16: Posizione Tributaria Netta | D16: =SUMIFS(DB_Complessivo!$E:$E,DB_Complessivo!$A:$A,"ACT",DB_Complessivo!$H:$H,$A16,DB_Complessivo!$B:$B,D$2)/1000 -> 44.04288 | E16: =SUMIFS(DB_Complessivo!$E:$E,DB_Complessivo!$A:$A,"ACT",DB_Complessivo!$H:$H,$A16,DB_Complessivo!$B:$B,E$2)/1000 -> 32.74144 | G16: Utile/Perdita di Esercizio | H16: =+SP!D38 -> 940.53884 | I16: =INDEX(SP!38:38,MATCH(I2,SP!2:2,0)) -> 75.48717
A17: 32.IC | C17: Posizione Intercompany | D17: =SUMIFS(DB_Complessivo!$E:$E,DB_Complessivo!$A:$A,"ACT",DB_Complessivo!$H:$H,$A17,DB_Complessivo!$B:$B,D$2)/1000 -> 0 | E17: =SUMIFS(DB_Complessivo!$E:$E,DB_Complessivo!$A:$A,"ACT",DB_Complessivo!$H:$H,$A17,DB_Complessivo!$B:$B,E$2)/1000 -> 0 | G17: PATRIMONIO NETTO | H17: =SUM(H14:H16) -> 2130.3377 | I17: =SUM(I14:I16) -> 2102.307
C18: CAPITALE CIRCOLANTE NETTO OPERATIVO | D18: =SUM(D10:D17) -> 1173.1885 | E18: =SUM(E10:E17) -> 286.29679
C20: CAPITALE INVESTITO NETTO OPERATIVO | D20: =SUM(D8,D18) -> 1072.0685 | E20: =SUM(E8,E18) -> 43.857723 | G20: TOTALE FONTI FINANZIARIE | H20: =SUM(H12,H17) -> 1072.0685 | I20: =SUM(I12,I17) -> 43.857723
C39: Check | D39: =D20-H20 -> 0 | E39: =E20-I20 -> 1.7053026e-13

Sheet RICLASSIFICATI -->

Sheet CE_CEE
B1: Riclassifica IV Direttiva CEE | C1: =+INDICE!B2 -> 45838 | D1: 45657
A3: A) | B3: A) VALORE DELLA PRODUZIONE | C3: =+SUM(C4:C6) -> 3857893.6 | D3: =+SUM(D4:D6) -> 7465208.9
A4: A.1) | B4: 1) ricavi delle vendite e delle prestazioni | C4: =-SUMIFS(DB_Complessivo!$E:$E,DB_Complessivo!$B:$B,C$1,DB_Complessivo!$A:$A,"ACT",DB_Complessivo!$L:$L,$A4) -> 3280198.3 | D4: =-SUMIFS(DB_Complessivo!$E:$E,DB_Complessivo!$B:$B,D$1,DB_Complessivo!$A:$A,"ACT",DB_Complessivo!$L:$L,$A4) -> 6470133.4
A5: A.2) | B5: 2) variazioni delle rimanenze di prodotti in corso di lavorazione, semilavorati e finiti | C5: =-SUMIFS(DB_Complessivo!$E:$E,DB_Complessivo!$B:$B,C$1,DB_Complessivo!$A:$A,"ACT",DB_Complessivo!$L:$L,$A5) -> -30723.34 | D5: =-SUMIFS(DB_Complessivo!$E:$E,DB_Complessivo!$B:$B,D$1,DB_Complessivo!$A:$A,"ACT",DB_Complessivo!$L:$L,$A5) -> -113780.36
A6: A.5) | B6: 5) altri ricavi e proventi, con separata indicazione dei contributi in conto esercizio | C6: =-SUMIFS(DB_Complessivo!$E:$E,DB_Complessivo!$B:$B,C$1,DB_Complessivo!$A:$A,"ACT",DB_Complessivo!$L:$L,$A6) -> 608418.58 | D6: =-SUMIFS(DB_Complessivo!$E:$E,DB_Complessivo!$B:$B,D$1,DB_Complessivo!$A:$A,"ACT",DB_Complessivo!$L:$L,$A6) -> 1108855.9
A8: B) | B8: B) COSTI DELLA PRODUZIONE | C8: =+SUM(C9:C16) -> 3794084.2 | D8: =+SUM(D9:D16) -> 6569006.6
A9: B.6) | B9: 6) per materie prime, suddidiarie, di consumo e di merci | C9: =SUMIFS(DB_Complessivo!$E:$E,DB_Complessivo!$B:$B,C$1,DB_Complessivo!$A:$A,"ACT",DB_Complessivo!$L:$L,$A9) -> 338334.64 | D9: =SUMIFS(DB_Complessivo!$E:$E,DB_Complessivo!$B:$B,D$1,DB_Complessivo!$A:$A,"ACT",DB_Complessivo!$L:$L,$A9) -> 711929.55
A10: B.7) | B10: 7) per servizi | C10: =SUMIFS(DB_Complessivo!$E:$E,DB_Complessivo!$B:$B,C$1,DB_Complessivo!$A:$A,"ACT",DB_Complessivo!$L:$L,$A10) -> 1114124 | D10: =SUMIFS(DB_Complessivo!$E:$E,DB_Complessivo!$B:$B,D$1,DB_Complessivo!$A:$A,"ACT",DB_Complessivo!$L:$L,$A10) -> 1955676.5
A11: B.8) | B11: 8) per godimento di beni di terzi | C11: =SUMIFS(DB_Complessivo!$E:$E,DB_Complessivo!$B:$B,C$1,DB_Complessivo!$A:$A,"ACT",DB_Complessivo!$L:$L,$A11) -> 69418.2 | D11: =SUMIFS(DB_Complessivo!$E:$E,DB_Complessivo!$B:$B,D$1,DB_Complessivo!$A:$A,"ACT",DB_Complessivo!$L:$L,$A11) -> 188758.52
A12: B.9) | B12: 9) per il personale | C12: =SUMIFS(DB_Complessivo!$E:$E,DB_Complessivo!$B:$B,C$1,DB_Complessivo!$A:$A,"ACT",DB_Complessivo!$L:$L,$A12) -> 2151159 | D12: =SUMIFS(DB_Complessivo!$E:$E,DB_Complessivo!$B:$B,D$1,DB_Complessivo!$A:$A,"ACT",DB_Complessivo!$L:$L,$A12) -> 3559720.9
A13: B.10) | B13: 10) Ammortamenti e svalutazioni | C13: =SUMIFS(DB_Complessivo!$E:$E,DB_Complessivo!$B:$B,C$1,DB_Complessivo!$A:$A,"ACT",DB_Complessivo!$L:$L,$A13) -> 67212.45 | D13: =SUMIFS(DB_Complessivo!$E:$E,DB_Complessivo!$B:$B,D$1,DB_Complessivo!$A:$A,"ACT",DB_Complessivo!$L:$L,$A13) -> 122444
A14: B.11) | B14: 11) variazioni delle rimanenze di materie prime, sussidiarie, di consumo e di merci | C14: =SUMIFS(DB_Complessivo!$E:$E,DB_Complessivo!$B:$B,C$1,DB_Complessivo!$A:$A,"ACT",DB_Complessivo!$L:$L,$A14) -> 51593.31 | D14: =SUMIFS(DB_Complessivo!$E:$E,DB_Complessivo!$B:$B,D$1,DB_Complessivo!$A:$A,"ACT",DB_Complessivo!$L:$L,$A14) -> -119025.56
A15: B.12) | B15: 12) accantonamenti per rischi | C15: =SUMIFS(DB_Complessivo!$E:$E,DB_Complessivo!$B:$B,C$1,DB_Complessivo!$A:$A,"ACT",DB_Complessivo!$L:$L,$A15) -> 0 | D15: =SUMIFS(DB_Complessivo!$E:$E,DB_Complessivo!$B:$B,D$1,DB_Complessivo!$A:$A,"ACT",DB_Complessivo!$L:$L,$A15) -> 0
A16: B.14) | B16: 14) oneri diversi di gestione | C16: =SUMIFS(DB_Complessivo!$E:$E,DB_Complessivo!$B:$B,C$1,DB_Complessivo!$A:$A,"ACT",DB_Complessivo!$L:$L,$A16) -> 2242.603 | D16: =SUMIFS(DB_Complessivo!$E:$E,DB_Complessivo!$B:$B,D$1,DB_Complessivo!$A:$A,"ACT",DB_Complessivo!$L:$L,$A16) -> 149502.65
A18: A-B) | B18: DIFFERENZA TRA VALORE E COSTI DELLA PRODUZIONE (A-B) | C18: =+C3-C8 -> 63809.38 | D18: =+D3-D8 -> 896202.32
A20: C) | B20: C) PROVENTI E ONERI FINANZIARI | C20: =+SUM(C21:C23) -> 11677.79 | D20: =+SUM(D21:D23) -> 44336.52
A21: C.15) | B21: 15) proventi da partecipazioni | C21: =-SUMIFS(DB_Complessivo!$E:$E,DB_Complessivo!$B:$B,C$1,DB_Complessivo!$A:$A,"ACT",DB_Complessivo!$L:$L,$A21) -> 0 | D21: =-SUMIFS(DB_Complessivo!$E:$E,DB_Complessivo!$B:$B,D$1,DB_Complessivo!$A:$A,"ACT",DB_Complessivo!$L:$L,$A21) -> 0
A22: C.16) | B22: 16) altri proventi finanziari | C22: =-SUMIFS(DB_Complessivo!$E:$E,DB_Complessivo!$B:$B,C$1,DB_Complessivo!$A:$A,"ACT",DB_Complessivo!$L:$L,$A22) -> 43286.17 | D22: =-SUMIFS(DB_Complessivo!$E:$E,DB_Complessivo!$B:$B,D$1,DB_Complessivo!$A:$A,"ACT",DB_Complessivo!$L:$L,$A22) -> 151587.43
A23: C.17) | B23: 17) interessi e altri oneri finanziari | C23: =-SUMIFS(DB_Complessivo!$E:$E,DB_Complessivo!$B:$B,C$1,DB_Complessivo!$A:$A,"ACT",DB_Complessivo!$L:$L,$A23) -> -31608.38 | D23: =-SUMIFS(DB_Complessivo!$E:$E,DB_Complessivo!$B:$B,D$1,DB_Complessivo!$A:$A,"ACT",DB_Complessivo!$L:$L,$A23) -> -107250.91
A25: E) | B25: E) PROVENTI E ONERI STRAORDINARI | C25: =+SUM(C26:C27) -> 0 | D25: =+SUM(D26:D27) -> 0
A26: E.20) | B26: 20) proventi con separata indicazione delle plusvalenze da alienazioni | C26: =-SUMIFS(DB_Complessivo!$E:$E,DB_Complessivo!$B:$B,C$1,DB_Complessivo!$A:$A,"ACT",DB_Complessivo!$L:$L,$A26) -> 0 | D26: =-SUMIFS(DB_Complessivo!$E:$E,DB_Complessivo!$B:$B,D$1,DB_Complessivo!$A:$A,"ACT",DB_Complessivo!$L:$L,$A26) -> 0
A27: E.21) | B27: 21) oneri, con separata indicazione delle minusvalenze da alienazione | C27: =-SUMIFS(DB_Complessivo!$E:$E,DB_Complessivo!$B:$B,C$1,DB_Complessivo!$A:$A,"ACT",DB_Complessivo!$L:$L,$A27) -> 0 | D27: =-SUMIFS(DB_Complessivo!$E:$E,DB_Complessivo!$B:$B,D$1,DB_Complessivo!$A:$A,"ACT",DB_Complessivo!$L:$L,$A27) -> 0
B29: RISULTATO PRIMA DELLE IMPOSTE (A-B+C+D+E) | C29: =+C18+C20+C25 -> 75487.17 | D29: =+D18+D20+D25 -> 940538.84
A31: E.22) | B31: 22) imposte sul reddito dell'esercizio, correnti, differite e anticipate | C31: =-SUMIFS(DB_Complessivo!$E:$E,DB_Complessivo!$B:$B,C$1,DB_Complessivo!$A:$A,"ACT",DB_Complessivo!$L:$L,$A31) -> 0 | D31: =-SUMIFS(DB_Complessivo!$E:$E,DB_Complessivo!$B:$B,D$1,DB_Complessivo!$A:$A,"ACT",DB_Complessivo!$L:$L,$A31) -> 0
B33: UTILE (O PERDITA) DELL'ESERCIZIO | C33: =+C29+C31 -> 75487.17 | D33: =+D29+D31 -> 940538.84

Sheet SP_CEE
B1: Stato Patrimoniale - Riclassifica IV Direttiva CEE | C1: =+INDICE!B2 -> 45838 | D1: 45657
B3: ATTIVO
A4: Crediti verso soci | B4: A) Crediti verso soci | C4: =+SUMIFS(DB_Complessivo!$E:$E,DB_Complessivo!$B:$B,C$1,DB_Complessivo!$A:$A,"act",DB_Complessivo!$M:$M,$A4) -> 250 | D4: =+SUMIFS(DB_Complessivo!$E:$E,DB_Complessivo!$B:$B,D$1,DB_Complessivo!$A:$A,"act",DB_Complessivo!$M:$M,$A4) -> 250
B5: B) Immobilizzazioni
A6: Immobilizzazioni Immateriali | B6: I - Immobilizzazioni immateriali | C6: =+SUMIFS(DB_Complessivo!$E:$E,DB_Complessivo!$B:$B,C$1,DB_Complessivo!$A:$A,"act",DB_Complessivo!$M:$M,$A6) -> 71357.54 | D6: =+SUMIFS(DB_Complessivo!$E:$E,DB_Complessivo!$B:$B,D$1,DB_Complessivo!$A:$A,"act",DB_Complessivo!$M:$M,$A6) -> 83937.44
A7: Immobilizzazioni Materiali | B7: II - Immobilizzazioni materiali | C7: =+SUMIFS(DB_Complessivo!$E:$E,DB_Complessivo!$B:$B,C$1,DB_Complessivo!$A:$A,"act",DB_Complessivo!$M:$M,$A7) -> 993704.59 | D7: =+SUMIFS(DB_Complessivo!$E:$E,DB_Complessivo!$B:$B,D$1,DB_Complessivo!$A:$A,"act",DB_Complessivo!$M:$M,$A7) -> 1007757.9
A8: Immobilizzazioni Finanziarie | B8: III - Immobilizazioni finanziarie | C8: =+SUMIFS(DB_Complessivo!$E:$E,DB_Complessivo!$B:$B,C$1,DB_Complessivo!$A:$A,"act",DB_Complessivo!$M:$M,$A8) -> 1118811.6 | D8: =+SUMIFS(DB_Complessivo!$E:$E,DB_Complessivo!$B:$B,D$1,DB_Complessivo!$A:$A,"act",DB_Complessivo!$M:$M,$A8) -> 1140229.1
B9: Totale immobilizzazioni (B) | C9: =+SUM(C6:C8) -> 2183873.7 | D9: =+SUM(D6:D8) -> 2231924.4
B10: C) Attivo circolante
A11: Rimanenze | B11: I - Rimanenze | C11: =+SUMIFS(DB_Complessivo!$E:$E,DB_Complessivo!$B:$B,C$1,DB_Complessivo!$A:$A,"act",DB_Complessivo!$M:$M,$A11) -> 491057.85 | D11: =+SUMIFS(DB_Complessivo!$E:$E,DB_Complessivo!$B:$B,D$1,DB_Complessivo!$A:$A,"act",DB_Complessivo!$M:$M,$A11) -> 573374.5
B12: II - Crediti | C12: =+SUM(C13:C15) -> 1796479.7 | D12: =+SUM(D13:D15) -> 2345615
A13: Crediti Commerciali | B13: 1) verso clienti | C13: =+SUMIFS(DB_Complessivo!$E:$E,DB_Complessivo!$B:$B,C$1,DB_Complessivo!$A:$A,"act",DB_Complessivo!$M:$M,$A13) -> 1353212.9 | D13: =+SUMIFS(DB_Complessivo!$E:$E,DB_Complessivo!$B:$B,D$1,DB_Complessivo!$A:$A,"act",DB_Complessivo!$M:$M,$A13) -> 1965616.2
A14: Crediti Tributari | B14: 5-bis) crediti tributari | C14: =+SUMIFS(DB_Complessivo!$E:$E,DB_Complessivo!$B:$B,C$1,DB_Complessivo!$A:$A,"act",DB_Complessivo!$M:$M,$A14) -> 90457.45 | D14: =+SUMIFS(DB_Complessivo!$E:$E,DB_Complessivo!$B:$B,D$1,DB_Complessivo!$A:$A,"act",DB_Complessivo!$M:$M,$A14) -> 129633.7
A15: Altri Crediti | B15: 5-quater) verso altri | C15: =+SUMIFS(DB_Complessivo!$E:$E,DB_Complessivo!$B:$B,C$1,DB_Complessivo!$A:$A,"act",DB_Complessivo!$M:$M,$A15) -> 352809.37 | D15: =+SUMIFS(DB_Complessivo!$E:$E,DB_Complessivo!$B:$B,D$1,DB_Complessivo!$A:$A,"act",DB_Complessivo!$M:$M,$A15) -> 250365.13
A16: Debiti a Breve (Liquidità) | B16: IV - Disponibilità liquide | C16: =+SUMIFS(DB_Complessivo!$E:$E,DB_Complessivo!$B:$B,C$1,DB_Complessivo!$A:$A,"act",DB_Complessivo!$M:$M,$A16) -> 3001868.4 | D16: =+SUMIFS(DB_Complessivo!$E:$E,DB_Complessivo!$B:$B,D$1,DB_Complessivo!$A:$A,"act",DB_Complessivo!$M:$M,$A16) -> 2263201.8
B17: Totale attivo circolante (C) | C17: =+SUM(C11:C12,C16) -> 5289406 | D17: =+SUM(D11:D12,D16) -> 5182191.3
A18: Ratei/Risconti Attivi | B18: D) Ratei e risconti | C18: =+SUMIFS(DB_Complessivo!$E:$E,DB_Complessivo!$B:$B,C$1,DB_Complessivo!$A:$A,"act",DB_Complessivo!$M:$M,$A18) -> 21633.2 | D18: =+SUMIFS(DB_Complessivo!$E:$E,DB_Complessivo!$B:$B,D$1,DB_Complessivo!$A:$A,"act",DB_Complessivo!$M:$M,$A18) -> 19674.69
B19: TOTALE ATTIVO | C19: =+SUM(C4,C9,C17,C18) -> 7495162.9 | D19: =+SUM(D4,D9,D17,D18) -> 7434040.4
B21: PASSIVO
B22: A) Patrimonio netto
A23: Capitale | B23: I - Capitale | C23: =-SUMIFS(DB_Complessivo!$E:$E,DB_Complessivo!$B:$B,C$1,DB_Complessivo!$A:$A,"act",DB_Complessivo!$M:$M,$A23) -> 951550 | D23: =-SUMIFS(DB_Complessivo!$E:$E,DB_Complessivo!$B:$B,D$1,DB_Complessivo!$A:$A,"act",DB_Complessivo!$M:$M,$A23) -> 907550
A24: Riserva Legale | B24: IV - Riserva legale | C24: =-SUMIFS(DB_Complessivo!$E:$E,DB_Complessivo!$B:$B,C$1,DB_Complessivo!$A:$A,"act",DB_Complessivo!$M:$M,$A24) -> 381571.79 | D24: =-SUMIFS(DB_Complessivo!$E:$E,DB_Complessivo!$B:$B,D$1,DB_Complessivo!$A:$A,"act",DB_Complessivo!$M:$M,$A24) -> 99477.04
A25: Altre Riserve | B25: VI - Altre riserve | C25: =-SUMIFS(DB_Complessivo!$E:$E,DB_Complessivo!$B:$B,C$1,DB_Complessivo!$A:$A,"act",DB_Complessivo!$M:$M,$A25) -> 633249.56 | D25: =-SUMIFS(DB_Complessivo!$E:$E,DB_Complessivo!$B:$B,D$1,DB_Complessivo!$A:$A,"act",DB_Complessivo!$M:$M,$A25) -> 100905.84
A26: VII - Riserva per operaz. di copertura dei flussi finanz. attesi | B26: VII - Riserva per operaz. di copertura dei flussi finanz. attesi | C26: =-SUMIFS(DB_Complessivo!$E:$E,DB_Complessivo!$B:$B,C$1,DB_Complessivo!$A:$A,"act",DB_Complessivo!$M:$M,$A26) -> 60698.52 | D26: =-SUMIFS(DB_Complessivo!$E:$E,DB_Complessivo!$B:$B,D$1,DB_Complessivo!$A:$A,"act",DB_Complessivo!$M:$M,$A26) -> 82116
B27: IX - Utile (perdita) dell'esercizio | C27: =+CE_CEE!C33 -> 75487.17 | D27: =+CE_CEE!D33 -> 940538.84
B28: Totale patrimonio netto (A) | C28: =+SUM(C23:C27) -> 2102557 | D28: =+SUM(D23:D27) -> 2130587.7
A29: Altri Fondi | B29: B) Fondi per rischi e oneri | C29: =-SUMIFS(DB_Complessivo!$E:$E,DB_Complessivo!$B:$B,C$1,DB_Complessivo!$A:$A,"act",DB_Complessivo!$M:$M,$A29) -> 574268.5 | D29: =-SUMIFS(DB_Complessivo!$E:$E,DB_Complessivo!$B:$B,D$1,DB_Complessivo!$A:$A,"act",DB_Complessivo!$M:$M,$A29) -> 518563.61
A30: Fondo TFR | B30: C) T.F.R. | C30: =-SUMIFS(DB_Complessivo!$E:$E,DB_Complessivo!$B:$B,C$1,DB_Complessivo!$A:$A,"act",DB_Complessivo!$M:$M,$A30) -> 733232.7 | D30: =-SUMIFS(DB_Complessivo!$E:$E,DB_Complessivo!$B:$B,D$1,DB_Complessivo!$A:$A,"act",DB_Complessivo!$M:$M,$A30) -> 674251.67
B31: D) Debiti
A32: Debiti Finanziari (MLT) | B32: 4) debiti verso banche | C32: =-SUMIFS(DB_Complessivo!$E:$E,DB_Complessivo!$B:$B,C$1,DB_Complessivo!$A:$A,"act",DB_Complessivo!$M:$M,$A32) -> 2046408.7 | D32: =-SUMIFS(DB_Complessivo!$E:$E,DB_Complessivo!$B:$B,D$1,DB_Complessivo!$A:$A,"act",DB_Complessivo!$M:$M,$A32) -> 2313517.7
A33: Debiti Vs Altri MLT | B33: 5) debiti verso altri finanziatori | C33: =-SUMIFS(DB_Complessivo!$E:$E,DB_Complessivo!$B:$B,C$1,DB_Complessivo!$A:$A,"act",DB_Complessivo!$M:$M,$A33) -> 15822 | D33: =-SUMIFS(DB_Complessivo!$E:$E,DB_Complessivo!$B:$B,D$1,DB_Complessivo!$A:$A,"act",DB_Complessivo!$M:$M,$A33) -> 31643.98
A34: Debiti Commerciali | B34: 7) debiti verso fornitori | C34: =-SUMIFS(DB_Complessivo!$E:$E,DB_Complessivo!$B:$B,C$1,DB_Complessivo!$A:$A,"act",DB_Complessivo!$M:$M,$A34) -> 827848.99 | D34: =-SUMIFS(DB_Complessivo!$E:$E,DB_Complessivo!$B:$B,D$1,DB_Complessivo!$A:$A,"act",DB_Complessivo!$M:$M,$A34) -> 786791.47
A35: Posizione Tributaria Netta | B35: 12) debiti tributari | C35: =-SUMIFS(DB_Complessivo!$E:$E,DB_Complessivo!$B:$B,C$1,DB_Complessivo!$A:$A,"act",DB_Complessivo!$M:$M,$A35) -> 57716.01 | D35: =-SUMIFS(DB_Complessivo!$E:$E,DB_Complessivo!$B:$B,D$1,DB_Complessivo!$A:$A,"act",DB_Complessivo!$M:$M,$A35) -> 85590.82
A36: Debiti vs Ist. Previdenziali | B36: 13) debiti verso istituti previdenziali | C36: =-SUMIFS(DB_Complessivo!$E:$E,DB_Complessivo!$B:$B,C$1,DB_Complessivo!$A:$A,"act",DB_Complessivo!$M:$M,$A36) -> 142139.59 | D36: =-SUMIFS(DB_Complessivo!$E:$E,DB_Complessivo!$B:$B,D$1,DB_Complessivo!$A:$A,"act",DB_Complessivo!$M:$M,$A36) -> 122778.08
A37: Altri Debiti | B37: 14) altri debiti | C37: =-SUMIFS(DB_Complessivo!$E:$E,DB_Complessivo!$B:$B,C$1,DB_Complessivo!$A:$A,"act",DB_Complessivo!$M:$M,$A37) -> 792119.35 | D37: =-SUMIFS(DB_Complessivo!$E:$E,DB_Complessivo!$B:$B,D$1,DB_Complessivo!$A:$A,"act",DB_Complessivo!$M:$M,$A37) -> 421805.89
B38: Totale Debiti (D) | C38: =+SUM(C32:C37) -> 3882054.6 | D38: =+SUM(D32:D37) -> 3762127.9
A39: Ratei/Risconti Passivi | B39: E) Ratei e risconti | C39: =-SUMIFS(DB_Complessivo!$E:$E,DB_Complessivo!$B:$B,C$1,DB_Complessivo!$A:$A,"act",DB_Complessivo!$M:$M,$A39) -> 203050 | D39: =-SUMIFS(DB_Complessivo!$E:$E,DB_Complessivo!$B:$B,D$1,DB_Complessivo!$A:$A,"act",DB_Complessivo!$M:$M,$A39) -> 348509.43
B40: TOTALE PASSIVO | C40: =+SUM(C28,C29,C30,C38,C39) -> 7495162.9 | D40: =+SUM(D28,D29,D30,D38,D39) -> 7434040.4

Sheet CE_YtD
C1: CONTO ECONOMICO di PROGETTO QUID
C2: EUR/000 | D2: 45688 | E2: =EOMONTH(D2,1) -> 45716 | F2: =EOMONTH(E2,1) -> 45747 | G2: =EOMONTH(F2,1) -> 45777 | H2: =EOMONTH(G2,1) -> 45808 | I2: =EOMONTH(H2,1) -> 45838 | J2: =EOMONTH(I2,1) -> 45869 | K2: =EOMONTH(J2,1) -> 45900 | L2: =EOMONTH(K2,1) -> 45930 | ... O2: =EOMONTH(N2,1) -> 46022 | P2: RR | Q2: Giu | R2: delta
A3: RICOP | C3: Ricavi Netti di Vendita | D3: =-SUMIFS(DB_Complessivo!$E:$E,DB_Complessivo!$A:$A,"ACT",DB_Complessivo!$B:$B,D$2,DB_Complessivo!$H:$H,$A3)/1000 -> 390.27999 | E3: =-SUMIFS(DB_Complessivo!$E:$E,DB_Complessivo!$A:$A,"ACT",DB_Complessivo!$B:$B,E$2,DB_Complessivo!$H:$H,$A3)/1000 -> 872.0409 | F3: =-SUMIFS(DB_Complessivo!$E:$E,DB_Complessivo!$A:$A,"ACT",DB_Complessivo!$B:$B,F$2,DB_Complessivo!$H:$H,$A3)/1000 -> 1476.7381 | G3: =-SUMIFS(DB_Complessivo!$E:$E,DB_Complessivo!$A:$A,"ACT",DB_Complessivo!$B:$B,G$2,DB_Complessivo!$H:$H,$A3)/1000 -> 2190.0387 | H3: =-SUMIFS(DB_Complessivo!$E:$E,DB_Complessivo!$A:$A,"ACT",DB_Complessivo!$B:$B,H$2,DB_Complessivo!$H:$H,$A3)/1000 -> 2791.7998 | I3: =-SUMIFS(DB_Complessivo!$E:$E,DB_Complessivo!$A:$A,"ACT",DB_Complessivo!$B:$B,I$2,DB_Complessivo!$H:$H,$A3)/1000 -> 3134.7637 | J3: =-SUMIFS(DB_Complessivo!$E:$E,DB_Complessivo!$A:$A,"ACT",DB_Complessivo!$B:$B,J$2,DB_Complessivo!$H:$H,$A3)/1000 -> 0 | K3: =-SUMIFS(DB_Complessivo!$E:$E,DB_Complessivo!$A:$A,"ACT",DB_Complessivo!$B:$B,K$2,DB_Complessivo!$H:$H,$A3)/1000 -> 0 | ... O3: =-SUMIFS(DB_Complessivo!$E:$E,DB_Complessivo!$A:$A,"ACT",DB_Complessivo!$B:$B,O$2,DB_Complessivo!$H:$H,$A3)/1000 -> 0 | P3: =+H3/5 -> 558.35996 | Q3: =+I3-H3 -> 342.96388 | R3: =+Q3-P3 -> -215.39608
A4: CORR | C4: Corrispettivi | D4: =-SUMIFS(DB_Complessivo!$E:$E,DB_Complessivo!$A:$A,"ACT",DB_Complessivo!$B:$B,D$2,DB_Complessivo!$H:$H,$A4)/1000 -> 38.97781 | E4: =-SUMIFS(DB_Complessivo!$E:$E,DB_Complessivo!$A:$A,"ACT",DB_Complessivo!$B:$B,E$2,DB_Complessivo!$H:$H,$A4)/1000 -> 72.51935 | F4: =-SUMIFS(DB_Complessivo!$E:$E,DB_Complessivo!$A:$A,"ACT",DB_Complessivo!$B:$B,F$2,DB_Complessivo!$H:$H,$A4)/1000 -> 106.98068 | G4: =-SUMIFS(DB_Complessivo!$E:$E,DB_Complessivo!$A:$A,"ACT",DB_Complessivo!$B:$B,G$2,DB_Complessivo!$H:$H,$A4)/1000 -> 119.15013 | H4: =-SUMIFS(DB_Complessivo!$E:$E,DB_Complessivo!$A:$A,"ACT",DB_Complessivo!$B:$B,H$2,DB_Complessivo!$H:$H,$A4)/1000 -> 133.36444 | I4: =-SUMIFS(DB_Complessivo!$E:$E,DB_Complessivo!$A:$A,"ACT",DB_Complessivo!$B:$B,I$2,DB_Complessivo!$H:$H,$A4)/1000 -> 145.43466 | J4: =-SUMIFS(DB_Complessivo!$E:$E,DB_Complessivo!$A:$A,"ACT",DB_Complessivo!$B:$B,J$2,DB_Complessivo!$H:$H,$A4)/1000 -> 0 | K4: =-SUMIFS(DB_Complessivo!$E:$E,DB_Complessivo!$A:$A,"ACT",DB_Complessivo!$B:$B,K$2,DB_Complessivo!$H:$H,$A4)/1000 -> 0 | ... O4: =-SUMIFS(DB_Complessivo!$E:$E,DB_Complessivo!$A:$A,"ACT",DB_Complessivo!$B:$B,O$2,DB_Complessivo!$H:$H,$A4)/1000 -> 0 | P4: =+H4/5 -> 26.672888 | Q4: =+I4-H4 -> 12.07022 | R4: =+Q4-P4 -> -14.602668
A5: VARPF | C5: Variazione magazzino PF | D5: =-SUMIFS(DB_Complessivo!$E:$E,DB_Complessivo!$A:$A,"ACT",DB_Complessivo!$B:$B,D$2,DB_Complessivo!$H:$H,$A5)/1000 -> 84.21847 | E5: =-SUMIFS(DB_Complessivo!$E:$E,DB_Complessivo!$A:$A,"ACT",DB_Complessivo!$B:$B,E$2,DB_Complessivo!$H:$H,$A5)/1000 -> 84.21847 | F5: =-SUMIFS(DB_Complessivo!$E:$E,DB_Complessivo!$A:$A,"ACT",DB_Complessivo!$B:$B,F$2,DB_Complessivo!$H:$H,$A5)/1000 -> 36.63012 | G5: =-SUMIFS(DB_Complessivo!$E:$E,DB_Complessivo!$A:$A,"ACT",DB_Complessivo!$B:$B,G$2,DB_Complessivo!$H:$H,$A5)/1000 -> -4.23812 | H5: =-SUMIFS(DB_Complessivo!$E:$E,DB_Complessivo!$A:$A,"ACT",DB_Complessivo!$B:$B,H$2,DB_Complessivo!$H:$H,$A5)/1000 -> 50.48681 | I5: =-SUMIFS(DB_Complessivo!$E:$E,DB_Complessivo!$A:$A,"ACT",DB_Complessivo!$B:$B,I$2,DB_Complessivo!$H:$H,$A5)/1000 -> -30.72334 | J5: =-SUMIFS(DB_Complessivo!$E:$E,DB_Complessivo!$A:$A,"ACT",DB_Complessivo!$B:$B,J$2,DB_Complessivo!$H:$H,$A5)/1000 -> 0 | K5: =-SUMIFS(DB_Complessivo!$E:$E,DB_Complessivo!$A:$A,"ACT",DB_Complessivo!$B:$B,K$2,DB_Complessivo!$H:$H,$A5)/1000 -> 0 | ... O5: =-SUMIFS(DB_Complessivo!$E:$E,DB_Complessivo!$A:$A,"ACT",DB_Complessivo!$B:$B,O$2,DB_Complessivo!$H:$H,$A5)/1000 -> 0 | P5: =+H5/5 -> 10.097362 | Q5: =+I5-H5 -> -81.21015 | R5: =+Q5-P5 -> -91.307512
A6: ALTRI | C6: Altri Ricavi | D6: =-SUMIFS(DB_Complessivo!$E:$E,DB_Complessivo!$A:$A,"ACT",DB_Complessivo!$B:$B,D$2,DB_Complessivo!$H:$H,$A6)/1000 -> 75.82325 | E6: =-SUMIFS(DB_Complessivo!$E:$E,DB_Complessivo!$A:$A,"ACT",DB_Complessivo!$B:$B,E$2,DB_Complessivo!$H:$H,$A6)/1000 -> 77.74175 | F6: =-SUMIFS(DB_Complessivo!$E:$E,DB_Complessivo!$A:$A,"ACT",DB_Complessivo!$B:$B,F$2,DB_Complessivo!$H:$H,$A6)/1000 -> 119.21726 | G6: =-SUMIFS(DB_Complessivo!$E:$E,DB_Complessivo!$A:$A,"ACT",DB_Complessivo!$B:$B,G$2,DB_Complessivo!$H:$H,$A6)/1000 -> 160.7944 | H6: =-SUMIFS(DB_Complessivo!$E:$E,DB_Complessivo!$A:$A,"ACT",DB_Complessivo!$B:$B,H$2,DB_Complessivo!$H:$H,$A6)/1000 -> 179.0014 | I6: =-SUMIFS(DB_Complessivo!$E:$E,DB_Complessivo!$A:$A,"ACT",DB_Complessivo!$B:$B,I$2,DB_Complessivo!$H:$H,$A6)/1000 -> 593.21178 | J6: =-SUMIFS(DB_Complessivo!$E:$E,DB_Complessivo!$A:$A,"ACT",DB_Complessivo!$B:$B,J$2,DB_Complessivo!$H:$H,$A6)/1000 -> 0 | K6: =-SUMIFS(DB_Complessivo!$E:$E,DB_Complessivo!$A:$A,"ACT",DB_Complessivo!$B:$B,K$2,DB_Complessivo!$H:$H,$A6)/1000 -> 0 | ... O6: =-SUMIFS(DB_Complessivo!$E:$E,DB_Complessivo!$A:$A,"ACT",DB_Complessivo!$B:$B,O$2,DB_Complessivo!$H:$H,$A6)/1000 -> 0 | P6: =+H6/5 -> 35.80028 | Q6: =+I6-H6 -> 414.21038 | R6: =+Q6-P6 -> 378.4101
A7: SUBTOTALE | C7: Ricavi | D7: =SUM(D3:D6) -> 589.29952 | E7: =SUM(E3:E6) -> 1106.5205 | F7: =SUM(F3:F6) -> 1739.5661 | G7: =SUM(G3:G6) -> 2465.7451 | H7: =SUM(H3:H6) -> 3154.6524 | I7: =SUM(I3:I6) -> 3842.6868 | J7: =SUM(J3:J6) -> 0 | K7: =SUM(K3:K6) -> 0 | ... O7: =SUM(O3:O6) -> 0 | P7: =+H7/5 -> 630.93049 | Q7: =+I7-H7 -> 688.03433 | R7: =+Q7-P7 -> 57.10384
A8: ACQDI | C8: Acquisti diretti di produzione | D8: =-SUMIFS(DB_Complessivo!$E:$E,DB_Complessivo!$A:$A,"ACT",DB_Complessivo!$B:$B,D$2,DB_Complessivo!$H:$H,$A8)/1000 -> -39.73812 | E8: =-SUMIFS(DB_Complessivo!$E:$E,DB_Complessivo!$A:$A,"ACT",DB_Complessivo!$B:$B,E$2,DB_Complessivo!$H:$H,$A8)/1000 -> -78.00929 | F8: =-SUMIFS(DB_Complessivo!$E:$E,DB_Complessivo!$A:$A,"ACT",DB_Complessivo!$B:$B,F$2,DB_Complessivo!$H:$H,$A8)/1000 -> -111.32941 | G8: =-SUMIFS(DB_Complessivo!$E:$E,DB_Complessivo!$A:$A,"ACT",DB_Complessivo!$B:$B,G$2,DB_Complessivo!$H:$H,$A8)/1000 -> -165.66581 | H8: =-SUMIFS(DB_Complessivo!$E:$E,DB_Complessivo!$A:$A,"ACT",DB_Complessivo!$B:$B,H$2,DB_Complessivo!$H:$H,$A8)/1000 -> -230.9614 | I8: =-SUMIFS(DB_Complessivo!$E:$E,DB_Complessivo!$A:$A,"ACT",DB_Complessivo!$B:$B,I$2,DB_Complessivo!$H:$H,$A8)/1000 -> -313.83995 | J8: =-SUMIFS(DB_Complessivo!$E:$E,DB_Complessivo!$A:$A,"ACT",DB_Complessivo!$B:$B,J$2,DB_Complessivo!$H:$H,$A8)/1000 -> 0 | K8: =-SUMIFS(DB_Complessivo!$E:$E,DB_Complessivo!$A:$A,"ACT",DB_Complessivo!$B:$B,K$2,DB_Complessivo!$H:$H,$A8)/1000 -> 0 | ... O8: =-SUMIFS(DB_Complessivo!$E:$E,DB_Complessivo!$A:$A,"ACT",DB_Complessivo!$B:$B,O$2,DB_Complessivo!$H:$H,$A8)/1000 -> 0 | P8: =+H8/5 -> -46.19228 | Q8: =+I8-H8 -> -82.87855 | R8: =+Q8-P8 -> -36.68627
A9: VARMP | C9: Variazioni magazzino MP / SL | D9: =-SUMIFS(DB_Complessivo!$E:$E,DB_Complessivo!$A:$A,"ACT",DB_Complessivo!$B:$B,D$2,DB_Complessivo!$H:$H,$A9)/1000 -> 141.30301 | E9: =-SUMIFS(DB_Complessivo!$E:$E,DB_Complessivo!$A:$A,"ACT",DB_Complessivo!$B:$B,E$2,DB_Complessivo!$H:$H,$A9)/1000 -> 141.30301 | F9: =-SUMIFS(DB_Complessivo!$E:$E,DB_Complessivo!$A:$A,"ACT",DB_Complessivo!$B:$B,F$2,DB_Complessivo!$H:$H,$A9)/1000 -> -2.69238 | G9: =-SUMIFS(DB_Complessivo!$E:$E,DB_Complessivo!$A:$A,"ACT",DB_Complessivo!$B:$B,G$2,DB_Complessivo!$H:$H,$A9)/1000 -> 0.02773 | H9: =-SUMIFS(DB_Complessivo!$E:$E,DB_Complessivo!$A:$A,"ACT",DB_Complessivo!$B:$B,H$2,DB_Complessivo!$H:$H,$A9)/1000 -> -49.94251 | I9: =-SUMIFS(DB_Complessivo!$E:$E,DB_Complessivo!$A:$A,"ACT",DB_Complessivo!$B:$B,I$2,DB_Complessivo!$H:$H,$A9)/1000 -> -51.59331 | J9: =-SUMIFS(DB_Complessivo!$E:$E,DB_Complessivo!$A:$A,"ACT",DB_Complessivo!$B:$B,J$2,DB_Complessivo!$H:$H,$A9)/1000 -> 0 | K9: =-SUMIFS(DB_Complessivo!$E:$E,DB_Complessivo!$A:$A,"ACT",DB_Complessivo!$B:$B,K$2,DB_Complessivo!$H:$H,$A9)/1000 -> 0 | ... O9: =-SUMIFS(DB_Complessivo!$E:$E,DB_Complessivo!$A:$A,"ACT",DB_Complessivo!$B:$B,O$2,DB_Complessivo!$H:$H,$A9)/1000 -> 0 | P9: =+H9/5 -> -9.988502 | Q9: =+I9-H9 -> -1.6508 | R9: =+Q9-P9 -> 8.337702
A10: SERDI | C10: Lavorazioni esterne | D10: =-SUMIFS(DB_Complessivo!$E:$E,DB_Complessivo!$A:$A,"ACT",DB_Complessivo!$B:$B,D$2,DB_Complessivo!$H:$H,$A10)/1000 -> -79.86552 | E10: =-SUMIFS(DB_Complessivo!$E:$E,DB_Complessivo!$A:$A,"ACT",DB_Complessivo!$B:$B,E$2,DB_Complessivo!$H:$H,$A10)/1000 -> -139.63166 | F10: =-SUMIFS(DB_Complessivo!$E:$E,DB_Complessivo!$A:$A,"ACT",DB_Complessivo!$B:$B,F$2,DB_Complessivo!$H:$H,$A10)/1000 -> -218.26396 | G10: =-SUMIFS(DB_Complessivo!$E:$E,DB_Complessivo!$A:$A,"ACT",DB_Complessivo!$B:$B,G$2,DB_Complessivo!$H:$H,$A10)/1000 -> -334.7308 | H10: =-SUMIFS(DB_Complessivo!$E:$E,DB_Complessivo!$A:$A,"ACT",DB_Complessivo!$B:$B,H$2,DB_Complessivo!$H:$H,$A10)/1000 -> -460.37053 | I10: =-SUMIFS(DB_Complessivo!$E:$E,DB_Complessivo!$A:$A,"ACT",DB_Complessivo!$B:$B,I$2,DB_Complessivo!$H:$H,$A10)/1000 -> -519.22252 | J10: =-SUMIFS(DB_Complessivo!$E:$E,DB_Complessivo!$A:$A,"ACT",DB_Complessivo!$B:$B,J$2,DB_Complessivo!$H:$H,$A10)/1000 -> 0 | K10: =-SUMIFS(DB_Complessivo!$E:$E,DB_Complessivo!$A:$A,"ACT",DB_Complessivo!$B:$B,K$2,DB_Complessivo!$H:$H,$A10)/1000 -> 0 | ... O10: =-SUMIFS(DB_Complessivo!$E:$E,DB_Complessivo!$A:$A,"ACT",DB_Complessivo!$B:$B,O$2,DB_Complessivo!$H:$H,$A10)/1000 -> 0 | P10: =+H10/5 -> -92.074106 | Q10: =+I10-H10 -> -58.85199 | R10: =+Q10-P10 -> 33.222116
A11: PERDI | C11: Manodopera diretta di produzione | D11: =-SUMIFS(DB_Complessivo!$E:$E,DB_Complessivo!$A:$A,"ACT",DB_Complessivo!$B:$B,D$2,DB_Complessivo!$H:$H,$A11)/1000 -> -129.28997 | E11: =-SUMIFS(DB_Complessivo!$E:$E,DB_Complessivo!$A:$A,"ACT",DB_Complessivo!$B:$B,E$2,DB_Complessivo!$H:$H,$A11)/1000 -> -258.90931 | F11: =-SUMIFS(DB_Complessivo!$E:$E,DB_Complessivo!$A:$A,"ACT",DB_Complessivo!$B:$B,F$2,DB_Complessivo!$H:$H,$A11)/1000 -> -383.87769 | G11: =-SUMIFS(DB_Complessivo!$E:$E,DB_Complessivo!$A:$A,"ACT",DB_Complessivo!$B:$B,G$2,DB_Complessivo!$H:$H,$A11)/1000 -> -520.59371 | H11: =-SUMIFS(DB_Complessivo!$E:$E,DB_Complessivo!$A:$A,"ACT",DB_Complessivo!$B:$B,H$2,DB_Complessivo!$H:$H,$A11)/1000 -> -657.12778 | I11: =-SUMIFS(DB_Complessivo!$E:$E,DB_Complessivo!$A:$A,"ACT",DB_Complessivo!$B:$B,I$2,DB_Complessivo!$H:$H,$A11)/1000 -> -780.02684 | J11: =-SUMIFS(DB_Complessivo!$E:$E,DB_Complessivo!$A:$A,"ACT",DB_Complessivo!$B:$B,J$2,DB_Complessivo!$H:$H,$A11)/1000 -> 0 | K11: =-SUMIFS(DB_Complessivo!$E:$E,DB_Complessivo!$A:$A,"ACT",DB_Complessivo!$B:$B,K$2,DB_Complessivo!$H:$H,$A11)/1000 -> 0 | ... O11: =-SUMIFS(DB_Complessivo!$E:$E,DB_Complessivo!$A:$A,"ACT",DB_Complessivo!$B:$B,O$2,DB_Complessivo!$H:$H,$A11)/1000 -> 0 | P11: =+H11/5 -> -131.42556 | Q11: =+I11-H11 -> -122.89906 | R11: =+Q11-P11 -> 8.5264952
A12: SUBTOTALE | C12: Totale costi diretti di produzione | D12: =SUM(D7:D11) -> 481.70892 | E12: =SUM(E7:E11) -> 771.27322 | F12: =SUM(F7:F11) -> 1023.4027 | G12: =SUM(G7:G11) -> 1444.7825 | H12: =SUM(H7:H11) -> 1756.2502 | I12: =SUM(I7:I11) -> 2178.0042 | J12: =SUM(J7:J11) -> 0 | K12: =SUM(K7:K11) -> 0 | ... O12: =SUM(O7:O11) -> 0 | P12: =+H12/5 -> 351.25005 | Q12: =+I12-H12 -> 421.75393 | R12: =+Q12-P12 -> 70.503883
A13: SUBTOTALE | C13: Margine diretto di produzione | D13: =IFERROR(D12/D$7,"") -> 0.81742629 | E13: =IFERROR(E12/E$7,"") -> 0.69702571 | F13: =IFERROR(F12/F$7,"") -> 0.58830916 | G13: =IFERROR(G12/G$7,"") -> 0.58594155 | H13: =IFERROR(H12/H$7,"") -> 0.5567175 | I13: =IFERROR(I12/I$7,"") -> 0.56679201 | J13: =IFERROR(J12/J$7,"") | K13: =IFERROR(K12/K$7,"") | ... O13: =IFERROR(O12/O$7,"") | P13: =+H13/5 -> 0.1113435 | Q13: =+I13-H13 -> 0.010074507 | R13: =+Q13-P13 -> -0.10126899
A14: ACQIN | C14: Acquisti indiretti di fabbrica | D14: =-SUMIFS(DB_Complessivo!$E:$E,DB_Complessivo!$A:$A,"ACT",DB_Complessivo!$B:$B,D$2,DB_Complessivo!$H:$H,$A14)/1000 -> -3.56428 | E14: =-SUMIFS(DB_Complessivo!$E:$E,DB_Complessivo!$A:$A,"ACT",DB_Complessivo!$B:$B,E$2,DB_Complessivo!$H:$H,$A14)/1000 -> -4.37732 | F14: =-SUMIFS(DB_Complessivo!$E:$E,DB_Complessivo!$A:$A,"ACT",DB_Complessivo!$B:$B,F$2,DB_Complessivo!$H:$H,$A14)/1000 -> -6.6156 | G14: =-SUMIFS(DB_Complessivo!$E:$E,DB_Complessivo!$A:$A,"ACT",DB_Complessivo!$B:$B,G$2,DB_Complessivo!$H:$H,$A14)/1000 -> -8.05259 | H14: =-SUMIFS(DB_Complessivo!$E:$E,DB_Complessivo!$A:$A,"ACT",DB_Complessivo!$B:$B,H$2,DB_Complessivo!$H:$H,$A14)/1000 -> -8.08431 | I14: =-SUMIFS(DB_Complessivo!$E:$E,DB_Complessivo!$A:$A,"ACT",DB_Complessivo!$B:$B,I$2,DB_Complessivo!$H:$H,$A14)/1000 -> -9.83135 | J14: =-SUMIFS(DB_Complessivo!$E:$E,DB_Complessivo!$A:$A,"ACT",DB_Complessivo!$B:$B,J$2,DB_Complessivo!$H:$H,$A14)/1000 -> 0 | K14: =-SUMIFS(DB_Complessivo!$E:$E,DB_Complessivo!$A:$A,"ACT",DB_Complessivo!$B:$B,K$2,DB_Complessivo!$H:$H,$A14)/1000 -> 0 | ... O14: =-SUMIFS(DB_Complessivo!$E:$E,DB_Complessivo!$A:$A,"ACT",DB_Complessivo!$B:$B,O$2,DB_Complessivo!$H:$H,$A14)/1000 -> 0 | P14: =+H14/5 -> -1.616862 | Q14: =+I14-H14 -> -1.74704 | R14: =+Q14-P14 -> -0.130178
A15: PERIM | C15: Costi del personale diretto improduttivo | D15: =-SUMIFS(DB_Complessivo!$E:$E,DB_Complessivo!$A:$A,"ACT",DB_Complessivo!$B:$B,D$2,DB_Complessivo!$H:$H,$A15)/1000 -> -55.409988 | E15: =-SUMIFS(DB_Complessivo!$E:$E,DB_Complessivo!$A:$A,"ACT",DB_Complessivo!$B:$B,E$2,DB_Complessivo!$H:$H,$A15)/1000 -> -110.96113 | F15: =-SUMIFS(DB_Complessivo!$E:$E,DB_Complessivo!$A:$A,"ACT",DB_Complessivo!$B:$B,F$2,DB_Complessivo!$H:$H,$A15)/1000 -> -164.51901 | G15: =-SUMIFS(DB_Complessivo!$E:$E,DB_Complessivo!$A:$A,"ACT",DB_Complessivo!$B:$B,G$2,DB_Complessivo!$H:$H,$A15)/1000 -> -223.11159 | H15: =-SUMIFS(DB_Complessivo!$E:$E,DB_Complessivo!$A:$A,"ACT",DB_Complessivo!$B:$B,H$2,DB_Complessivo!$H:$H,$A15)/1000 -> -281.62619 | I15: =-SUMIFS(DB_Complessivo!$E:$E,DB_Complessivo!$A:$A,"ACT",DB_Complessivo!$B:$B,I$2,DB_Complessivo!$H:$H,$A15)/1000 -> -334.29722 | J15: =-SUMIFS(DB_Complessivo!$E:$E,DB_Complessivo!$A:$A,"ACT",DB_Complessivo!$B:$B,J$2,DB_Complessivo!$H:$H,$A15)/1000 -> 0 | K15: =-SUMIFS(DB_Complessivo!$E:$E,DB_Complessivo!$A:$A,"ACT",DB_Complessivo!$B:$B,K$2,DB_Complessivo!$H:$H,$A15)/1000 -> 0 | ... O15: =-SUMIFS(DB_Complessivo!$E:$E,DB_Complessivo!$A:$A,"ACT",DB_Complessivo!$B:$B,O$2,DB_Complessivo!$H:$H,$A15)/1000 -> 0 | P15: =+H15/5 -> -56.325239 | Q15: =+I15-H15 -> -52.671026 | R15: =+Q15-P15 -> 3.6542122
A16: PERIN | C16: Costi del Personale indiretto di fabbrica | D16: =-SUMIFS(DB_Complessivo!$E:$E,DB_Complessivo!$A:$A,"ACT",DB_Complessivo!$B:$B,D$2,DB_Complessivo!$H:$H,$A16)/1000 -> -59.855184 | E16: =-SUMIFS(DB_Complessivo!$E:$E,DB_Complessivo!$A:$A,"ACT",DB_Complessivo!$B:$B,E$2,DB_Complessivo!$H:$H,$A16)/1000 -> -118.28812 | F16: =-SUMIFS(DB_Complessivo!$E:$E,DB_Complessivo!$A:$A,"ACT",DB_Complessivo!$B:$B,F$2,DB_Complessivo!$H:$H,$A16)/1000 -> -210.00672 | G16: =-SUMIFS(DB_Complessivo!$E:$E,DB_Complessivo!$A:$A,"ACT",DB_Complessivo!$B:$B,G$2,DB_Complessivo!$H:$H,$A16)/1000 -> -423.60559 | H16: =-SUMIFS(DB_Complessivo!$E:$E,DB_Complessivo!$A:$A,"ACT",DB_Complessivo!$B:$B,H$2,DB_Complessivo!$H:$H,$A16)/1000 -> -342.88135 | I16: =-SUMIFS(DB_Complessivo!$E:$E,DB_Complessivo!$A:$A,"ACT",DB_Complessivo!$B:$B,I$2,DB_Complessivo!$H:$H,$A16)/1000 -> -406.57358 | J16: =-SUMIFS(DB_Complessivo!$E:$E,DB_Complessivo!$A:$A,"ACT",DB_Complessivo!$B:$B,J$2,DB_Complessivo!$H:$H,$A16)/1000 -> 0 | K16: =-SUMIFS(DB_Complessivo!$E:$E,DB_Complessivo!$A:$A,"ACT",DB_Complessivo!$B:$B,K$2,DB_Complessivo!$H:$H,$A16)/1000 -> 0 | ... O16: =-SUMIFS(DB_Complessivo!$E:$E,DB_Complessivo!$A:$A,"ACT",DB_Complessivo!$B:$B,O$2,DB_Complessivo!$H:$H,$A16)/1000 -> 0 | P16: =+H16/5 -> -68.576271 | Q16: =+I16-H16 -> -63.692227 | R16: =+Q16-P16 -> 4.8840441
A17: SERIN | C17: Servizi indiretti di fabbrica | D17: =-SUMIFS(DB_Complessivo!$E:$E,DB_Complessivo!$A:$A,"ACT",DB_Complessivo!$B:$B,D$2,DB_Complessivo!$H:$H,$A17)/1000 -> -12.6146 | E17: =-SUMIFS(DB_Complessivo!$E:$E,DB_Complessivo!$A:$A,"ACT",DB_Complessivo!$B:$B,E$2,DB_Complessivo!$H:$H,$A17)/1000 -> -28.43427 | F17: =-SUMIFS(DB_Complessivo!$E:$E,DB_Complessivo!$A:$A,"ACT",DB_Complessivo!$B:$B,F$2,DB_Complessivo!$H:$H,$A17)/1000 -> -37.23609 | G17: =-SUMIFS(DB_Complessivo!$E:$E,DB_Complessivo!$A:$A,"ACT",DB_Complessivo!$B:$B,G$2,DB_Complessivo!$H:$H,$A17)/1000 -> -48.34769 | H17: =-SUMIFS(DB_Complessivo!$E:$E,DB_Complessivo!$A:$A,"ACT",DB_Complessivo!$B:$B,H$2,DB_Complessivo!$H:$H,$A17)/1000 -> -71.03972 | I17: =-SUMIFS(DB_Complessivo!$E:$E,DB_Complessivo!$A:$A,"ACT",DB_Complessivo!$B:$B,I$2,DB_Complessivo!$H:$H,$A17)/1000 -> -96.76461 | J17: =-SUMIFS(DB_Complessivo!$E:$E,DB_Complessivo!$A:$A,"ACT",DB_Complessivo!$B:$B,J$2,DB_Complessivo!$H:$H,$A17)/1000 -> 0 | K17: =-SUMIFS(DB_Complessivo!$E:$E,DB_Complessivo!$A:$A,"ACT",DB_Complessivo!$B:$B,K$2,DB_Complessivo!$H:$H,$A17)/1000 -> 0 | ... O17: =-SUMIFS(DB_Complessivo!$E:$E,DB_Complessivo!$A:$A,"ACT",DB_Complessivo!$B:$B,O$2,DB_Complessivo!$H:$H,$A17)/1000 -> 0 | P17: =+H17/5 -> -14.207944 | Q17: =+I17-H17 -> -25.72489 | R17: =+Q17-P17 -> -11.516946
A18: AMMIN | C18: Ammortamenti indiretti di fabbrica | D18: =-SUMIFS(DB_Complessivo!$E:$E,DB_Complessivo!$A:$A,"ACT",DB_Complessivo!$B:$B,D$2,DB_Complessivo!$H:$H,$A18)/1000 -> -7.18826 | E18: =-SUMIFS(DB_Complessivo!$E:$E,DB_Complessivo!$A:$A,"ACT",DB_Complessivo!$B:$B,E$2,DB_Complessivo!$H:$H,$A18)/1000 -> -14.37652 | F18: =-SUMIFS(DB_Complessivo!$E:$E,DB_Complessivo!$A:$A,"ACT",DB_Complessivo!$B:$B,F$2,DB_Complessivo!$H:$H,$A18)/1000 -> -21.96351 | G18: =-SUMIFS(DB_Complessivo!$E:$E,DB_Complessivo!$A:$A,"ACT",DB_Complessivo!$B:$B,G$2,DB_Complessivo!$H:$H,$A18)/1000 -> -29.28468 | H18: =-SUMIFS(DB_Complessivo!$E:$E,DB_Complessivo!$A:$A,"ACT",DB_Complessivo!$B:$B,H$2,DB_Complessivo!$H:$H,$A18)/1000 -> -36.60585 | I18: =-SUMIFS(DB_Complessivo!$E:$E,DB_Complessivo!$A:$A,"ACT",DB_Complessivo!$B:$B,I$2,DB_Complessivo!$H:$H,$A18)/1000 -> -43.92693 | J18: =-SUMIFS(DB_Complessivo!$E:$E,DB_Complessivo!$A:$A,"ACT",DB_Complessivo!$B:$B,J$2,DB_Complessivo!$H:$H,$A18)/1000 -> 0 | K18: =-SUMIFS(DB_Complessivo!$E:$E,DB_Complessivo!$A:$A,"ACT",DB_Complessivo!$B:$B,K$2,DB_Complessivo!$H:$H,$A18)/1000 -> 0 | ... O18: =-SUMIFS(DB_Complessivo!$E:$E,DB_Complessivo!$A:$A,"ACT",DB_Complessivo!$B:$B,O$2,DB_Complessivo!$H:$H,$A18)/1000 -> 0 | P18: =+H18/5 -> -7.32117 | Q18: =+I18-H18 -> -7.32108 | R18: =+Q18-P18 -> 9e-05
A19: SUBTOTALE | C19: Totale costi indiretti di fabbrica | D19: =SUM(D12,D14:D18) -> 343.07661 | E19: =SUM(E12,E14:E18) -> 494.83586 | F19: =SUM(F12,F14:F18) -> 583.06175 | G19: =SUM(G12,G14:G18) -> 712.38035 | H19: =SUM(H12,H14:H18) -> 1016.0128 | I19: =SUM(I12,I14:I18) -> 1286.6105 | J19: =SUM(J12,J14:J18) -> 0 | K19: =SUM(K12,K14:K18) -> 0 | ... O19: =SUM(O12,O14:O18) -> 0 | P19: =+H19/5 -> 203.20256 | Q19: =+I19-H19 -> 270.59767 | R19: =+Q19-P19 -> 67.395106
A20: SUBTOTALE | C20: Margine indiretto di fabbrica | D20: =IFERROR(D19/D$7,"") -> 0.58217697 | E20: =IFERROR(E19/E$7,"") -> 0.44719991 | F20: =IFERROR(F19/F$7,"") -> 0.33517654 | G20: =IFERROR(G19/G$7,"") -> 0.28891079 | H20: =IFERROR(H19/H$7,"") -> 0.32206806 | I20: =IFERROR(I19/I$7,"") -> 0.33482054 | J20: =IFERROR(J19/J$7,"") | K20: =IFERROR(K19/K$7,"") | ... O20: =IFERROR(O19/O$7,"") | P20: =+H20/5 -> 0.064413612 | Q20: =+I20-H20 -> 0.012752479 | R20: =+Q20-P20 -> -0.051661133
A21: PERST | C21: Costi del personale di struttura | D21: =-SUMIFS(DB_Complessivo!$E:$E,DB_Complessivo!$A:$A,"ACT",DB_Complessivo!$B:$B,D$2,DB_Complessivo!$H:$H,$A21)/1000 -> -121.85699 | E21: =-SUMIFS(DB_Complessivo!$E:$E,DB_Complessivo!$A:$A,"ACT",DB_Complessivo!$B:$B,E$2,DB_Complessivo!$H:$H,$A21)/1000 -> -234.11656 | F21: =-SUMIFS(DB_Complessivo!$E:$E,DB_Complessivo!$A:$A,"ACT",DB_Complessivo!$B:$B,F$2,DB_Complessivo!$H:$H,$A21)/1000 -> -312.41913 | G21: =-SUMIFS(DB_Complessivo!$E:$E,DB_Complessivo!$A:$A,"ACT",DB_Complessivo!$B:$B,G$2,DB_Complessivo!$H:$H,$A21)/1000 -> -284.04739 | H21: =-SUMIFS(DB_Complessivo!$E:$E,DB_Complessivo!$A:$A,"ACT",DB_Complessivo!$B:$B,H$2,DB_Complessivo!$H:$H,$A21)/1000 -> -415.49291 | I21: =-SUMIFS(DB_Complessivo!$E:$E,DB_Complessivo!$A:$A,"ACT",DB_Complessivo!$B:$B,I$2,DB_Complessivo!$H:$H,$A21)/1000 -> -630.26133 | J21: =-SUMIFS(DB_Complessivo!$E:$E,DB_Complessivo!$A:$A,"ACT",DB_Complessivo!$B:$B,J$2,DB_Complessivo!$H:$H,$A21)/1000 -> 0 | K21: =-SUMIFS(DB_Complessivo!$E:$E,DB_Complessivo!$A:$A,"ACT",DB_Complessivo!$B:$B,K$2,DB_Complessivo!$H:$H,$A21)/1000 -> 0 | ... O21: =-SUMIFS(DB_Complessivo!$E:$E,DB_Complessivo!$A:$A,"ACT",DB_Complessivo!$B:$B,O$2,DB_Complessivo!$H:$H,$A21)/1000 -> 0 | P21: =+H21/5 -> -83.098581 | Q21: =+I21-H21 -> -214.76843 | R21: =+Q21-P21 -> -131.66984
A22: SERST | C22: Servizi di struttura | D22: =-SUMIFS(DB_Complessivo!$E:$E,DB_Complessivo!$A:$A,"ACT",DB_Complessivo!$B:$B,D$2,DB_Complessivo!$H:$H,$A22)/1000 -> -44.99773 | E22: =-SUMIFS(DB_Complessivo!$E:$E,DB_Complessivo!$A:$A,"ACT",DB_Complessivo!$B:$B,E$2,DB_Complessivo!$H:$H,$A22)/1000 -> -86.62874 | F22: =-SUMIFS(DB_Complessivo!$E:$E,DB_Complessivo!$A:$A,"ACT",DB_Complessivo!$B:$B,F$2,DB_Complessivo!$H:$H,$A22)/1000 -> -150.84994 | G22: =-SUMIFS(DB_Complessivo!$E:$E,DB_Complessivo!$A:$A,"ACT",DB_Complessivo!$B:$B,G$2,DB_Complessivo!$H:$H,$A22)/1000 -> -253.60356 | H22: =-SUMIFS(DB_Complessivo!$E:$E,DB_Complessivo!$A:$A,"ACT",DB_Complessivo!$B:$B,H$2,DB_Complessivo!$H:$H,$A22)/1000 -> -258.94823 | I22: =-SUMIFS(DB_Complessivo!$E:$E,DB_Complessivo!$A:$A,"ACT",DB_Complessivo!$B:$B,I$2,DB_Complessivo!$H:$H,$A22)/1000 -> -385.23776 | J22: =-SUMIFS(DB_Complessivo!$E:$E,DB_Complessivo!$A:$A,"ACT",DB_Complessivo!$B:$B,J$2,DB_Complessivo!$H:$H,$A22)/1000 -> 0 | K22: =-SUMIFS(DB_Complessivo!$E:$E,DB_Complessivo!$A:$A,"ACT",DB_Complessivo!$B:$B,K$2,DB_Complessivo!$H:$H,$A22)/1000 -> 0 | ... O22: =-SUMIFS(DB_Complessivo!$E:$E,DB_Complessivo!$A:$A,"ACT",DB_Complessivo!$B:$B,O$2,DB_Complessivo!$H:$H,$A22)/1000 -> 0 | P22: =+H22/5 -> -51.789646 | Q22: =+I22-H22 -> -126.28953 | R22: =+Q22-P22 -> -74.499884
A23: AFFIT | C23: Affitti | D23: =-SUMIFS(DB_Complessivo!$E:$E,DB_Complessivo!$A:$A,"ACT",DB_Complessivo!$B:$B,D$2,DB_Complessivo!$H:$H,$A23)/1000 -> -4.6209 | E23: =-SUMIFS(DB_Complessivo!$E:$E,DB_Complessivo!$A:$A,"ACT",DB_Complessivo!$B:$B,E$2,DB_Complessivo!$H:$H,$A23)/1000 -> -7.4918 | F23: =-SUMIFS(DB_Complessivo!$E:$E,DB_Complessivo!$A:$A,"ACT",DB_Complessivo!$B:$B,F$2,DB_Complessivo!$H:$H,$A23)/1000 -> -17.6127 | G23: =-SUMIFS(DB_Complessivo!$E:$E,DB_Complessivo!$A:$A,"ACT",DB_Complessivo!$B:$B,G$2,DB_Complessivo!$H:$H,$A23)/1000 -> -24.6336 | H23: =-SUMIFS(DB_Complessivo!$E:$E,DB_Complessivo!$A:$A,"ACT",DB_Complessivo!$B:$B,H$2,DB_Complessivo!$H:$H,$A23)/1000 -> -32.8545 | I23: =-SUMIFS(DB_Complessivo!$E:$E,DB_Complessivo!$A:$A,"ACT",DB_Complessivo!$B:$B,I$2,DB_Complessivo!$H:$H,$A23)/1000 -> -46.5754 | J23: =-SUMIFS(DB_Complessivo!$E:$E,DB_Complessivo!$A:$A,"ACT",DB_Complessivo!$B:$B,J$2,DB_Complessivo!$H:$H,$A23)/1000 -> 0 | K23: =-SUMIFS(DB_Complessivo!$E:$E,DB_Complessivo!$A:$A,"ACT",DB_Complessivo!$B:$B,K$2,DB_Complessivo!$H:$H,$A23)/1000 -> 0 | ... O23: =-SUMIFS(DB_Complessivo!$E:$E,DB_Complessivo!$A:$A,"ACT",DB_Complessivo!$B:$B,O$2,DB_Complessivo!$H:$H,$A23)/1000 -> 0 | P23: =+H23/5 -> -6.5709 | Q23: =+I23-H23 -> -13.7209 | R23: =+Q23-P23 -> -7.15
A24: COSGS | C24: Costi generali di struttura | D24: =-SUMIFS(DB_Complessivo!$E:$E,DB_Complessivo!$A:$A,"ACT",DB_Complessivo!$B:$B,D$2,DB_Complessivo!$H:$H,$A24)/1000 -> -28.64946 | E24: =-SUMIFS(DB_Complessivo!$E:$E,DB_Complessivo!$A:$A,"ACT",DB_Complessivo!$B:$B,E$2,DB_Complessivo!$H:$H,$A24)/1000 -> -52.22292 | F24: =-SUMIFS(DB_Complessivo!$E:$E,DB_Complessivo!$A:$A,"ACT",DB_Complessivo!$B:$B,F$2,DB_Complessivo!$H:$H,$A24)/1000 -> -70.00877 | G24: =-SUMIFS(DB_Complessivo!$E:$E,DB_Complessivo!$A:$A,"ACT",DB_Complessivo!$B:$B,G$2,DB_Complessivo!$H:$H,$A24)/1000 -> -95.60835 | H24: =-SUMIFS(DB_Complessivo!$E:$E,DB_Complessivo!$A:$A,"ACT",DB_Complessivo!$B:$B,H$2,DB_Complessivo!$H:$H,$A24)/1000 -> -116.26548 | I24: =-SUMIFS(DB_Complessivo!$E:$E,DB_Complessivo!$A:$A,"ACT",DB_Complessivo!$B:$B,I$2,DB_Complessivo!$H:$H,$A24)/1000 -> -174.7357 | J24: =-SUMIFS(DB_Complessivo!$E:$E,DB_Complessivo!$A:$A,"ACT",DB_Complessivo!$B:$B,J$2,DB_Complessivo!$H:$H,$A24)/1000 -> 0 | K24: =-SUMIFS(DB_Complessivo!$E:$E,DB_Complessivo!$A:$A,"ACT",DB_Complessivo!$B:$B,K$2,DB_Complessivo!$H:$H,$A24)/1000 -> 0 | ... O24: =-SUMIFS(DB_Complessivo!$E:$E,DB_Complessivo!$A:$A,"ACT",DB_Complessivo!$B:$B,O$2,DB_Complessivo!$H:$H,$A24)/1000 -> 0 | P24: =+H24/5 -> -23.253096 | Q24: =+I24-H24 -> -58.470223 | R24: =+Q24-P24 -> -35.217127
A25: AMMST | C25: Ammortamenti di struttura | D25: =-SUMIFS(DB_Complessivo!$E:$E,DB_Complessivo!$A:$A,"ACT",DB_Complessivo!$B:$B,D$2,DB_Complessivo!$H:$H,$A25)/1000 -> -3.76901 | E25: =-SUMIFS(DB_Complessivo!$E:$E,DB_Complessivo!$A:$A,"ACT",DB_Complessivo!$B:$B,E$2,DB_Complessivo!$H:$H,$A25)/1000 -> -7.53802 | F25: =-SUMIFS(DB_Complessivo!$E:$E,DB_Complessivo!$A:$A,"ACT",DB_Complessivo!$B:$B,F$2,DB_Complessivo!$H:$H,$A25)/1000 -> -11.64276 | G25: =-SUMIFS(DB_Complessivo!$E:$E,DB_Complessivo!$A:$A,"ACT",DB_Complessivo!$B:$B,G$2,DB_Complessivo!$H:$H,$A25)/1000 -> -15.52368 | H25: =-SUMIFS(DB_Complessivo!$E:$E,DB_Complessivo!$A:$A,"ACT",DB_Complessivo!$B:$B,H$2,DB_Complessivo!$H:$H,$A25)/1000 -> -19.4046 | I25: =-SUMIFS(DB_Complessivo!$E:$E,DB_Complessivo!$A:$A,"ACT",DB_Complessivo!$B:$B,I$2,DB_Complessivo!$H:$H,$A25)/1000 -> -23.28552 | J25: =-SUMIFS(DB_Complessivo!$E:$E,DB_Complessivo!$A:$A,"ACT",DB_Complessivo!$B:$B,J$2,DB_Complessivo!$H:$H,$A25)/1000 -> 0 | K25: =-SUMIFS(DB_Complessivo!$E:$E,DB_Complessivo!$A:$A,"ACT",DB_Complessivo!$B:$B,K$2,DB_Complessivo!$H:$H,$A25)/1000 -> 0 | ... O25: =-SUMIFS(DB_Complessivo!$E:$E,DB_Complessivo!$A:$A,"ACT",DB_Complessivo!$B:$B,O$2,DB_Complessivo!$H:$H,$A25)/1000 -> 0 | P25: =+H25/5 -> -3.88092 | Q25: =+I25-H25 -> -3.88092 | R25: =+Q25-P25 -> 0
A26: ACC | C26: Accantonamenti | D26: =-SUMIFS(DB_Complessivo!$E:$E,DB_Complessivo!$A:$A,"ACT",DB_Complessivo!$B:$B,D$2,DB_Complessivo!$H:$H,$A26)/1000 -> 0 | E26: =-SUMIFS(DB_Complessivo!$E:$E,DB_Complessivo!$A:$A,"ACT",DB_Complessivo!$B:$B,E$2,DB_Complessivo!$H:$H,$A26)/1000 -> 0 | F26: =-SUMIFS(DB_Complessivo!$E:$E,DB_Complessivo!$A:$A,"ACT",DB_Complessivo!$B:$B,F$2,DB_Complessivo!$H:$H,$A26)/1000 -> 0 | G26: =-SUMIFS(DB_Complessivo!$E:$E,DB_Complessivo!$A:$A,"ACT",DB_Complessivo!$B:$B,G$2,DB_Complessivo!$H:$H,$A26)/1000 -> 0 | H26: =-SUMIFS(DB_Complessivo!$E:$E,DB_Complessivo!$A:$A,"ACT",DB_Complessivo!$B:$B,H$2,DB_Complessivo!$H:$H,$A26)/1000 -> 0 | I26: =-SUMIFS(DB_Complessivo!$E:$E,DB_Complessivo!$A:$A,"ACT",DB_Complessivo!$B:$B,I$2,DB_Complessivo!$H:$H,$A26)/1000 -> 0 | J26: =-SUMIFS(DB_Complessivo!$E:$E,DB_Complessivo!$A:$A,"ACT",DB_Complessivo!$B:$B,J$2,DB_Complessivo!$H:$H,$A26)/1000 -> 0 | K26: =-SUMIFS(DB_Complessivo!$E:$E,DB_Complessivo!$A:$A,"ACT",DB_Complessivo!$B:$B,K$2,DB_Complessivo!$H:$H,$A26)/1000 -> 0 | ... O26: =-SUMIFS(DB_Complessivo!$E:$E,DB_Complessivo!$A:$A,"ACT",DB_Complessivo!$B:$B,O$2,DB_Complessivo!$H:$H,$A26)/1000 -> 0 | P26: =+H26/5 -> 0 | Q26: =+I26-H26 -> 0 | R26: =+Q26-P26 -> 0
A27: SUBTOTALE | C27: Totale costi indiretti di struttura | D27: =SUM(D19,D21:D26) -> 139.18251 | E27: =SUM(E19,E21:E26) -> 106.83781 | F27: =SUM(F19,F21:F26) -> 20.528443 | G27: =SUM(G19,G21:G26) -> 38.963773 | H27: =SUM(H19,H21:H26) -> 173.04708 | I27: =SUM(I19,I21:I26) -> 26.51475 | J27: =SUM(J19,J21:J26) -> 0 | K27: =SUM(K19,K21:K26) -> 0 | ... O27: =SUM(O19,O21:O26) -> 0 | P27: =+H27/5 -> 34.609417 | Q27: =+I27-H27 -> -146.53233 | R27: =+Q27-P27 -> -181.14175
A28: SUBTOTALE | C28: EBIT | D28: =IFERROR(D27/D$7,"") -> 0.23618297 | E28: =IFERROR(E27/E$7,"") -> 0.096552948 | F28: =IFERROR(F27/F$7,"") -> 0.011800898 | G28: =IFERROR(G27/G$7,"") -> 0.015802028 | H28: =IFERROR(H27/H$7,"") -> 0.054854563 | I28: =IFERROR(I27/I$7,"") -> 0.006900055 | J28: =IFERROR(J27/J$7,"") | K28: =IFERROR(K27/K$7,"") | ... O28: =IFERROR(O27/O$7,"") | P28: =+H28/5 -> 0.010970913 | Q28: =+I28-H28 -> -0.047954508 | R28: =+Q28-P28 -> -0.058925421
A29: ONFIN | C29: Gestione Finanziaria | D29: =-SUMIFS(DB_Complessivo!$E:$E,DB_Complessivo!$A:$A,"ACT",DB_Complessivo!$B:$B,D$2,DB_Complessivo!$H:$H,$A29)/1000 -> -29.11194 | E29: =-SUMIFS(DB_Complessivo!$E:$E,DB_Complessivo!$A:$A,"ACT",DB_Complessivo!$B:$B,E$2,DB_Complessivo!$H:$H,$A29)/1000 -> -30.13937 | F29: =-SUMIFS(DB_Complessivo!$E:$E,DB_Complessivo!$A:$A,"ACT",DB_Complessivo!$B:$B,F$2,DB_Complessivo!$H:$H,$A29)/1000 -> -30.13937 | G29: =-SUMIFS(DB_Complessivo!$E:$E,DB_Complessivo!$A:$A,"ACT",DB_Complessivo!$B:$B,G$2,DB_Complessivo!$H:$H,$A29)/1000 -> -7.25147 | H29: =-SUMIFS(DB_Complessivo!$E:$E,DB_Complessivo!$A:$A,"ACT",DB_Complessivo!$B:$B,H$2,DB_Complessivo!$H:$H,$A29)/1000 -> -7.25147 | I29: =-SUMIFS(DB_Complessivo!$E:$E,DB_Complessivo!$A:$A,"ACT",DB_Complessivo!$B:$B,I$2,DB_Complessivo!$H:$H,$A29)/1000 -> 11.67779 | J29: =-SUMIFS(DB_Complessivo!$E:$E,DB_Complessivo!$A:$A,"ACT",DB_Complessivo!$B:$B,J$2,DB_Complessivo!$H:$H,$A29)/1000 -> 0 | K29: =-SUMIFS(DB_Complessivo!$E:$E,DB_Complessivo!$A:$A,"ACT",DB_Complessivo!$B:$B,K$2,DB_Complessivo!$H:$H,$A29)/1000 -> 0 | ... O29: =-SUMIFS(DB_Complessivo!$E:$E,DB_Complessivo!$A:$A,"ACT",DB_Complessivo!$B:$B,O$2,DB_Complessivo!$H:$H,$A29)/1000 -> 0 | P29: =+H29/5 -> -1.450294 | Q29: =+I29-H29 -> 18.92926 | R29: =+Q29-P29 -> 20.379554
A30: ONSTR | C30: Gestione Straordinaria e Non Core | D30: =-SUMIFS(DB_Complessivo!$E:$E,DB_Complessivo!$A:$A,"ACT",DB_Complessivo!$B:$B,D$2,DB_Complessivo!$H:$H,$A30)/1000 -> -12.29759 | E30: =-SUMIFS(DB_Complessivo!$E:$E,DB_Complessivo!$A:$A,"ACT",DB_Complessivo!$B:$B,E$2,DB_Complessivo!$H:$H,$A30)/1000 -> -17.15021 | F30: =-SUMIFS(DB_Complessivo!$E:$E,DB_Complessivo!$A:$A,"ACT",DB_Complessivo!$B:$B,F$2,DB_Complessivo!$H:$H,$A30)/1000 -> 39.06868 | G30: =-SUMIFS(DB_Complessivo!$E:$E,DB_Complessivo!$A:$A,"ACT",DB_Complessivo!$B:$B,G$2,DB_Complessivo!$H:$H,$A30)/1000 -> 61.97228 | H30: =-SUMIFS(DB_Complessivo!$E:$E,DB_Complessivo!$A:$A,"ACT",DB_Complessivo!$B:$B,H$2,DB_Complessivo!$H:$H,$A30)/1000 -> -49.87874 | I30: =-SUMIFS(DB_Complessivo!$E:$E,DB_Complessivo!$A:$A,"ACT",DB_Complessivo!$B:$B,I$2,DB_Complessivo!$H:$H,$A30)/1000 -> 37.29463 | J30: =-SUMIFS(DB_Complessivo!$E:$E,DB_Complessivo!$A:$A,"ACT",DB_Complessivo!$B:$B,J$2,DB_Complessivo!$H:$H,$A30)/1000 -> 0 | K30: =-SUMIFS(DB_Complessivo!$E:$E,DB_Complessivo!$A:$A,"ACT",DB_Complessivo!$B:$B,K$2,DB_Complessivo!$H:$H,$A30)/1000 -> 0 | ... O30: =-SUMIFS(DB_Complessivo!$E:$E,DB_Complessivo!$A:$A,"ACT",DB_Complessivo!$B:$B,O$2,DB_Complessivo!$H:$H,$A30)/1000 -> 0 | P30: =+H30/5 -> -9.975748 | Q30: =+I30-H30 -> 87.17337 | R30: =+Q30-P30 -> 97.149118
A31: SUBTOTALE | C31: = EBT | D31: =SUM(D27,D29:D30) -> 97.772983 | E31: =SUM(E27,E29:E30) -> 59.548233 | F31: =SUM(F27,F29:F30) -> 29.457753 | G31: =SUM(G27,G29:G30) -> 93.684583 | H31: =SUM(H27,H29:H30) -> 115.91687 | I31: =SUM(I27,I29:I30) -> 75.48717 | J31: =SUM(J27,J29:J30) -> 0 | K31: =SUM(K27,K29:K30) -> 0 | ... O31: =SUM(O27,O29:O30) -> 0 | P31: =+H31/5 -> 23.183375 | Q31: =+I31-H31 -> -40.429703 | R31: =+Q31-P31 -> -63.613078
A32: TAX | C32: - Imposte | D32: =-SUMIFS(DB_Complessivo!$E:$E,DB_Complessivo!$A:$A,"ACT",DB_Complessivo!$B:$B,D$2,DB_Complessivo!$H:$H,$A32)/1000 -> 0 | E32: =-SUMIFS(DB_Complessivo!$E:$E,DB_Complessivo!$A:$A,"ACT",DB_Complessivo!$B:$B,E$2,DB_Complessivo!$H:$H,$A32)/1000 -> 0 | F32: =-SUMIFS(DB_Complessivo!$E:$E,DB_Complessivo!$A:$A,"ACT",DB_Complessivo!$B:$B,F$2,DB_Complessivo!$H:$H,$A32)/1000 -> 0 | G32: =-SUMIFS(DB_Complessivo!$E:$E,DB_Complessivo!$A:$A,"ACT",DB_Complessivo!$B:$B,G$2,DB_Complessivo!$H:$H,$A32)/1000 -> 0 | H32: =-SUMIFS(DB_Complessivo!$E:$E,DB_Complessivo!$A:$A,"ACT",DB_Complessivo!$B:$B,H$2,DB_Complessivo!$H:$H,$A32)/1000 -> 0 | I32: =-SUMIFS(DB_Complessivo!$E:$E,DB_Complessivo!$A:$A,"ACT",DB_Complessivo!$B:$B,I$2,DB_Complessivo!$H:$H,$A32)/1000 -> 0 | J32: =-SUMIFS(DB_Complessivo!$E:$E,DB_Complessivo!$A:$A,"ACT",DB_Complessivo!$B:$B,J$2,DB_Complessivo!$H:$H,$A32)/1000 -> 0 | K32: =-SUMIFS(DB_Complessivo!$E:$E,DB_Complessivo!$A:$A,"ACT",DB_Complessivo!$B:$B,K$2,DB_Complessivo!$H:$H,$A32)/1000 -> 0 | ... O32: =-SUMIFS(DB_Complessivo!$E:$E,DB_Complessivo!$A:$A,"ACT",DB_Complessivo!$B:$B,O$2,DB_Complessivo!$H:$H,$A32)/1000 -> 0 | P32: =+H32/5 -> 0 | Q32: =+I32-H32 -> 0 | R32: =+Q32-P32 -> 0
A33: SUBTOTALE | C33: = Utile/perdita di esercizio | D33: =SUM(D31:D32) -> 97.772983 | E33: =SUM(E31:E32) -> 59.548233 | F33: =SUM(F31:F32) -> 29.457753 | G33: =SUM(G31:G32) -> 93.684583 | H33: =SUM(H31:H32) -> 115.91687 | I33: =SUM(I31:I32) -> 75.48717 | J33: =SUM(J31:J32) -> 0 | K33: =SUM(K31:K32) -> 0 | ... O33: =SUM(O31:O32) -> 0
I35: =+I33*1000 -> 75487.17

Sheet CE_MoM
C1: CONTO ECONOMICO di PROGETTO QUID
C2: EUR/000 | D2: 45688 | E2: =EOMONTH(D2,1) -> 45716 | F2: =EOMONTH(E2,1) -> 45747 | G2: =EOMONTH(F2,1) -> 45777 | H2: =EOMONTH(G2,1) -> 45808 | I2: =EOMONTH(H2,1) -> 45838 | J2: =EOMONTH(I2,1) -> 45869 | K2: =EOMONTH(J2,1) -> 45900 | L2: =EOMONTH(K2,1) -> 45930 | ... O2: =EOMONTH(N2,1) -> 46022
A3: RICOP | C3: Ricavi Netti di Vendita | D3: =CE_YtD!D3 -> 390.27999 | E3: =CE_YtD!E3-CE_YtD!D3 -> 481.76091 | F3: =CE_YtD!F3-CE_YtD!E3 -> 604.69716 | G3: =CE_YtD!G3-CE_YtD!F3 -> 713.30061 | H3: =CE_YtD!H3-CE_YtD!G3 -> 601.76113 | I3: =CE_YtD!I3-CE_YtD!H3 -> 342.96388 | J3: =CE_YtD!J3-CE_YtD!I3 -> -3134.7637 | K3: =CE_YtD!K3-CE_YtD!J3 -> 0 | L3: =CE_YtD!L3-CE_YtD!K3 -> 0 | ... O3: =CE_YtD!O3-CE_YtD!N3 -> 0
A4: CORR | C4: Corrispettivi | D4: =CE_YtD!D4 -> 38.97781 | E4: =CE_YtD!E4-CE_YtD!D4 -> 33.54154 | F4: =CE_YtD!F4-CE_YtD!E4 -> 34.46133 | G4: =CE_YtD!G4-CE_YtD!F4 -> 12.16945 | H4: =CE_YtD!H4-CE_YtD!G4 -> 14.21431 | I4: =CE_YtD!I4-CE_YtD!H4 -> 12.07022 | J4: =CE_YtD!J4-CE_YtD!I4 -> -145.43466 | K4: =CE_YtD!K4-CE_YtD!J4 -> 0 | L4: =CE_YtD!L4-CE_YtD!K4 -> 0 | ... O4: =CE_YtD!O4-CE_YtD!N4 -> 0
A5: VARPF | C5: Variazione magazzino PF | D5: =CE_YtD!D5 -> 84.21847 | E5: =CE_YtD!E5-CE_YtD!D5 -> 0 | F5: =CE_YtD!F5-CE_YtD!E5 -> -47.58835 | G5: =CE_YtD!G5-CE_YtD!F5 -> -40.86824 | H5: =CE_YtD!H5-CE_YtD!G5 -> 54.72493 | I5: =CE_YtD!I5-CE_YtD!H5 -> -81.21015 | J5: =CE_YtD!J5-CE_YtD!I5 -> 30.72334 | K5: =CE_YtD!K5-CE_YtD!J5 -> 0 | L5: =CE_YtD!L5-CE_YtD!K5 -> 0 | ... O5: =CE_YtD!O5-CE_YtD!N5 -> 0
A6: ALTRI | C6: Altri Ricavi | D6: =CE_YtD!D6 -> 75.82325 | E6: =CE_YtD!E6-CE_YtD!D6 -> 1.9185 | F6: =CE_YtD!F6-CE_YtD!E6 -> 41.47551 | G6: =CE_YtD!G6-CE_YtD!F6 -> 41.57714 | H6: =CE_YtD!H6-CE_YtD!G6 -> 18.207 | I6: =CE_YtD!I6-CE_YtD!H6 -> 414.21038 | J6: =CE_YtD!J6-CE_YtD!I6 -> -593.21178 | K6: =CE_YtD!K6-CE_YtD!J6 -> 0 | L6: =CE_YtD!L6-CE_YtD!K6 -> 0 | ... O6: =CE_YtD!O6-CE_YtD!N6 -> 0
A7: SUBTOTALE | C7: Ricavi | D7: =SUM(D3:D6) -> 589.29952 | E7: =SUM(E3:E6) -> 517.22095 | F7: =SUM(F3:F6) -> 633.04565 | G7: =SUM(G3:G6) -> 726.17896 | H7: =SUM(H3:H6) -> 688.90737 | I7: =SUM(I3:I6) -> 688.03433 | J7: =SUM(J3:J6) -> -3842.6868 | K7: =SUM(K3:K6) -> 0 | ... O7: =SUM(O3:O6) -> 0
A8: ACQDI | C8: Acquisti diretti di produzione | D8: =CE_YtD!D8 -> -39.73812 | E8: =CE_YtD!E8-CE_YtD!D8 -> -38.27117 | F8: =CE_YtD!F8-CE_YtD!E8 -> -33.32012 | G8: =CE_YtD!G8-CE_YtD!F8 -> -54.3364 | H8: =CE_YtD!H8-CE_YtD!G8 -> -65.29559 | I8: =CE_YtD!I8-CE_YtD!H8 -> -82.87855 | J8: =CE_YtD!J8-CE_YtD!I8 -> 313.83995 | K8: =CE_YtD!K8-CE_YtD!J8 -> 0 | L8: =CE_YtD!L8-CE_YtD!K8 -> 0 | ... O8: =CE_YtD!O8-CE_YtD!N8 -> 0
A9: VARMP | C9: Variazioni magazzino MP / SL | D9: =CE_YtD!D9 -> 141.30301 | E9: =CE_YtD!E9-CE_YtD!D9 -> 0 | F9: =CE_YtD!F9-CE_YtD!E9 -> -143.99539 | G9: =CE_YtD!G9-CE_YtD!F9 -> 2.72011 | H9: =CE_YtD!H9-CE_YtD!G9 -> -49.97024 | I9: =CE_YtD!I9-CE_YtD!H9 -> -1.6508 | J9: =CE_YtD!J9-CE_YtD!I9 -> 51.59331 | K9: =CE_YtD!K9-CE_YtD!J9 -> 0 | L9: =CE_YtD!L9-CE_YtD!K9 -> 0 | ... O9: =CE_YtD!O9-CE_YtD!N9 -> 0
A10: SERDI | C10: Lavorazioni esterne | D10: =CE_YtD!D10 -> -79.86552 | E10: =CE_YtD!E10-CE_YtD!D10 -> -59.76614 | F10: =CE_YtD!F10-CE_YtD!E10 -> -78.6323 | G10: =CE_YtD!G10-CE_YtD!F10 -> -116.46684 | H10: =CE_YtD!H10-CE_YtD!G10 -> -125.63973 | I10: =CE_YtD!I10-CE_YtD!H10 -> -58.85199 | J10: =CE_YtD!J10-CE_YtD!I10 -> 519.22252 | K10: =CE_YtD!K10-CE_YtD!J10 -> 0 | L10: =CE_YtD!L10-CE_YtD!K10 -> 0 | ... O10: =CE_YtD!O10-CE_YtD!N10 -> 0
A11: PERDI | C11: Manodopera diretta di produzione | D11: =CE_YtD!D11 -> -129.28997 | E11: =CE_YtD!E11-CE_YtD!D11 -> -129.61934 | F11: =CE_YtD!F11-CE_YtD!E11 -> -124.96838 | G11: =CE_YtD!G11-CE_YtD!F11 -> -136.71602 | H11: =CE_YtD!H11-CE_YtD!G11 -> -136.53407 | I11: =CE_YtD!I11-CE_YtD!H11 -> -122.89906 | J11: =CE_YtD!J11-CE_YtD!I11 -> 780.02684 | K11: =CE_YtD!K11-CE_YtD!J11 -> 0 | L11: =CE_YtD!L11-CE_YtD!K11 -> 0 | ... O11: =CE_YtD!O11-CE_YtD!N11 -> 0
A12: SUBTOTALE | C12: Totale costi diretti di produzione | D12: =SUM(D7:D11) -> 481.70892 | E12: =SUM(E7:E11) -> 289.5643 | F12: =SUM(F7:F11) -> 252.12946 | G12: =SUM(G7:G11) -> 421.37981 | H12: =SUM(H7:H11) -> 311.46774 | I12: =SUM(I7:I11) -> 421.75393 | J12: =SUM(J7:J11) -> -2178.0042 | K12: =SUM(K7:K11) -> 0 | ... O12: =SUM(O7:O11) -> 0
A13: SUBTOTALE | C13: Margine diretto di produzione | D13: =IFERROR(D12/D$7,"") -> 0.81742629 | E13: =IFERROR(E12/E$7,"") -> 0.55984643 | F13: =IFERROR(F12/F$7,"") -> 0.39828006 | G13: =IFERROR(G12/G$7,"") -> 0.58026992 | H13: =IFERROR(H12/H$7,"") -> 0.45211846 | I13: =IFERROR(I12/I$7,"") -> 0.61298384 | J13: =IFERROR(J12/J$7,"") -> 0.56679201 | K13: =IFERROR(K12/K$7,"") | ... O13: =IFERROR(O12/O$7,"")
A14: ACQIN | C14: Acquisti indiretti di fabbrica | D14: =CE_YtD!D14 -> -3.56428 | E14: =CE_YtD!E14-CE_YtD!D14 -> -0.81304 | F14: =CE_YtD!F14-CE_YtD!E14 -> -2.23828 | G14: =CE_YtD!G14-CE_YtD!F14 -> -1.43699 | H14: =CE_YtD!H14-CE_YtD!G14 -> -0.03172 | I14: =CE_YtD!I14-CE_YtD!H14 -> -1.74704 | J14: =CE_YtD!J14-CE_YtD!I14 -> 9.83135 | K14: =CE_YtD!K14-CE_YtD!J14 -> 0 | L14: =CE_YtD!L14-CE_YtD!K14 -> 0 | ... O14: =CE_YtD!O14-CE_YtD!N14 -> 0
A15: PERIM | C15: Costi del personale diretto improduttivo | D15: =CE_YtD!D15 -> -55.409988 | E15: =CE_YtD!E15-CE_YtD!D15 -> -55.551145 | F15: =CE_YtD!F15-CE_YtD!E15 -> -53.557877 | G15: =CE_YtD!G15-CE_YtD!F15 -> -58.59258 | H15: =CE_YtD!H15-CE_YtD!G15 -> -58.514603 | I15: =CE_YtD!I15-CE_YtD!H15 -> -52.671026 | J15: =CE_YtD!J15-CE_YtD!I15 -> 334.29722 | K15: =CE_YtD!K15-CE_YtD!J15 -> 0 | L15: =CE_YtD!L15-CE_YtD!K15 -> 0 | ... O15: =CE_YtD!O15-CE_YtD!N15 -> 0
A16: PERIN | C16: Costi del Personale indiretto di fabbrica | D16: =CE_YtD!D16 -> -59.855184 | E16: =CE_YtD!E16-CE_YtD!D16 -> -58.432939 | F16: =CE_YtD!F16-CE_YtD!E16 -> -91.718601 | G16: =CE_YtD!G16-CE_YtD!F16 -> -213.59886 | H16: =CE_YtD!H16-CE_YtD!G16 -> 80.724233 | I16: =CE_YtD!I16-CE_YtD!H16 -> -63.692227 | J16: =CE_YtD!J16-CE_YtD!I16 -> 406.57358 | K16: =CE_YtD!K16-CE_YtD!J16 -> 0 | L16: =CE_YtD!L16-CE_YtD!K16 -> 0 | ... O16: =CE_YtD!O16-CE_YtD!N16 -> 0
A17: SERIN | C17: Servizi indiretti di fabbrica | D17: =CE_YtD!D17 -> -12.6146 | E17: =CE_YtD!E17-CE_YtD!D17 -> -15.81967 | F17: =CE_YtD!F17-CE_YtD!E17 -> -8.80182 | G17: =CE_YtD!G17-CE_YtD!F17 -> -11.1116 | H17: =CE_YtD!H17-CE_YtD!G17 -> -22.69203 | I17: =CE_YtD!I17-CE_YtD!H17 -> -25.72489 | J17: =CE_YtD!J17-CE_YtD!I17 -> 96.76461 | K17: =CE_YtD!K17-CE_YtD!J17 -> 0 | L17: =CE_YtD!L17-CE_YtD!K17 -> 0 | ... O17: =CE_YtD!O17-CE_YtD!N17 -> 0
A18: AMMIN | C18: Ammortamenti indiretti di fabbrica | D18: =CE_YtD!D18 -> -7.18826 | E18: =CE_YtD!E18-CE_YtD!D18 -> -7.18826 | F18: =CE_YtD!F18-CE_YtD!E18 -> -7.58699 | G18: =CE_YtD!G18-CE_YtD!F18 -> -7.32117 | H18: =CE_YtD!H18-CE_YtD!G18 -> -7.32117 | I18: =CE_YtD!I18-CE_YtD!H18 -> -7.32108 | J18: =CE_YtD!J18-CE_YtD!I18 -> 43.92693 | K18: =CE_YtD!K18-CE_YtD!J18 -> 0 | L18: =CE_YtD!L18-CE_YtD!K18 -> 0 | ... O18: =CE_YtD!O18-CE_YtD!N18 -> 0
A19: SUBTOTALE | C19: Totale costi indiretti di fabbrica | D19: =SUM(D12,D14:D18) -> 343.07661 | E19: =SUM(E12,E14:E18) -> 151.75925 | F19: =SUM(F12,F14:F18) -> 88.225891 | G19: =SUM(G12,G14:G18) -> 129.31861 | H19: =SUM(H12,H14:H18) -> 303.63245 | I19: =SUM(I12,I14:I18) -> 270.59767 | J19: =SUM(J12,J14:J18) -> -1286.6105 | K19: =SUM(K12,K14:K18) -> 0 | ... O19: =SUM(O12,O14:O18) -> 0
A20: SUBTOTALE | C20: Margine indiretto di fabbrica | D20: =IFERROR(D19/D$7,"") -> 0.58217697 | E20: =IFERROR(E19/E$7,"") -> 0.2934128 | F20: =IFERROR(F19/F$7,"") -> 0.13936734 | G20: =IFERROR(G19/G$7,"") -> 0.1780809 | H20: =IFERROR(H19/H$7,"") -> 0.44074495 | I20: =IFERROR(I19/I$7,"") -> 0.39329094 | J20: =IFERROR(J19/J$7,"") -> 0.33482054 | K20: =IFERROR(K19/K$7,"") | ... O20: =IFERROR(O19/O$7,"")
A21: PERST | C21: Costi del personale di struttura | D21: =CE_YtD!D21 -> -121.85699 | E21: =CE_YtD!E21-CE_YtD!D21 -> -112.25957 | F21: =CE_YtD!F21-CE_YtD!E21 -> -78.302571 | G21: =CE_YtD!G21-CE_YtD!F21 -> 28.371745 | H21: =CE_YtD!H21-CE_YtD!G21 -> -131.44552 | I21: =CE_YtD!I21-CE_YtD!H21 -> -214.76843 | J21: =CE_YtD!J21-CE_YtD!I21 -> 630.26133 | K21: =CE_YtD!K21-CE_YtD!J21 -> 0 | L21: =CE_YtD!L21-CE_YtD!K21 -> 0 | ... O21: =CE_YtD!O21-CE_YtD!N21 -> 0
A22: SERST | C22: Servizi di struttura | D22: =CE_YtD!D22 -> -44.99773 | E22: =CE_YtD!E22-CE_YtD!D22 -> -41.63101 | F22: =CE_YtD!F22-CE_YtD!E22 -> -64.2212 | G22: =CE_YtD!G22-CE_YtD!F22 -> -102.75362 | H22: =CE_YtD!H22-CE_YtD!G22 -> -5.34467 | I22: =CE_YtD!I22-CE_YtD!H22 -> -126.28953 | J22: =CE_YtD!J22-CE_YtD!I22 -> 385.23776 | K22: =CE_YtD!K22-CE_YtD!J22 -> 0 | L22: =CE_YtD!L22-CE_YtD!K22 -> 0 | ... O22: =CE_YtD!O22-CE_YtD!N22 -> 0
A23: AFFIT | C23: Affitti | D23: =CE_YtD!D23 -> -4.6209 | E23: =CE_YtD!E23-CE_YtD!D23 -> -2.8709 | F23: =CE_YtD!F23-CE_YtD!E23 -> -10.1209 | G23: =CE_YtD!G23-CE_YtD!F23 -> -7.0209 | H23: =CE_YtD!H23-CE_YtD!G23 -> -8.2209 | I23: =CE_YtD!I23-CE_YtD!H23 -> -13.7209 | J23: =CE_YtD!J23-CE_YtD!I23 -> 46.5754 | K23: =CE_YtD!K23-CE_YtD!J23 -> 0 | L23: =CE_YtD!L23-CE_YtD!K23 -> 0 | ... O23: =CE_YtD!O23-CE_YtD!N23 -> 0
A24: COSGS | C24: Costi generali di struttura | D24: =CE_YtD!D24 -> -28.64946 | E24: =CE_YtD!E24-CE_YtD!D24 -> -23.57346 | F24: =CE_YtD!F24-CE_YtD!E24 -> -17.78585 | G24: =CE_YtD!G24-CE_YtD!F24 -> -25.59958 | H24: =CE_YtD!H24-CE_YtD!G24 -> -20.65713 | I24: =CE_YtD!I24-CE_YtD!H24 -> -58.470223 | J24: =CE_YtD!J24-CE_YtD!I24 -> 174.7357 | K24: =CE_YtD!K24-CE_YtD!J24 -> 0 | L24: =CE_YtD!L24-CE_YtD!K24 -> 0 | ... O24: =CE_YtD!O24-CE_YtD!N24 -> 0
A25: AMMST | C25: Ammortamenti di struttura | D25: =CE_YtD!D25 -> -3.76901 | E25: =CE_YtD!E25-CE_YtD!D25 -> -3.76901 | F25: =CE_YtD!F25-CE_YtD!E25 -> -4.10474 | G25: =CE_YtD!G25-CE_YtD!F25 -> -3.88092 | H25: =CE_YtD!H25-CE_YtD!G25 -> -3.88092 | I25: =CE_YtD!I25-CE_YtD!H25 -> -3.88092 | J25: =CE_YtD!J25-CE_YtD!I25 -> 23.28552 | K25: =CE_YtD!K25-CE_YtD!J25 -> 0 | L25: =CE_YtD!L25-CE_YtD!K25 -> 0 | ... O25: =CE_YtD!O25-CE_YtD!N25 -> 0
A26: ACC | C26: Accantonamenti | D26: =CE_YtD!D26 -> 0 | E26: =CE_YtD!E26-CE_YtD!D26 -> 0 | F26: =CE_YtD!F26-CE_YtD!E26 -> 0 | G26: =CE_YtD!G26-CE_YtD!F26 -> 0 | H26: =CE_YtD!H26-CE_YtD!G26 -> 0 | I26: =CE_YtD!I26-CE_YtD!H26 -> 0 | J26: =CE_YtD!J26-CE_YtD!I26 -> 0 | K26: =CE_YtD!K26-CE_YtD!J26 -> 0 | L26: =CE_YtD!L26-CE_YtD!K26 -> 0 | ... O26: =CE_YtD!O26-CE_YtD!N26 -> 0
A27: SUBTOTALE | C27: Totale costi indiretti di struttura | D27: =SUM(D19,D21:D26) -> 139.18251 | E27: =SUM(E19,E21:E26) -> -32.3447 | F27: =SUM(F19,F21:F26) -> -86.30937 | G27: =SUM(G19,G21:G26) -> 18.43533 | H27: =SUM(H19,H21:H26) -> 134.08331 | I27: =SUM(I19,I21:I26) -> -146.53233 | J27: =SUM(J19,J21:J26) -> -26.51475 | K27: =SUM(K19,K21:K26) -> 0 | ... O27: =SUM(O19,O21:O26) -> 0
A28: SUBTOTALE | C28: EBIT | D28: =IFERROR(D27/D$7,"") -> 0.23618297 | E28: =IFERROR(E27/E$7,"") -> -0.062535557 | F28: =IFERROR(F27/F$7,"") -> -0.13633988 | G28: =IFERROR(G27/G$7,"") -> 0.025386759 | H28: =IFERROR(H27/H$7,"") -> 0.19463184 | I28: =IFERROR(I27/I$7,"") -> -0.21297242 | J28: =IFERROR(J27/J$7,"") -> 0.006900055 | K28: =IFERROR(K27/K$7,"") | ... O28: =IFERROR(O27/O$7,"")
A29: ONFIN | C29: Gestione Finanziaria | D29: =CE_YtD!D29 -> -29.11194 | E29: =CE_YtD!E29-CE_YtD!D29 -> -1.02743 | F29: =CE_YtD!F29-CE_YtD!E29 -> 0 | G29: =CE_YtD!G29-CE_YtD!F29 -> 22.8879 | H29: =CE_YtD!H29-CE_YtD!G29 -> 0 | I29: =CE_YtD!I29-CE_YtD!H29 -> 18.92926 | J29: =CE_YtD!J29-CE_YtD!I29 -> -11.67779 | K29: =CE_YtD!K29-CE_YtD!J29 -> 0 | L29: =CE_YtD!L29-CE_YtD!K29 -> 0 | ... O29: =CE_YtD!O29-CE_YtD!N29 -> 0
A30: ONSTR | C30: Gestione Straordinaria e Non Core | D30: =CE_YtD!D30 -> -12.29759 | E30: =CE_YtD!E30-CE_YtD!D30 -> -4.85262 | F30: =CE_YtD!F30-CE_YtD!E30 -> 56.21889 | G30: =CE_YtD!G30-CE_YtD!F30 -> 22.9036 | H30: =CE_YtD!H30-CE_YtD!G30 -> -111.85102 | I30: =CE_YtD!I30-CE_YtD!H30 -> 87.17337 | J30: =CE_YtD!J30-CE_YtD!I30 -> -37.29463 | K30: =CE_YtD!K30-CE_YtD!J30 -> 0 | L30: =CE_YtD!L30-CE_YtD!K30 -> 0 | ... O30: =CE_YtD!O30-CE_YtD!N30 -> 0
A31: SUBTOTALE | C31: = EBT | D31: =SUM(D27,D29:D30) -> 97.772983 | E31: =SUM(E27,E29:E30) -> -38.22475 | F31: =SUM(F27,F29:F30) -> -30.09048 | G31: =SUM(G27,G29:G30) -> 64.22683 | H31: =SUM(H27,H29:H30) -> 22.23229 | I31: =SUM(I27,I29:I30) -> -40.429703 | J31: =SUM(J27,J29:J30) -> -75.48717 | K31: =SUM(K27,K29:K30) -> 0 | ... O31: =SUM(O27,O29:O30) -> 0
A32: TAX | C32: - Imposte | D32: =CE_YtD!D32 -> 0 | E32: =CE_YtD!E32-CE_YtD!D32 -> 0 | F32: =CE_YtD!F32-CE_YtD!E32 -> 0 | G32: =CE_YtD!G32-CE_YtD!F32 -> 0 | H32: =CE_YtD!H32-CE_YtD!G32 -> 0 | I32: =CE_YtD!I32-CE_YtD!H32 -> 0 | J32: =CE_YtD!J32-CE_YtD!I32 -> 0 | K32: =CE_YtD!K32-CE_YtD!J32 -> 0 | L32: =CE_YtD!L32-CE_YtD!K32 -> 0 | ... O32: =CE_YtD!O32-CE_YtD!N32 -> 0
A33: SUBTOTALE | C33: = Utile/perdita di esercizio | D33: =SUM(D31:D32) -> 97.772983 | E33: =SUM(E31:E32) -> -38.22475 | F33: =SUM(F31:F32) -> -30.09048 | G33: =SUM(G31:G32) -> 64.22683 | H33: =SUM(H31:H32) -> 22.23229 | I33: =SUM(I31:I32) -> -40.429703 | J33: =SUM(J31:J32) -> -75.48717 | K33: =SUM(K31:K32) -> 0 | ... O33: =SUM(O31:O32) -> 0

Sheet Pivot_CDR
A3: CE/SP | B3: CE
A4: Mese Competenza | B4: 45838
A6: Sum of Saldo (D-A) | B6: Column Labels
A7: Row Labels | B7: ACT | C7: BDG | D7: REV_BDG
A8: Barbagallo | B8: -25778.28 | C8: 41600 | D8: 23740.57 | E8: =+B8-C8 -> -67378.28
A9: COSTI STRUTTURA | B9: 17507.89 | C9: 60350 | D9: 23740.57 | E9: =+B9-C9 -> -42842.11
A10: GEST. EXTRACARATT. | B10: -43286.17 | C10: -18750 | D10: 0 | E10: =+B10-C10 -> -24536.17
A11: Liviero | B11: -207715.61 | C11: -165533.33 | D11: -178032.74 | E11: =+B11-C11 -> -42182.277
A12: RICAVI | B12: -217848.15 | C12: -196000 | D12: -188076.96 | E12: =+B12-C12 -> -21848.15
A13: COSTI STRUTTURA | B13: 10132.54 | C13: 30466.667 | D13: 10044.22 | E13: =+B13-C13 -> -20334.127
A14: Maestrello | B14: 123451.24 | C14: 43137.04 | D14: 41122.756 | E14: =+B14-C14 -> 80314.2
A15: RICAVI | B15: 30723.34 | D15: -50486.81 | E15: =+B15-C15 -> 30723.34
A16: COSTI DIRETTI | B16: 60316.97 | C16: 6500 | D16: 57974.374 | E16: =+B16-C16 -> 53816.97
A17: COSTI INDIRETTI | B17: 28747.42 | C17: 29310.02 | D17: 29238.98 | E17: =+B17-C17 -> -562.6
A18: COSTI STRUTTURA | B18: 3663.51 | C18: 7327.02 | D18: 4396.212 | E18: =+B18-C18 -> -3663.51
A19: Penazzi | B19: -3048183.6 | C19: -3016000 | D19: -3001945.5 | E19: =+B19-C19 -> -32183.64
A20: RICAVI | B20: -3062350.2 | C20: -3016000 | D20: -3014967 | E20: =+B20-C20 -> -46350.19
A21: COSTI INDIRETTI | B21: 135.3 | D21: 162.36 | E21: =+B21-C21 -> 135.3
A22: COSTI STRUTTURA | B22: 14031.25 | D22: 12859.2 | E22: =+B22-C22 -> 14031.25
A23: Ramponi | B23: 881276.6 | C23: 691933.09 | D23: 867538.67 | E23: =+B23-C23 -> 189343.51
A24: COSTI DIRETTI | B24: 824338.81 | C24: 669733.09 | D24: 813144.89 | E24: =+B24-C24 -> 154605.72
A25: COSTI INDIRETTI | B25: 56937.79 | C25: 22200 | D25: 54393.786 | E25: =+B25-C25 -> 34737.79
A26: Tornieri | B26: 2644038.1 | C26: 2311577 | D26: 2504853.5 | E26: =+B26-C26 -> 332461.13
A27: RICAVI | B27: -8336.69 | D27: -6092.81 | E27: =+B27-C27 -> -8336.69
A28: COSTI DIRETTI | B28: 781720.98 | C28: 776090.67 | D28: 797158.47 | E28: =+B28-C28 -> 5630.3116
A29: COSTI INDIRETTI | B29: 761646.25 | C29: 776031.98 | D29: 771637.66 | E29: =+B29-C29 -> -14385.729
A30: COSTI STRUTTURA | B30: 1146302.2 | C30: 758704.3 | D30: 892271.47 | E30: =+B30-C30 -> 387597.87
A31: GEST. EXTRACARATT. | B31: -37294.63 | C31: 750 | D31: 49878.74 | E31: =+B31-C31 -> -38044.63
A32: Valotto | B32: -539702.26 | C32: -405000 | D32: -236463.31 | E32: =+B32-C32 -> -134702.26
A33: RICAVI | B33: -584875.09 | C33: -425000 | D33: -283921.65 | E33: =+B33-C33 -> -159875.09
A34: COSTI STRUTTURA | B34: 45172.83 | C34: 20000 | D34: 47458.337 | E34: =+B34-C34 -> 25172.83
A35: Direzionali | B35: 97126.69 | C35: 76963.556 | D35: 65518.4 | E35: =+B35-C35 -> 20163.134
A36: COSTI DIRETTI | B36: -1694.14 | D36: -1694.14 | E36: =+B36-C36 -> -1694.14
A37: COSTI INDIRETTI | B37: 43926.93 | C37: 40489.5 | D37: 43927.02 | E37: =+B37-C37 -> 3437.43
A38: COSTI STRUTTURA | B38: 23285.52 | C38: 18452.046 | D38: 23285.52 | E38: =+B38-C38 -> 4833.4743
A39: GEST. EXTRACARATT. | B39: 31608.38 | C39: 18022.01 | D39: 0 | E39: =+B39-C39 -> 13586.37
A40: Grand Total | B40: -75487.17 | C40: -421322.69 | D40: 86332.385 | E40: =+B40-C40 -> 345835.52
E41: =+B41-C41 -> 0
E42: =+B42-C42 -> 0
E43: =+B43-C43 -> 0
E44: =+B44-C44 -> 0
E45: =+B45-C45 -> 0
E46: =+B46-C46 -> 0

Sheet Pivot_CE
A3: ACT/BDG | B3: ACT
A4: CE/SP | B4: CE
A6: Sum of Saldo (D-A) | B6: Column Labels | H6: MoM
A7: Row Labels | B7: 45688 | C7: 45716 | D7: 45747 | E7: 45777 | F7: 45808 | G7: 45838 | H7: Gen | I7: Feb | J7: Mar | K7: Apr | L7: Mag | M7: Giu | N7: Media 5 Mesi
A8: RICAVI | B8: -589299.52 | C8: -1106520.5 | D8: -1739566.1 | E8: -2465745.1 | F8: -3154652.4 | G8: -3842686.8 | H8: =+B8 -> -589299.52 | I8: =+C8-B8 -> -517220.95 | J8: =+D8-C8 -> -633045.65 | K8: =+E8-D8 -> -726178.96 | L8: =+F8-E8 -> -688907.37 | M8: =+G8-F8 -> -688034.33 | N8: =+AVERAGE(H8:L8) -> -630930.49
A9: COSTI DIRETTI | B9: 107590.6 | C9: 335247.25 | D9: 716163.44 | E9: 1020962.6 | F9: 1398402.2 | G9: 1664682.6 | H9: =+B9 -> 107590.6 | I9: =+C9-B9 -> 227656.65 | J9: =+D9-C9 -> 380916.19 | K9: =+E9-D9 -> 304799.15 | L9: =+F9-E9 -> 377439.63 | M9: =+G9-F9 -> 266280.4 | N9: =+AVERAGE(H9:L9) -> 279680.44
A10: Acquisti diretti di produzione | B10: 39738.12 | C10: 78009.29 | D10: 111329.41 | E10: 165665.81 | F10: 230961.4 | G10: 313839.95 | H10: =+B10 -> 39738.12 | I10: =+C10-B10 -> 38271.17 | J10: =+D10-C10 -> 33320.12 | K10: =+E10-D10 -> 54336.4 | L10: =+F10-E10 -> 65295.59 | M10: =+G10-F10 -> 82878.55 | N10: =+AVERAGE(H10:L10) -> 46192.28
A11: Variazioni magazzino MP / SL | B11: -141303.01 | C11: -141303.01 | D11: 2692.38 | E11: -27.73 | F11: 49942.51 | G11: 51593.31 | H11: =+B11 -> -141303.01 | I11: =+C11-B11 -> 0 | J11: =+D11-C11 -> 143995.39 | K11: =+E11-D11 -> -2720.11 | L11: =+F11-E11 -> 49970.24 | M11: =+G11-F11 -> 1650.8 | N11: =+AVERAGE(H11:L11) -> 9988.502
A12: Lavorazioni esterne | B12: 79865.52 | C12: 139631.66 | D12: 218263.96 | E12: 334730.8 | F12: 460370.53 | G12: 519222.52 | H12: =+B12 -> 79865.52 | I12: =+C12-B12 -> 59766.14 | J12: =+D12-C12 -> 78632.3 | K12: =+E12-D12 -> 116466.84 | L12: =+F12-E12 -> 125639.73 | M12: =+G12-F12 -> 58851.99 | N12: =+AVERAGE(H12:L12) -> 92074.106
A13: Manodopera diretta di produzione | B13: 129289.97 | C13: 258909.31 | D13: 383877.69 | E13: 520593.71 | F13: 657127.78 | G13: 780026.84 | H13: =+B13 -> 129289.97 | I13: =+C13-B13 -> 129619.34 | J13: =+D13-C13 -> 124968.38 | K13: =+E13-D13 -> 136716.02 | L13: =+F13-E13 -> 136534.07 | M13: =+G13-F13 -> 122899.06 | N13: =+AVERAGE(H13:L13) -> 131425.56
A14: COSTI INDIRETTI | B14: 138632.31 | C14: 276437.36 | D14: 440340.93 | E14: 732402.14 | F14: 740237.43 | G14: 891393.69 | H14: =+B14 -> 138632.31 | I14: =+C14-B14 -> 137805.05 | J14: =+D14-C14 -> 163903.57 | K14: =+E14-D14 -> 292061.2 | L14: =+F14-E14 -> 7835.2899 | M14: =+G14-F14 -> 151156.26 | N14: =+AVERAGE(H14:L14) -> 148047.49
A15: Acquisti indiretti di fabbrica | B15: 3564.28 | C15: 4377.32 | D15: 6615.6 | E15: 8052.59 | F15: 8084.31 | G15: 9831.35 | H15: =+B15 -> 3564.28 | I15: =+C15-B15 -> 813.04 | J15: =+D15-C15 -> 2238.28 | K15: =+E15-D15 -> 1436.99 | L15: =+F15-E15 -> 31.72 | M15: =+G15-F15 -> 1747.04 | N15: =+AVERAGE(H15:L15) -> 1616.862
A16: Costi del personale diretto improduttivo | B16: 55409.988 | C16: 110961.13 | D16: 164519.01 | E16: 223111.59 | F16: 281626.19 | G16: 334297.22 | H16: =+B16 -> 55409.988 | I16: =+C16-B16 -> 55551.145 | J16: =+D16-C16 -> 53557.877 | K16: =+E16-D16 -> 58592.58 | L16: =+F16-E16 -> 58514.603 | M16: =+G16-F16 -> 52671.026 | N16: =+AVERAGE(H16:L16) -> 56325.239
A17: Costi del Personale indiretto di fabbrica | B17: 59855.184 | C17: 118288.12 | D17: 210006.72 | E17: 423605.59 | F17: 342881.35 | G17: 406573.58 | H17: =+B17 -> 59855.184 | I17: =+C17-B17 -> 58432.939 | J17: =+D17-C17 -> 91718.601 | K17: =+E17-D17 -> 213598.86 | L17: =+F17-E17 -> -80724.233 | M17: =+G17-F17 -> 63692.227 | N17: =+AVERAGE(H17:L17) -> 68576.271
A18: Servizi indiretti di fabbrica | B18: 12614.6 | C18: 28434.27 | D18: 37236.09 | E18: 48347.69 | F18: 71039.72 | G18: 96764.61 | H18: =+B18 -> 12614.6 | I18: =+C18-B18 -> 15819.67 | J18: =+D18-C18 -> 8801.82 | K18: =+E18-D18 -> 11111.6 | L18: =+F18-E18 -> 22692.03 | M18: =+G18-F18 -> 25724.89 | N18: =+AVERAGE(H18:L18) -> 14207.944
A19: Ammortamenti indiretti di fabbrica | B19: 7188.26 | C19: 14376.52 | D19: 21963.51 | E19: 29284.68 | F19: 36605.85 | G19: 43926.93 | H19: =+B19 -> 7188.26 | I19: =+C19-B19 -> 7188.26 | J19: =+D19-C19 -> 7586.99 | K19: =+E19-D19 -> 7321.17 | L19: =+F19-E19 -> 7321.17 | M19: =+G19-F19 -> 7321.08 | N19: =+AVERAGE(H19:L19) -> 7321.17
... A29: Grand Total | B29: -97772.983 | C29: -59548.233 | D29: -29457.753 | E29: -93684.583 | F29: -115916.87 | G29: -75487.17 | H29: =+B29 -> -97772.983 | I29: =+C29-B29 -> 38224.75 | J29: =+D29-C29 -> 30090.48 | K29: =+E29-D29 -> -64226.83 | L29: =+F29-E29 -> -22232.29 | M29: =+G29-F29 -> 40429.703 | N29: =+AVERAGE(H29:L29) -> -23183.375
H30: =+B30 -> 0 | I30: =+C30-B30 -> 0 | J30: =+D30-C30 -> 0 | K30: =+E30-D30 -> 0 | L30: =+F30-E30 -> 0 | M30: =+G30-F30 -> 0 | N30: =+AVERAGE(H30:L30) -> 0
H31: =+B31 -> 0 | I31: =+C31-B31 -> 0 | J31: =+D31-C31 -> 0 | K31: =+E31-D31 -> 0 | L31: =+F31-E31 -> 0 | M31: =+G31-F31 -> 0 | N31: =+AVERAGE(H31:L31) -> 0
H32: =+B32 -> 0 | I32: =+C32-B32 -> 0 | J32: =+D32-C32 -> 0 | K32: =+E32-D32 -> 0 | L32: =+F32-E32 -> 0 | M32: =+G32-F32 -> 0 | N32: =+AVERAGE(H32:L32) -> 0
H33: =+B33 -> 0 | I33: =+C33-B33 -> 0 | J33: =+D33-C33 -> 0 | K33: =+E33-D33 -> 0 | L33: =+F33-E33 -> 0 | M33: =+G33-F33 -> 0 | N33: =+AVERAGE(H33:L33) -> 0
H34: =+B34 -> 0 | I34: =+C34-B34 -> 0 | J34: =+D34-C34 -> 0 | K34: =+E34-D34 -> 0 | L34: =+F34-E34 -> 0 | M34: =+G34-F34 -> 0 | N34: =+AVERAGE(H34:L34) -> 0
H35: =+B35 -> 0 | I35: =+C35-B35 -> 0 | J35: =+D35-C35 -> 0 | K35: =+E35-D35 -> 0 | L35: =+F35-E35 -> 0 | M35: =+G35-F35 -> 0 | N35: =+AVERAGE(H35:L35) -> 0
H36: =+B36 -> 0 | I36: =+C36-B36 -> 0 | J36: =+D36-C36 -> 0 | K36: =+E36-D36 -> 0 | L36: =+F36-E36 -> 0 | M36: =+G36-F36 -> 0 | N36: =+AVERAGE(H36:L36) -> 0
H37: =+B37 -> 0 | I37: =+C37-B37 -> 0 | J37: =+D37-C37 -> 0 | K37: =+E37-D37 -> 0 | L37: =+F37-E37 -> 0 | M37: =+G37-F37 -> 0 | N37: =+AVERAGE(H37:L37) -> 0
H38: =+B38 -> 0 | I38: =+C38-B38 -> 0 | J38: =+D38-C38 -> 0 | K38: =+E38-D38 -> 0 | L38: =+F38-E38 -> 0 | M38: =+G38-F38 -> 0 | N38: =+AVERAGE(H38:L38) -> 0
H39: =+B39 -> 0 | I39: =+C39-B39 -> 0 | J39: =+D39-C39 -> 0 | K39: =+E39-D39 -> 0 | L39: =+F39-E39 -> 0 | M39: =+G39-F39 -> 0 | N39: =+AVERAGE(H39:L39) -> 0
H40: =+B40 -> 0 | I40: =+C40-B40 -> 0 | J40: =+D40-C40 -> 0 | K40: =+E40-D40 -> 0 | L40: =+F40-E40 -> 0 | M40: =+G40-F40 -> 0 | N40: =+AVERAGE(H40:L40) -> 0
H41: =+B41 -> 0 | I41: =+C41-B41 -> 0 | J41: =+D41-C41 -> 0 | K41: =+E41-D41 -> 0 | L41: =+F41-E41 -> 0 | M41: =+G41-F41 -> 0 | N41: =+AVERAGE(H41:L41) -> 0
... H100: =+B100 -> 0 | I100: =+C100-B100 -> 0 | J100: =+D100-C100 -> 0 | K100: =+E100-D100 -> 0 | L100: =+F100-E100 -> 0 | M100: =+G100-F100 -> 0 | N100: =+AVERAGE(H100:L100) -> 0

Sheet Pivot_CE (2)
A4: CE/SP | B4: CE
A6: Sum of Saldo (D-A) | B6: Column Labels
A7: Row Labels | B7: ACT | C7: BDG | D7: REV_BDG
A8: Accantonamenti | B8: 5252530.7
A9: RICAVI | B9: -1.6081739e+08 | C9: -80631795 | D9: -91323405
A10: COSTI DIRETTI | B10: 67351552 | C10: 44193587 | D10: 37324185
A11: COSTI INDIRETTI | B11: 26090647 | C11: 15593814 | D11: 20707423
A12: COSTI STRUTTURA | B12: 48089634 | C12: 24698350 | D12: 27548436
A13: Costi del personale di struttura | B13: 19225295 | C13: 12161861 | D13: 14197877
A14: Servizi di struttura | B14: 15966426 | C14: 6926804.4 | D14: 7288672.8
A15: Affitti | B15: 4448164.6 | C15: 1492556.2 | D15: 1562213.7
A16: Costi generali di struttura | B16: 7608365.2 | C16: 3516815.5 | D16: 3822183.2
A17: Ammortamenti di struttura | B17: 841382.99 | C17: 600312.35 | D17: 677489.22
A18: GEST. EXTRACARATT. | B18: -9727142.8 | C18: -257502.54 | D18: 568231.95
A19: Imposte | B19: 2844
A20: Grand Total | B20: -23757329 | C20: 3596453.8 | D20: -5175128.7

Sheet Sheet2
A1: Voce di Spesa/Ricavo | B1: ACT | E1: BDG | H1: Delta | I1: (%)
A3: Ricavi Caratteristici | B3: =+SUM(B4:B5) -> 2884286.6 | C3: =+B3/B$3 -> 1 | E3: =+SUM(E4:E5) -> 2767166.7 | F3: =+E3/E$3 -> 1 | H3: =+B3-E3 -> 117119.94 | I3: =+H3/E3 -> 0.042324861
A4: Vendite | B4: 2791799.8 | E4: 2767166.7
A5: Variaz. Magazzino | B5: =50486.81+42000 -> 92486.81
A6: Ricavi Corrispettivi | B6: =+SUM(B7:B8) -> 91364.44 | C6: =+B6/B$3 -> 0.031676616 | E6: =+SUM(E7:E8) -> 88000 | F6: =+E6/E$3 -> 0.031801482 | H6: =+B6-E6 -> 3364.44 | I6: =+H6/E6 -> 0.038232273
A7: Corrispettivi | B7: 133364.44 | E7: 88000
A8: Variaz. Magazzino | B8: -42000
A9: GRANT | B9: 179001.4 | C9: =+B9/B$3 -> 0.062060892 | E9: 425000 | F9: =+E9/E$3 -> 0.1535867 | H9: =+B9-E9 -> -245998.6 | I9: =+H9/E9 -> -0.57882024
A11: Consumi MP+ACC | B11: =+SUM(B12:B13) -> -280903.91 | C11: =+B11/B$3 -> -0.097391122 | E11: =+SUM(E12:E13) -> -214298.03 | F11: =+E11/E$3 -> -0.077443124 | H11: =+B11-E11 -> -66605.879 | I11: =+H11/E11 -> 0.31080957
A12: Acquisti | B12: -230961.4 | E12: -214298.03
A13: Variaz. Magazzino | B13: -49942.51
A14: Lavorazioni esterne | B14: -460370.53 | C14: =+B14/B$3 -> -0.15961331 | E14: -394311.88 | F14: =+E14/E$3 -> -0.14249661 | H14: =+B14-E14 -> -66058.653 | I14: =+H14/E14 -> 0.16752895
A16: Costi Indiretti/Struttura | B16: =+SUM(B17:B21) -> -485992.24 | C16: =+B16/B$3 -> -0.16849651 | E16: =+SUM(E17:E21) -> -429783.52 | F16: =+E16/E$3 -> -0.15531537 | H16: =+B16-E16 -> -56208.719 | I16: =+H16/E16 -> 0.13078379
A17: Acquisti indiretti di fabbrica | B17: -8084.31 | E17: -8665.5975
A18: Costi del personale diretto improduttivo | B18: -71039.72 | E18: -52328.999
A19: Servizi di struttura | B19: -258948.23 | E19: -240067.35
A20: Affitti | B20: -31654.5 | E20: -22916.667
A21: Costi generali di struttura | B21: -116265.48 | E21: -105804.9
A23: Personale | B23: =+SUM(B24:B27) -> -1697128.2 | C23: =+B23/B$3 -> -0.58840485 | E23: =+SUM(E24:E27) -> -1638478.1 | F23: =+E23/E$3 -> -0.59211401 | H23: =+B23-E23 -> -58650.095 | I23: =+H23/E23 -> 0.03579547
A24: Manodopera diretta di produzione | B24: -657127.78 | E24: -646325.56
A25: Costi del personale diretto improduttivo | B25: -281626.19 | E25: -276996.67
A26: Costi del Personale indiretto di fabbrica | B26: -342881.35 | E26: -351627.07
A27: Costi del personale di struttura | B27: -415492.91 | E27: -363528.85
A29: Ammortamenti | B29: =+SUM(B30:B31) -> -56010.45 | C29: =+B29/B$3 -> -0.019419169 | E29: =+SUM(E30:E31) -> -49117.955 | F29: =+E29/E$3 -> -0.01775027 | H29: =+B29-E29 -> -6892.4952 | I29: =+H29/E29 -> 0.14032537
A30: Ammortamenti indiretti di fabbrica | B30: -36605.85 | E30: -33741.25
A31: Ammortamenti di struttura | B31: -19404.6 | E31: -15376.705
A33: EBIT | B33: =+SUM(B3,B6,B9,B11,B14,B16,B23,B29) -> 174247.08 | C33: =+B33/B$3 -> 0.060412541 | E33: =+SUM(E3,E6,E9,E11,E14,E16,E23,E29) -> 554177.14 | F33: =+E33/E$3 -> 0.2002688 | H33: =+B33-E33 -> -379930.06 | I33: =+H33/E33 -> -0.68557512

Sheet Pivot_SP
A1: ACT/BDG | B1: ACT
A2: CE/SP | B2: SP
A3: Mese Competenza | B3: 45657
A5: Row Labels | B5: Sum of Saldo (D-A)
A6: Altri Crediti | B6: 270189.41
A7: Altri Debiti | B7: -648421.84
A8: Altri Fondi | B8: -518563.61
A9: Capitale | B9: -907300 | E9: 457688.93 | F9: =+E9-E12 -> -2692.3833
A10: Crediti Commerciali | B10: 1965616.2
A11: Debiti a Breve (Liquidità) | B11: 2755661.1 | E11: 581501.59 | F11: =+E11-E12 -> 121120.27 | H11: =+F11-F9 -> 123812.66
A12: Debiti Commerciali | B12: -786791.47 | E12: 460381.31
A13: Debiti Finanziari (MLT) | B13: -2345161.7
A14: Debiti verso Dipendenti | B14: -244821.15
A15: Fondo Ammortamento Imm. Imm. | B15: -126955.35
A16: Fondo Ammortamento Imm. Mat. | B16: -728923.66
A17: Fondo TFR | B17: -674251.67
A18: Immobilizzazioni Finanziarie | B18: 1140229.1
A19: Immobilizzazioni Immateriali | B19: 210892.79
A20: Immobilizzazioni Materiali | B20: 1736681.5
A21: Posizione Tributaria Netta | B21: 44042.88
A22: Rimanenze | B22: 573374.5
A23: Riserve | B23: -282498.88
A24: Utilizzo Linee Anticipo Fatture | B24: -492459.33
A25: Grand Total | B25: 940538.84

Sheet SP
C1: STATO PATRIMONIALE di PROGETTO QUID
C2: EUR/000 | D2: 45657 | E2: =EOMONTH(D2,1) -> 45688 | F2: =EOMONTH(E2,1) -> 45716 | G2: =EOMONTH(F2,1) -> 45747 | H2: =EOMONTH(G2,1) -> 45777 | I2: =EOMONTH(H2,1) -> 45808 | J2: =EOMONTH(I2,1) -> 45838 | K2: =EOMONTH(J2,1) -> 45869 | L2: =EOMONTH(K2,1) -> 45900 | ... Q2: =EOMONTH(P2,1) -> 46053
C4: Immobilizzazioni Immateriali Nette | D4: =+SUM(D5:D6) -> 83.93744 | E4: =+SUM(E5:E6) -> 81.84079 | F4: =+SUM(F5:F6) -> 79.74414 | G4: =+SUM(G5:G6) -> -6.28995 | H4: =+SUM(H5:H6) -> -8.3866 | I4: =+SUM(I5:I6) -> -10.48325 | J4: =+SUM(J5:J6) -> 71.35754 | K4: =+SUM(K5:K6) -> 0 | ... Q4: =+SUM(Q5:Q6) -> 0
A5: 23.I.IMM | C5: - Immobilizzazioni Immateriali | D5: =SUMIFS(DB_Complessivo!$E:$E,DB_Complessivo!$A:$A,"ACT",DB_Complessivo!$H:$H,$A5,DB_Complessivo!$B:$B,D$2)/1000 -> 210.89279 | E5: =SUMIFS(DB_Complessivo!$E:$E,DB_Complessivo!$A:$A,"ACT",DB_Complessivo!$H:$H,$A5,DB_Complessivo!$B:$B,E$2)/1000 -> 210.89279 | F5: =SUMIFS(DB_Complessivo!$E:$E,DB_Complessivo!$A:$A,"ACT",DB_Complessivo!$H:$H,$A5,DB_Complessivo!$B:$B,F$2)/1000 -> 210.89279 | G5: =SUMIFS(DB_Complessivo!$E:$E,DB_Complessivo!$A:$A,"ACT",DB_Complessivo!$H:$H,$A5,DB_Complessivo!$B:$B,G$2)/1000 -> 0 | H5: =SUMIFS(DB_Complessivo!$E:$E,DB_Complessivo!$A:$A,"ACT",DB_Complessivo!$H:$H,$A5,DB_Complessivo!$B:$B,H$2)/1000 -> 0 | I5: =SUMIFS(DB_Complessivo!$E:$E,DB_Complessivo!$A:$A,"ACT",DB_Complessivo!$H:$H,$A5,DB_Complessivo!$B:$B,I$2)/1000 -> 0 | J5: =SUMIFS(DB_Complessivo!$E:$E,DB_Complessivo!$A:$A,"ACT",DB_Complessivo!$H:$H,$A5,DB_Complessivo!$B:$B,J$2)/1000 -> 210.89279 | K5: =SUMIFS(DB_Complessivo!$E:$E,DB_Complessivo!$A:$A,"ACT",DB_Complessivo!$H:$H,$A5,DB_Complessivo!$B:$B,K$2)/1000 -> 0 | ... Q5: =SUMIFS(DB_Complessivo!$E:$E,DB_Complessivo!$A:$A,"ACT",DB_Complessivo!$H:$H,$A5,DB_Complessivo!$B:$B,Q$2)/1000 -> 0
A6: 23.I.IMMFON | C6: - Fondo Ammortamento Imm. Imm. | D6: =SUMIFS(DB_Complessivo!$E:$E,DB_Complessivo!$A:$A,"ACT",DB_Complessivo!$H:$H,$A6,DB_Complessivo!$B:$B,D$2)/1000 -> -126.95535 | E6: =SUMIFS(DB_Complessivo!$E:$E,DB_Complessivo!$A:$A,"ACT",DB_Complessivo!$H:$H,$A6,DB_Complessivo!$B:$B,E$2)/1000 -> -129.052 | F6: =SUMIFS(DB_Complessivo!$E:$E,DB_Complessivo!$A:$A,"ACT",DB_Complessivo!$H:$H,$A6,DB_Complessivo!$B:$B,F$2)/1000 -> -131.14865 | G6: =SUMIFS(DB_Complessivo!$E:$E,DB_Complessivo!$A:$A,"ACT",DB_Complessivo!$H:$H,$A6,DB_Complessivo!$B:$B,G$2)/1000 -> -6.28995 | H6: =SUMIFS(DB_Complessivo!$E:$E,DB_Complessivo!$A:$A,"ACT",DB_Complessivo!$H:$H,$A6,DB_Complessivo!$B:$B,H$2)/1000 -> -8.3866 | I6: =SUMIFS(DB_Complessivo!$E:$E,DB_Complessivo!$A:$A,"ACT",DB_Complessivo!$H:$H,$A6,DB_Complessivo!$B:$B,I$2)/1000 -> -10.48325 | J6: =SUMIFS(DB_Complessivo!$E:$E,DB_Complessivo!$A:$A,"ACT",DB_Complessivo!$H:$H,$A6,DB_Complessivo!$B:$B,J$2)/1000 -> -139.53525 | K6: =SUMIFS(DB_Complessivo!$E:$E,DB_Complessivo!$A:$A,"ACT",DB_Complessivo!$H:$H,$A6,DB_Complessivo!$B:$B,K$2)/1000 -> 0 | ... Q6: =SUMIFS(DB_Complessivo!$E:$E,DB_Complessivo!$A:$A,"ACT",DB_Complessivo!$H:$H,$A6,DB_Complessivo!$B:$B,Q$2)/1000 -> 0
C7: Immobilizzazioni Materiali Nette | D7: =+SUM(D8:D9) -> 1007.7579 | E7: =+SUM(E8:E9) -> 1007.1581 | F7: =+SUM(F8:F9) -> 1007.5875 | G7: =+SUM(G8:G9) -> 0.57294 | H7: =+SUM(H8:H9) -> -8.5325 | I7: =+SUM(I8:I9) -> -11.23794 | J7: =+SUM(J8:J9) -> 993.70459 | K7: =+SUM(K8:K9) -> 0 | ... Q7: =+SUM(Q8:Q9) -> 0
A8: 24.I.MAT | C8: Immobilizzazioni Materiali | D8: =SUMIFS(DB_Complessivo!$E:$E,DB_Complessivo!$A:$A,"ACT",DB_Complessivo!$H:$H,$A8,DB_Complessivo!$B:$B,D$2)/1000 -> 1736.6815 | E8: =SUMIFS(DB_Complessivo!$E:$E,DB_Complessivo!$A:$A,"ACT",DB_Complessivo!$H:$H,$A8,DB_Complessivo!$B:$B,E$2)/1000 -> 1744.9424 | F8: =SUMIFS(DB_Complessivo!$E:$E,DB_Complessivo!$A:$A,"ACT",DB_Complessivo!$H:$H,$A8,DB_Complessivo!$B:$B,F$2)/1000 -> 1754.2324 | G8: =SUMIFS(DB_Complessivo!$E:$E,DB_Complessivo!$A:$A,"ACT",DB_Complessivo!$H:$H,$A8,DB_Complessivo!$B:$B,G$2)/1000 -> 27.88926 | H8: =SUMIFS(DB_Complessivo!$E:$E,DB_Complessivo!$A:$A,"ACT",DB_Complessivo!$H:$H,$A8,DB_Complessivo!$B:$B,H$2)/1000 -> 27.88926 | I8: =SUMIFS(DB_Complessivo!$E:$E,DB_Complessivo!$A:$A,"ACT",DB_Complessivo!$H:$H,$A8,DB_Complessivo!$B:$B,I$2)/1000 -> 34.28926 | J8: =SUMIFS(DB_Complessivo!$E:$E,DB_Complessivo!$A:$A,"ACT",DB_Complessivo!$H:$H,$A8,DB_Complessivo!$B:$B,J$2)/1000 -> 1777.2608 | K8: =SUMIFS(DB_Complessivo!$E:$E,DB_Complessivo!$A:$A,"ACT",DB_Complessivo!$H:$H,$A8,DB_Complessivo!$B:$B,K$2)/1000 -> 0 | ... Q8: =SUMIFS(DB_Complessivo!$E:$E,DB_Complessivo!$A:$A,"ACT",DB_Complessivo!$H:$H,$A8,DB_Complessivo!$B:$B,Q$2)/1000 -> 0
A9: 23.I.MATFON | C9: Fondo Ammortamento Imm. Mat. | D9: =SUMIFS(DB_Complessivo!$E:$E,DB_Complessivo!$A:$A,"ACT",DB_Complessivo!$H:$H,$A9,DB_Complessivo!$B:$B,D$2)/1000 -> -728.92366 | E9: =SUMIFS(DB_Complessivo!$E:$E,DB_Complessivo!$A:$A,"ACT",DB_Complessivo!$H:$H,$A9,DB_Complessivo!$B:$B,E$2)/1000 -> -737.78428 | F9: =SUMIFS(DB_Complessivo!$E:$E,DB_Complessivo!$A:$A,"ACT",DB_Complessivo!$H:$H,$A9,DB_Complessivo!$B:$B,F$2)/1000 -> -746.6449 | G9: =SUMIFS(DB_Complessivo!$E:$E,DB_Complessivo!$A:$A,"ACT",DB_Complessivo!$H:$H,$A9,DB_Complessivo!$B:$B,G$2)/1000 -> -27.31632 | H9: =SUMIFS(DB_Complessivo!$E:$E,DB_Complessivo!$A:$A,"ACT",DB_Complessivo!$H:$H,$A9,DB_Complessivo!$B:$B,H$2)/1000 -> -36.42176 | I9: =SUMIFS(DB_Complessivo!$E:$E,DB_Complessivo!$A:$A,"ACT",DB_Complessivo!$H:$H,$A9,DB_Complessivo!$B:$B,I$2)/1000 -> -45.5272 | J9: =SUMIFS(DB_Complessivo!$E:$E,DB_Complessivo!$A:$A,"ACT",DB_Complessivo!$H:$H,$A9,DB_Complessivo!$B:$B,J$2)/1000 -> -783.55621 | K9: =SUMIFS(DB_Complessivo!$E:$E,DB_Complessivo!$A:$A,"ACT",DB_Complessivo!$H:$H,$A9,DB_Complessivo!$B:$B,K$2)/1000 -> 0 | ... Q9: =SUMIFS(DB_Complessivo!$E:$E,DB_Complessivo!$A:$A,"ACT",DB_Complessivo!$H:$H,$A9,DB_Complessivo!$B:$B,Q$2)/1000 -> 0
A10: 38.TFR | C10: Fondo TFR | D10: =SUMIFS(DB_Complessivo!$E:$E,DB_Complessivo!$A:$A,"ACT",DB_Complessivo!$H:$H,$A10,DB_Complessivo!$B:$B,D$2)/1000 -> -674.25167 | E10: =SUMIFS(DB_Complessivo!$E:$E,DB_Complessivo!$A:$A,"ACT",DB_Complessivo!$H:$H,$A10,DB_Complessivo!$B:$B,E$2)/1000 -> -689.28415 | F10: =SUMIFS(DB_Complessivo!$E:$E,DB_Complessivo!$A:$A,"ACT",DB_Complessivo!$H:$H,$A10,DB_Complessivo!$B:$B,F$2)/1000 -> -703.63193 | G10: =SUMIFS(DB_Complessivo!$E:$E,DB_Complessivo!$A:$A,"ACT",DB_Complessivo!$H:$H,$A10,DB_Complessivo!$B:$B,G$2)/1000 -> -39.07728 | H10: =SUMIFS(DB_Complessivo!$E:$E,DB_Complessivo!$A:$A,"ACT",DB_Complessivo!$H:$H,$A10,DB_Complessivo!$B:$B,H$2)/1000 -> -55.72003 | I10: =SUMIFS(DB_Complessivo!$E:$E,DB_Complessivo!$A:$A,"ACT",DB_Complessivo!$H:$H,$A10,DB_Complessivo!$B:$B,I$2)/1000 -> -71.57976 | J10: =SUMIFS(DB_Complessivo!$E:$E,DB_Complessivo!$A:$A,"ACT",DB_Complessivo!$H:$H,$A10,DB_Complessivo!$B:$B,J$2)/1000 -> -733.2327 | K10: =SUMIFS(DB_Complessivo!$E:$E,DB_Complessivo!$A:$A,"ACT",DB_Complessivo!$H:$H,$A10,DB_Complessivo!$B:$B,K$2)/1000 -> 0 | ... Q10: =SUMIFS(DB_Complessivo!$E:$E,DB_Complessivo!$A:$A,"ACT",DB_Complessivo!$H:$H,$A10,DB_Complessivo!$B:$B,Q$2)/1000 -> 0
A11: 33.PROV | C11: Altri Fondi | D11: =SUMIFS(DB_Complessivo!$E:$E,DB_Complessivo!$A:$A,"ACT",DB_Complessivo!$H:$H,$A11,DB_Complessivo!$B:$B,D$2)/1000 -> -518.56361 | E11: =SUMIFS(DB_Complessivo!$E:$E,DB_Complessivo!$A:$A,"ACT",DB_Complessivo!$H:$H,$A11,DB_Complessivo!$B:$B,E$2)/1000 -> -518.56361 | F11: =SUMIFS(DB_Complessivo!$E:$E,DB_Complessivo!$A:$A,"ACT",DB_Complessivo!$H:$H,$A11,DB_Complessivo!$B:$B,F$2)/1000 -> -518.56361 | G11: =SUMIFS(DB_Complessivo!$E:$E,DB_Complessivo!$A:$A,"ACT",DB_Complessivo!$H:$H,$A11,DB_Complessivo!$B:$B,G$2)/1000 -> 0 | H11: =SUMIFS(DB_Complessivo!$E:$E,DB_Complessivo!$A:$A,"ACT",DB_Complessivo!$H:$H,$A11,DB_Complessivo!$B:$B,H$2)/1000 -> 0 | I11: =SUMIFS(DB_Complessivo!$E:$E,DB_Complessivo!$A:$A,"ACT",DB_Complessivo!$H:$H,$A11,DB_Complessivo!$B:$B,I$2)/1000 -> 0 | J11: =SUMIFS(DB_Complessivo!$E:$E,DB_Complessivo!$A:$A,"ACT",DB_Complessivo!$H:$H,$A11,DB_Complessivo!$B:$B,J$2)/1000 -> -574.2685 | K11: =SUMIFS(DB_Complessivo!$E:$E,DB_Complessivo!$A:$A,"ACT",DB_Complessivo!$H:$H,$A11,DB_Complessivo!$B:$B,K$2)/1000 -> 0 | ... Q11: =SUMIFS(DB_Complessivo!$E:$E,DB_Complessivo!$A:$A,"ACT",DB_Complessivo!$H:$H,$A11,DB_Complessivo!$B:$B,Q$2)/1000 -> 0
C12: ATTIVO FISSO NETTO | D12: =SUM(D4,D7,D10:D11) -> -101.11996 | E12: =SUM(E4,E7,E10:E11) -> -118.84889 | F12: =SUM(F4,F7,F10:F11) -> -134.86394 | G12: =SUM(G4,G7,G10:G11) -> -44.79429 | H12: =SUM(H4,H7,H10:H11) -> -72.63913 | I12: =SUM(I4,I7,I10:I11) -> -93.30095 | J12: =SUM(J4,J7,J10:J11) -> -242.43907 | K12: =SUM(K4,K7,K10:K11) -> 0 | ... Q12: =SUM(Q4,Q7,Q10:Q11) -> 0
A14: 26.MAG | C14: Rimanenze | D14: =SUMIFS(DB_Complessivo!$E:$E,DB_Complessivo!$A:$A,"ACT",DB_Complessivo!$H:$H,$A14,DB_Complessivo!$B:$B,D$2)/1000 -> 573.3745 | E14: =SUMIFS(DB_Complessivo!$E:$E,DB_Complessivo!$A:$A,"ACT",DB_Complessivo!$H:$H,$A14,DB_Complessivo!$B:$B,E$2)/1000 -> 775.51839 | F14: =SUMIFS(DB_Complessivo!$E:$E,DB_Complessivo!$A:$A,"ACT",DB_Complessivo!$H:$H,$A14,DB_Complessivo!$B:$B,F$2)/1000 -> 775.51839 | G14: =SUMIFS(DB_Complessivo!$E:$E,DB_Complessivo!$A:$A,"ACT",DB_Complessivo!$H:$H,$A14,DB_Complessivo!$B:$B,G$2)/1000 -> 33.93774 | H14: =SUMIFS(DB_Complessivo!$E:$E,DB_Complessivo!$A:$A,"ACT",DB_Complessivo!$H:$H,$A14,DB_Complessivo!$B:$B,H$2)/1000 -> -4.21039 | I14: =SUMIFS(DB_Complessivo!$E:$E,DB_Complessivo!$A:$A,"ACT",DB_Complessivo!$H:$H,$A14,DB_Complessivo!$B:$B,I$2)/1000 -> 0.5443 | J14: =SUMIFS(DB_Complessivo!$E:$E,DB_Complessivo!$A:$A,"ACT",DB_Complessivo!$H:$H,$A14,DB_Complessivo!$B:$B,J$2)/1000 -> 491.05785 | K14: =SUMIFS(DB_Complessivo!$E:$E,DB_Complessivo!$A:$A,"ACT",DB_Complessivo!$H:$H,$A14,DB_Complessivo!$B:$B,K$2)/1000 -> 0 | ... Q14: =SUMIFS(DB_Complessivo!$E:$E,DB_Complessivo!$A:$A,"ACT",DB_Complessivo!$H:$H,$A14,DB_Complessivo!$B:$B,Q$2)/1000 -> 0
A15: 27.CLI | C15: Crediti Commerciali | D15: =SUMIFS(DB_Complessivo!$E:$E,DB_Complessivo!$A:$A,"ACT",DB_Complessivo!$H:$H,$A15,DB_Complessivo!$B:$B,D$2)/1000 -> 1965.6162 | E15: =SUMIFS(DB_Complessivo!$E:$E,DB_Complessivo!$A:$A,"ACT",DB_Complessivo!$H:$H,$A15,DB_Complessivo!$B:$B,E$2)/1000 -> 2121.1728 | F15: =SUMIFS(DB_Complessivo!$E:$E,DB_Complessivo!$A:$A,"ACT",DB_Complessivo!$H:$H,$A15,DB_Complessivo!$B:$B,F$2)/1000 -> 2707.3329 | G15: =SUMIFS(DB_Complessivo!$E:$E,DB_Complessivo!$A:$A,"ACT",DB_Complessivo!$H:$H,$A15,DB_Complessivo!$B:$B,G$2)/1000 -> 1516.543 | H15: =SUMIFS(DB_Complessivo!$E:$E,DB_Complessivo!$A:$A,"ACT",DB_Complessivo!$H:$H,$A15,DB_Complessivo!$B:$B,H$2)/1000 -> 2429.4454 | I15: =SUMIFS(DB_Complessivo!$E:$E,DB_Complessivo!$A:$A,"ACT",DB_Complessivo!$H:$H,$A15,DB_Complessivo!$B:$B,I$2)/1000 -> 3184.5264 | J15: =SUMIFS(DB_Complessivo!$E:$E,DB_Complessivo!$A:$A,"ACT",DB_Complessivo!$H:$H,$A15,DB_Complessivo!$B:$B,J$2)/1000 -> 1353.2129 | K15: =SUMIFS(DB_Complessivo!$E:$E,DB_Complessivo!$A:$A,"ACT",DB_Complessivo!$H:$H,$A15,DB_Complessivo!$B:$B,K$2)/1000 -> 0 | ... Q15: =SUMIFS(DB_Complessivo!$E:$E,DB_Complessivo!$A:$A,"ACT",DB_Complessivo!$H:$H,$A15,DB_Complessivo!$B:$B,Q$2)/1000 -> 0
A16: 28.FOR | C16: Debiti Commerciali | D16: =SUMIFS(DB_Complessivo!$E:$E,DB_Complessivo!$A:$A,"ACT",DB_Complessivo!$H:$H,$A16,DB_Complessivo!$B:$B,D$2)/1000 -> -786.79147 | E16: =SUMIFS(DB_Complessivo!$E:$E,DB_Complessivo!$A:$A,"ACT",DB_Complessivo!$H:$H,$A16,DB_Complessivo!$B:$B,E$2)/1000 -> -1040.7201 | F16: =SUMIFS(DB_Complessivo!$E:$E,DB_Complessivo!$A:$A,"ACT",DB_Complessivo!$H:$H,$A16,DB_Complessivo!$B:$B,F$2)/1000 -> -1277.7142 | G16: =SUMIFS(DB_Complessivo!$E:$E,DB_Complessivo!$A:$A,"ACT",DB_Complessivo!$H:$H,$A16,DB_Complessivo!$B:$B,G$2)/1000 -> -519.5785 | H16: =SUMIFS(DB_Complessivo!$E:$E,DB_Complessivo!$A:$A,"ACT",DB_Complessivo!$H:$H,$A16,DB_Complessivo!$B:$B,H$2)/1000 -> -891.23225 | I16: =SUMIFS(DB_Complessivo!$E:$E,DB_Complessivo!$A:$A,"ACT",DB_Complessivo!$H:$H,$A16,DB_Complessivo!$B:$B,I$2)/1000 -> -1279.5817 | J16: =SUMIFS(DB_Complessivo!$E:$E,DB_Complessivo!$A:$A,"ACT",DB_Complessivo!$H:$H,$A16,DB_Complessivo!$B:$B,J$2)/1000 -> -827.84899 | K16: =SUMIFS(DB_Complessivo!$E:$E,DB_Complessivo!$A:$A,"ACT",DB_Complessivo!$H:$H,$A16,DB_Complessivo!$B:$B,K$2)/1000 -> 0 | ... Q16: =SUMIFS(DB_Complessivo!$E:$E,DB_Complessivo!$A:$A,"ACT",DB_Complessivo!$H:$H,$A16,DB_Complessivo!$B:$B,Q$2)/1000 -> 0
A17: 29.AC | C17: Altri Crediti | D17: =SUMIFS(DB_Complessivo!$E:$E,DB_Complessivo!$A:$A,"ACT",DB_Complessivo!$H:$H,$A17,DB_Complessivo!$B:$B,D$2)/1000 -> 270.18941 | E17: =SUMIFS(DB_Complessivo!$E:$E,DB_Complessivo!$A:$A,"ACT",DB_Complessivo!$H:$H,$A17,DB_Complessivo!$B:$B,E$2)/1000 -> 251.67853 | F17: =SUMIFS(DB_Complessivo!$E:$E,DB_Complessivo!$A:$A,"ACT",DB_Complessivo!$H:$H,$A17,DB_Complessivo!$B:$B,F$2)/1000 -> 297.02743 | G17: =SUMIFS(DB_Complessivo!$E:$E,DB_Complessivo!$A:$A,"ACT",DB_Complessivo!$H:$H,$A17,DB_Complessivo!$B:$B,G$2)/1000 -> 68.71522 | H17: =SUMIFS(DB_Complessivo!$E:$E,DB_Complessivo!$A:$A,"ACT",DB_Complessivo!$H:$H,$A17,DB_Complessivo!$B:$B,H$2)/1000 -> 33.73448 | I17: =SUMIFS(DB_Complessivo!$E:$E,DB_Complessivo!$A:$A,"ACT",DB_Complessivo!$H:$H,$A17,DB_Complessivo!$B:$B,I$2)/1000 -> 163.68855 | J17: =SUMIFS(DB_Complessivo!$E:$E,DB_Complessivo!$A:$A,"ACT",DB_Complessivo!$H:$H,$A17,DB_Complessivo!$B:$B,J$2)/1000 -> 374.77313 | K17: =SUMIFS(DB_Complessivo!$E:$E,DB_Complessivo!$A:$A,"ACT",DB_Complessivo!$H:$H,$A17,DB_Complessivo!$B:$B,K$2)/1000 -> 0 | ... Q17: =SUMIFS(DB_Complessivo!$E:$E,DB_Complessivo!$A:$A,"ACT",DB_Complessivo!$H:$H,$A17,DB_Complessivo!$B:$B,Q$2)/1000 -> 0
A18: 30.AD | C18: Altri Debiti | D18: =SUMIFS(DB_Complessivo!$E:$E,DB_Complessivo!$A:$A,"ACT",DB_Complessivo!$H:$H,$A18,DB_Complessivo!$B:$B,D$2)/1000 -> -648.42184 | E18: =SUMIFS(DB_Complessivo!$E:$E,DB_Complessivo!$A:$A,"ACT",DB_Complessivo!$H:$H,$A18,DB_Complessivo!$B:$B,E$2)/1000 -> -617.0743 | F18: =SUMIFS(DB_Complessivo!$E:$E,DB_Complessivo!$A:$A,"ACT",DB_Complessivo!$H:$H,$A18,DB_Complessivo!$B:$B,F$2)/1000 -> -740.066 | G18: =SUMIFS(DB_Complessivo!$E:$E,DB_Complessivo!$A:$A,"ACT",DB_Complessivo!$H:$H,$A18,DB_Complessivo!$B:$B,G$2)/1000 -> -262.12435 | H18: =SUMIFS(DB_Complessivo!$E:$E,DB_Complessivo!$A:$A,"ACT",DB_Complessivo!$H:$H,$A18,DB_Complessivo!$B:$B,H$2)/1000 -> -373.78785 | I18: =SUMIFS(DB_Complessivo!$E:$E,DB_Complessivo!$A:$A,"ACT",DB_Complessivo!$H:$H,$A18,DB_Complessivo!$B:$B,I$2)/1000 -> -472.27405 | J18: =SUMIFS(DB_Complessivo!$E:$E,DB_Complessivo!$A:$A,"ACT",DB_Complessivo!$H:$H,$A18,DB_Complessivo!$B:$B,J$2)/1000 -> -701.66725 | K18: =SUMIFS(DB_Complessivo!$E:$E,DB_Complessivo!$A:$A,"ACT",DB_Complessivo!$H:$H,$A18,DB_Complessivo!$B:$B,K$2)/1000 -> 0 | ... Q18: =SUMIFS(DB_Complessivo!$E:$E,DB_Complessivo!$A:$A,"ACT",DB_Complessivo!$H:$H,$A18,DB_Complessivo!$B:$B,Q$2)/1000 -> 0
A19: 55.DIP | C19: Debiti verso Dipendenti | D19: =SUMIFS(DB_Complessivo!$E:$E,DB_Complessivo!$A:$A,"ACT",DB_Complessivo!$H:$H,$A19,DB_Complessivo!$B:$B,D$2)/1000 -> -244.82115 | E19: =SUMIFS(DB_Complessivo!$E:$E,DB_Complessivo!$A:$A,"ACT",DB_Complessivo!$H:$H,$A19,DB_Complessivo!$B:$B,E$2)/1000 -> -470.6994 | F19: =SUMIFS(DB_Complessivo!$E:$E,DB_Complessivo!$A:$A,"ACT",DB_Complessivo!$H:$H,$A19,DB_Complessivo!$B:$B,F$2)/1000 -> -673.85958 | G19: =SUMIFS(DB_Complessivo!$E:$E,DB_Complessivo!$A:$A,"ACT",DB_Complessivo!$H:$H,$A19,DB_Complessivo!$B:$B,G$2)/1000 -> -644.64502 | H19: =SUMIFS(DB_Complessivo!$E:$E,DB_Complessivo!$A:$A,"ACT",DB_Complessivo!$H:$H,$A19,DB_Complessivo!$B:$B,H$2)/1000 -> -884.89274 | I19: =SUMIFS(DB_Complessivo!$E:$E,DB_Complessivo!$A:$A,"ACT",DB_Complessivo!$H:$H,$A19,DB_Complessivo!$B:$B,I$2)/1000 -> -1115.8161 | J19: =SUMIFS(DB_Complessivo!$E:$E,DB_Complessivo!$A:$A,"ACT",DB_Complessivo!$H:$H,$A19,DB_Complessivo!$B:$B,J$2)/1000 -> -435.97225 | K19: =SUMIFS(DB_Complessivo!$E:$E,DB_Complessivo!$A:$A,"ACT",DB_Complessivo!$H:$H,$A19,DB_Complessivo!$B:$B,K$2)/1000 -> 0 | ... Q19: =SUMIFS(DB_Complessivo!$E:$E,DB_Complessivo!$A:$A,"ACT",DB_Complessivo!$H:$H,$A19,DB_Complessivo!$B:$B,Q$2)/1000 -> 0
A20: 31.PTN | C20: Posizione Tributaria Netta | D20: =SUMIFS(DB_Complessivo!$E:$E,DB_Complessivo!$A:$A,"ACT",DB_Complessivo!$H:$H,$A20,DB_Complessivo!$B:$B,D$2)/1000 -> 44.04288 | E20: =SUMIFS(DB_Complessivo!$E:$E,DB_Complessivo!$A:$A,"ACT",DB_Complessivo!$H:$H,$A20,DB_Complessivo!$B:$B,E$2)/1000 -> 26.20014 | F20: =SUMIFS(DB_Complessivo!$E:$E,DB_Complessivo!$A:$A,"ACT",DB_Complessivo!$H:$H,$A20,DB_Complessivo!$B:$B,F$2)/1000 -> -104.12498 | G20: =SUMIFS(DB_Complessivo!$E:$E,DB_Complessivo!$A:$A,"ACT",DB_Complessivo!$H:$H,$A20,DB_Complessivo!$B:$B,G$2)/1000 -> -313.56337 | H20: =SUMIFS(DB_Complessivo!$E:$E,DB_Complessivo!$A:$A,"ACT",DB_Complessivo!$H:$H,$A20,DB_Complessivo!$B:$B,H$2)/1000 -> -416.00094 | I20: =SUMIFS(DB_Complessivo!$E:$E,DB_Complessivo!$A:$A,"ACT",DB_Complessivo!$H:$H,$A20,DB_Complessivo!$B:$B,I$2)/1000 -> -579.07905 | J20: =SUMIFS(DB_Complessivo!$E:$E,DB_Complessivo!$A:$A,"ACT",DB_Complessivo!$H:$H,$A20,DB_Complessivo!$B:$B,J$2)/1000 -> 32.74144 | K20: =SUMIFS(DB_Complessivo!$E:$E,DB_Complessivo!$A:$A,"ACT",DB_Complessivo!$H:$H,$A20,DB_Complessivo!$B:$B,K$2)/1000 -> 0 | ... Q20: =SUMIFS(DB_Complessivo!$E:$E,DB_Complessivo!$A:$A,"ACT",DB_Complessivo!$H:$H,$A20,DB_Complessivo!$B:$B,Q$2)/1000 -> 0
A21: 32.IC | C21: Posizione Intercompany | D21: =SUMIFS(DB_Complessivo!$E:$E,DB_Complessivo!$A:$A,"ACT",DB_Complessivo!$H:$H,$A21,DB_Complessivo!$B:$B,D$2)/1000 -> 0 | E21: =SUMIFS(DB_Complessivo!$E:$E,DB_Complessivo!$A:$A,"ACT",DB_Complessivo!$H:$H,$A21,DB_Complessivo!$B:$B,E$2)/1000 -> 0 | F21: =SUMIFS(DB_Complessivo!$E:$E,DB_Complessivo!$A:$A,"ACT",DB_Complessivo!$H:$H,$A21,DB_Complessivo!$B:$B,F$2)/1000 -> 0 | G21: =SUMIFS(DB_Complessivo!$E:$E,DB_Complessivo!$A:$A,"ACT",DB_Complessivo!$H:$H,$A21,DB_Complessivo!$B:$B,G$2)/1000 -> 0 | H21: =SUMIFS(DB_Complessivo!$E:$E,DB_Complessivo!$A:$A,"ACT",DB_Complessivo!$H:$H,$A21,DB_Complessivo!$B:$B,H$2)/1000 -> 0 | I21: =SUMIFS(DB_Complessivo!$E:$E,DB_Complessivo!$A:$A,"ACT",DB_Complessivo!$H:$H,$A21,DB_Complessivo!$B:$B,I$2)/1000 -> 0 | J21: =SUMIFS(DB_Complessivo!$E:$E,DB_Complessivo!$A:$A,"ACT",DB_Complessivo!$H:$H,$A21,DB_Complessivo!$B:$B,J$2)/1000 -> 0 | K21: =SUMIFS(DB_Complessivo!$E:$E,DB_Complessivo!$A:$A,"ACT",DB_Complessivo!$H:$H,$A21,DB_Complessivo!$B:$B,K$2)/1000 -> 0 | ... Q21: =SUMIFS(DB_Complessivo!$E:$E,DB_Complessivo!$A:$A,"ACT",DB_Complessivo!$H:$H,$A21,DB_Complessivo!$B:$B,Q$2)/1000 -> 0
C22: CAPITALE CIRCOLANTE NETTO OPERATIVO | D22: =SUM(D14:D21) -> 1173.1885 | E22: =SUM(E14:E21) -> 1046.076 | F22: =SUM(F14:F21) -> 984.11404 | G22: =SUM(G14:G21) -> -120.71527 | H22: =SUM(H14:H21) -> -106.94433 | I22: =SUM(I14:I21) -> -97.991677 | J22: =SUM(J14:J21) -> 286.29679 | K22: =SUM(K14:K21) -> 0 | ... Q22: =SUM(Q14:Q21) -> 0
C24: CAPITALE INVESTITO NETTO OPERATIVO | D24: =SUM(D12,D22) -> 1072.0685 | E24: =SUM(E12,E22) -> 927.22715 | F24: =SUM(F12,F22) -> 849.2501 | G24: =SUM(G12,G22) -> -165.50956 | H24: =SUM(H12,H22) -> -179.58346 | I24: =SUM(I12,I22) -> -191.29263 | J24: =SUM(J12,J22) -> 43.857723 | K24: =SUM(K12,K22) -> 0 | ... Q24: =SUM(Q12,Q22) -> 0
A26: 36.LIQ | C26: Debiti a Breve (Liquidità) | D26: =-SUMIFS(DB_Complessivo!$E:$E,DB_Complessivo!$A:$A,"ACT",DB_Complessivo!$H:$H,$A26,DB_Complessivo!$B:$B,D$2)/1000 -> -2755.6611 | E26: =-SUMIFS(DB_Complessivo!$E:$E,DB_Complessivo!$A:$A,"ACT",DB_Complessivo!$H:$H,$A26,DB_Complessivo!$B:$B,E$2)/1000 -> -2955.6159 | F26: =-SUMIFS(DB_Complessivo!$E:$E,DB_Complessivo!$A:$A,"ACT",DB_Complessivo!$H:$H,$A26,DB_Complessivo!$B:$B,F$2)/1000 -> -2980.5519 | G26: =-SUMIFS(DB_Complessivo!$E:$E,DB_Complessivo!$A:$A,"ACT",DB_Complessivo!$H:$H,$A26,DB_Complessivo!$B:$B,G$2)/1000 -> -124.93094 | H26: =-SUMIFS(DB_Complessivo!$E:$E,DB_Complessivo!$A:$A,"ACT",DB_Complessivo!$H:$H,$A26,DB_Complessivo!$B:$B,H$2)/1000 -> -346.83167 | I26: =-SUMIFS(DB_Complessivo!$E:$E,DB_Complessivo!$A:$A,"ACT",DB_Complessivo!$H:$H,$A26,DB_Complessivo!$B:$B,I$2)/1000 -> -380.82313 | J26: =-SUMIFS(DB_Complessivo!$E:$E,DB_Complessivo!$A:$A,"ACT",DB_Complessivo!$H:$H,$A26,DB_Complessivo!$B:$B,J$2)/1000 -> -3022.1902 | K26: =-SUMIFS(DB_Complessivo!$E:$E,DB_Complessivo!$A:$A,"ACT",DB_Complessivo!$H:$H,$A26,DB_Complessivo!$B:$B,K$2)/1000 -> 0 | ... Q26: =-SUMIFS(DB_Complessivo!$E:$E,DB_Complessivo!$A:$A,"ACT",DB_Complessivo!$H:$H,$A26,DB_Complessivo!$B:$B,Q$2)/1000 -> 0
A27: 36.ANT | C27: Utilizzo Linee Anticipo Fatture | D27: =-SUMIFS(DB_Complessivo!$E:$E,DB_Complessivo!$A:$A,"ACT",DB_Complessivo!$H:$H,$A27,DB_Complessivo!$B:$B,D$2)/1000 -> 492.45933 | E27: =-SUMIFS(DB_Complessivo!$E:$E,DB_Complessivo!$A:$A,"ACT",DB_Complessivo!$H:$H,$A27,DB_Complessivo!$B:$B,E$2)/1000 -> 530.76374 | F27: =-SUMIFS(DB_Complessivo!$E:$E,DB_Complessivo!$A:$A,"ACT",DB_Complessivo!$H:$H,$A27,DB_Complessivo!$B:$B,F$2)/1000 -> 530.76374 | G27: =-SUMIFS(DB_Complessivo!$E:$E,DB_Complessivo!$A:$A,"ACT",DB_Complessivo!$H:$H,$A27,DB_Complessivo!$B:$B,G$2)/1000 -> 38.30441 | H27: =-SUMIFS(DB_Complessivo!$E:$E,DB_Complessivo!$A:$A,"ACT",DB_Complessivo!$H:$H,$A27,DB_Complessivo!$B:$B,H$2)/1000 -> 38.30441 | I27: =-SUMIFS(DB_Complessivo!$E:$E,DB_Complessivo!$A:$A,"ACT",DB_Complessivo!$H:$H,$A27,DB_Complessivo!$B:$B,I$2)/1000 -> 38.30441 | J27: =-SUMIFS(DB_Complessivo!$E:$E,DB_Complessivo!$A:$A,"ACT",DB_Complessivo!$H:$H,$A27,DB_Complessivo!$B:$B,J$2)/1000 -> 20.32174 | K27: =-SUMIFS(DB_Complessivo!$E:$E,DB_Complessivo!$A:$A,"ACT",DB_Complessivo!$H:$H,$A27,DB_Complessivo!$B:$B,K$2)/1000 -> 0 | ... Q27: =-SUMIFS(DB_Complessivo!$E:$E,DB_Complessivo!$A:$A,"ACT",DB_Complessivo!$H:$H,$A27,DB_Complessivo!$B:$B,Q$2)/1000 -> 0
C28: PFN a Breve Termine | D28: =SUM(D26:D27) -> -2263.2018 | E28: =SUM(E26:E27) -> -2424.8521 | F28: =SUM(F26:F27) -> -2449.7881 | G28: =SUM(G26:G27) -> -86.62653 | H28: =SUM(H26:H27) -> -308.52726 | I28: =SUM(I26:I27) -> -342.51872 | J28: =SUM(J26:J27) -> -3001.8684 | K28: =SUM(K26:K27) -> 0 | ... Q28: =SUM(Q26:Q27) -> 0
A30: 37.DFIN | C30: Debiti Finanziari (MLT) | D30: =-SUMIFS(DB_Complessivo!$E:$E,DB_Complessivo!$A:$A,"ACT",DB_Complessivo!$H:$H,$A30,DB_Complessivo!$B:$B,D$2)/1000 -> 2345.1617 | E30: =-SUMIFS(DB_Complessivo!$E:$E,DB_Complessivo!$A:$A,"ACT",DB_Complessivo!$H:$H,$A30,DB_Complessivo!$B:$B,E$2)/1000 -> 2250.9372 | F30: =-SUMIFS(DB_Complessivo!$E:$E,DB_Complessivo!$A:$A,"ACT",DB_Complessivo!$H:$H,$A30,DB_Complessivo!$B:$B,F$2)/1000 -> 2236.0209 | G30: =-SUMIFS(DB_Complessivo!$E:$E,DB_Complessivo!$A:$A,"ACT",DB_Complessivo!$H:$H,$A30,DB_Complessivo!$B:$B,G$2)/1000 -> -109.14078 | H30: =-SUMIFS(DB_Complessivo!$E:$E,DB_Complessivo!$A:$A,"ACT",DB_Complessivo!$H:$H,$A30,DB_Complessivo!$B:$B,H$2)/1000 -> -109.14078 | I30: =-SUMIFS(DB_Complessivo!$E:$E,DB_Complessivo!$A:$A,"ACT",DB_Complessivo!$H:$H,$A30,DB_Complessivo!$B:$B,I$2)/1000 -> -109.14078 | J30: =-SUMIFS(DB_Complessivo!$E:$E,DB_Complessivo!$A:$A,"ACT",DB_Complessivo!$H:$H,$A30,DB_Complessivo!$B:$B,J$2)/1000 -> 2062.2307 | K30: =-SUMIFS(DB_Complessivo!$E:$E,DB_Complessivo!$A:$A,"ACT",DB_Complessivo!$H:$H,$A30,DB_Complessivo!$B:$B,K$2)/1000 -> 0 | ... Q30: =-SUMIFS(DB_Complessivo!$E:$E,DB_Complessivo!$A:$A,"ACT",DB_Complessivo!$H:$H,$A30,DB_Complessivo!$B:$B,Q$2)/1000 -> 0
A31: 25.I.FIN | C31: Immobilizzazioni Finanziarie | D31: =-SUMIFS(DB_Complessivo!$E:$E,DB_Complessivo!$A:$A,"ACT",DB_Complessivo!$H:$H,$A31,DB_Complessivo!$B:$B,D$2)/1000 -> -1140.2291 | E31: =-SUMIFS(DB_Complessivo!$E:$E,DB_Complessivo!$A:$A,"ACT",DB_Complessivo!$H:$H,$A31,DB_Complessivo!$B:$B,E$2)/1000 -> -1140.2291 | F31: =-SUMIFS(DB_Complessivo!$E:$E,DB_Complessivo!$A:$A,"ACT",DB_Complessivo!$H:$H,$A31,DB_Complessivo!$B:$B,F$2)/1000 -> -1140.2291 | G31: =-SUMIFS(DB_Complessivo!$E:$E,DB_Complessivo!$A:$A,"ACT",DB_Complessivo!$H:$H,$A31,DB_Complessivo!$B:$B,G$2)/1000 -> 0 | H31: =-SUMIFS(DB_Complessivo!$E:$E,DB_Complessivo!$A:$A,"ACT",DB_Complessivo!$H:$H,$A31,DB_Complessivo!$B:$B,H$2)/1000 -> 0 | I31: =-SUMIFS(DB_Complessivo!$E:$E,DB_Complessivo!$A:$A,"ACT",DB_Complessivo!$H:$H,$A31,DB_Complessivo!$B:$B,I$2)/1000 -> 0 | J31: =-SUMIFS(DB_Complessivo!$E:$E,DB_Complessivo!$A:$A,"ACT",DB_Complessivo!$H:$H,$A31,DB_Complessivo!$B:$B,J$2)/1000 -> -1118.8116 | K31: =-SUMIFS(DB_Complessivo!$E:$E,DB_Complessivo!$A:$A,"ACT",DB_Complessivo!$H:$H,$A31,DB_Complessivo!$B:$B,K$2)/1000 -> 0 | ... Q31: =-SUMIFS(DB_Complessivo!$E:$E,DB_Complessivo!$A:$A,"ACT",DB_Complessivo!$H:$H,$A31,DB_Complessivo!$B:$B,Q$2)/1000 -> 0
C32: PFN a ML Termine | D32: =SUM(D30:D31) -> 1204.9326 | E32: =SUM(E30:E31) -> 1110.7081 | F32: =SUM(F30:F31) -> 1095.7918 | G32: =SUM(G30:G31) -> -109.14078 | H32: =SUM(H30:H31) -> -109.14078 | I32: =SUM(I30:I31) -> -109.14078 | J32: =SUM(J30:J31) -> 943.41911 | K32: =SUM(K30:K31) -> 0 | ... Q32: =SUM(Q30:Q31) -> 0
C34: POSIZIONE FINANZIARIA NETTA | D34: =D28+D32 -> -1058.2692 | E34: =E28+E32 -> -1314.144 | F34: =F28+F32 -> -1353.9963 | G34: =G28+G32 -> -195.76731 | H34: =H28+H32 -> -417.66804 | I34: =I28+I32 -> -451.6595 | J34: =J28+J32 -> -2058.4493 | K34: =K28+K32 -> 0 | ... Q34: =Q28+Q32 -> 0
A36: 34.CS | C36: Capitale | D36: =-SUMIFS(DB_Complessivo!$E:$E,DB_Complessivo!$A:$A,"ACT",DB_Complessivo!$H:$H,$A36,DB_Complessivo!$B:$B,D$2)/1000 -> 907.3 | E36: =-SUMIFS(DB_Complessivo!$E:$E,DB_Complessivo!$A:$A,"ACT",DB_Complessivo!$H:$H,$A36,DB_Complessivo!$B:$B,E$2)/1000 -> 907.5 | F36: =-SUMIFS(DB_Complessivo!$E:$E,DB_Complessivo!$A:$A,"ACT",DB_Complessivo!$H:$H,$A36,DB_Complessivo!$B:$B,F$2)/1000 -> 907.6 | G36: =-SUMIFS(DB_Complessivo!$E:$E,DB_Complessivo!$A:$A,"ACT",DB_Complessivo!$H:$H,$A36,DB_Complessivo!$B:$B,G$2)/1000 -> 0.8 | H36: =-SUMIFS(DB_Complessivo!$E:$E,DB_Complessivo!$A:$A,"ACT",DB_Complessivo!$H:$H,$A36,DB_Complessivo!$B:$B,H$2)/1000 -> 144.4 | I36: =-SUMIFS(DB_Complessivo!$E:$E,DB_Complessivo!$A:$A,"ACT",DB_Complessivo!$H:$H,$A36,DB_Complessivo!$B:$B,I$2)/1000 -> 144.45 | J36: =-SUMIFS(DB_Complessivo!$E:$E,DB_Complessivo!$A:$A,"ACT",DB_Complessivo!$H:$H,$A36,DB_Complessivo!$B:$B,J$2)/1000 -> 951.3 | K36: =-SUMIFS(DB_Complessivo!$E:$E,DB_Complessivo!$A:$A,"ACT",DB_Complessivo!$H:$H,$A36,DB_Complessivo!$B:$B,K$2)/1000 -> 0 | ... Q36: =-SUMIFS(DB_Complessivo!$E:$E,DB_Complessivo!$A:$A,"ACT",DB_Complessivo!$H:$H,$A36,DB_Complessivo!$B:$B,Q$2)/1000 -> 0
A37: 35.RIS | C37: Riserve | D37: =-SUMIFS(DB_Complessivo!$E:$E,DB_Complessivo!$A:$A,"ACT",DB_Complessivo!$H:$H,$A37,DB_Complessivo!$B:$B,D$2)/1000 -> 282.49888 | E37: =-SUMIFS(DB_Complessivo!$E:$E,DB_Complessivo!$A:$A,"ACT",DB_Complessivo!$H:$H,$A37,DB_Complessivo!$B:$B,E$2)/1000 -> 1236.0982 | F37: =-SUMIFS(DB_Complessivo!$E:$E,DB_Complessivo!$A:$A,"ACT",DB_Complessivo!$H:$H,$A37,DB_Complessivo!$B:$B,F$2)/1000 -> 1236.0982 | G37: =-SUMIFS(DB_Complessivo!$E:$E,DB_Complessivo!$A:$A,"ACT",DB_Complessivo!$H:$H,$A37,DB_Complessivo!$B:$B,G$2)/1000 -> 0 | H37: =-SUMIFS(DB_Complessivo!$E:$E,DB_Complessivo!$A:$A,"ACT",DB_Complessivo!$H:$H,$A37,DB_Complessivo!$B:$B,H$2)/1000 -> 0 | I37: =-SUMIFS(DB_Complessivo!$E:$E,DB_Complessivo!$A:$A,"ACT",DB_Complessivo!$H:$H,$A37,DB_Complessivo!$B:$B,I$2)/1000 -> 0 | J37: =-SUMIFS(DB_Complessivo!$E:$E,DB_Complessivo!$A:$A,"ACT",DB_Complessivo!$H:$H,$A37,DB_Complessivo!$B:$B,J$2)/1000 -> 1075.5199 | K37: =-SUMIFS(DB_Complessivo!$E:$E,DB_Complessivo!$A:$A,"ACT",DB_Complessivo!$H:$H,$A37,DB_Complessivo!$B:$B,K$2)/1000 -> 0 | ... Q37: =-SUMIFS(DB_Complessivo!$E:$E,DB_Complessivo!$A:$A,"ACT",DB_Complessivo!$H:$H,$A37,DB_Complessivo!$B:$B,Q$2)/1000 -> 0
C38: Utile/Perdita di Esercizio | D38: 940.53884 | E38: =+CE_YtD!D33 -> 97.772983 | F38: =+CE_YtD!E33 -> 59.548233 | G38: =+CE_YtD!F33 -> 29.457753 | H38: =+CE_YtD!G33 -> 93.684583 | I38: =+CE_YtD!H33 -> 115.91687 | J38: =+CE_YtD!I33 -> 75.48717 | K38: =+CE_YtD!J33 -> 0 | L38: =+CE_YtD!K33 -> 0 | ... Q38: =+CE_YtD!P33 -> 0
C39: PATRIMONIO NETTO | D39: =SUM(D36:D38) -> 2130.3377 | E39: =SUM(E36:E38) -> 2241.3712 | F39: =SUM(F36:F38) -> 2203.2464 | G39: =SUM(G36:G38) -> 30.257753 | H39: =SUM(H36:H38) -> 238.08458 | I39: =SUM(I36:I38) -> 260.36687 | J39: =SUM(J36:J38) -> 2102.307 | K39: =SUM(K36:K38) -> 0 | ... Q39: =SUM(Q36:Q38) -> 0
C41: TOTALE FONTI FINANZIARIE | D41: =SUM(D34,D39) -> 1072.0685 | E41: =SUM(E34,E39) -> 927.22715 | F41: =SUM(F34,F39) -> 849.2501 | G41: =SUM(G34,G39) -> -165.50956 | H41: =SUM(H34,H39) -> -179.58346 | I41: =SUM(I34,I39) -> -191.29263 | J41: =SUM(J34,J39) -> 43.857723 | K41: =SUM(K34,K39) -> 0 | ... Q41: =SUM(Q34,Q39) -> 0
C44: Check | D44: =D24-D41 -> 0 | E44: =E24-E41 -> 1.0231815e-12 | F44: =F24-F41 -> 1.5916157e-12 | G44: =G24-G41 -> 1.5063506e-12 | H44: =H24-H41 -> 9.6633812e-13 | I44: =I24-I41 -> 4.3769433e-12 | J44: =J24-J41 -> 1.7053026e-13 | K44: =K24-K41 -> 0 | ... Q44: =Q24-Q41 -> 0

Sheet FCT
C1: CONTO ECONOMICO di PROGETTO QUID | D1: =IF(D2<=INDICE!$B$2,"ACT","BDG") -> ACT | E1: =IF(E2<=INDICE!$B$2,"ACT","BDG") -> ACT | F1: =IF(F2<=INDICE!$B$2,"ACT","BDG") -> ACT | G1: =IF(G2<=INDICE!$B$2,"ACT","BDG") -> ACT | H1: =IF(H2<=INDICE!$B$2,"ACT","BDG") -> ACT | I1: =IF(I2<=INDICE!$B$2,"ACT","BDG") -> ACT | J1: =IF(J2<=INDICE!$B$2,"ACT","REV_BDG") -> REV_BDG | K1: =IF(K2<=INDICE!$B$2,"ACT","REV_BDG") -> REV_BDG | L1: =IF(L2<=INDICE!$B$2,"ACT","REV_BDG") -> REV_BDG | M1: =IF(M2<=INDICE!$B$2,"ACT","REV_BDG") -> REV_BDG | N1: =IF(N2<=INDICE!$B$2,"ACT","REV_BDG") -> REV_BDG | O1: =IF(O2<=INDICE!$B$2,"ACT","REV_BDG") -> REV_BDG
C2: EUR/000 | D2: 45688 | E2: =EOMONTH(D2,1) -> 45716 | F2: =EOMONTH(E2,1) -> 45747 | G2: =EOMONTH(F2,1) -> 45777 | H2: =EOMONTH(G2,1) -> 45808 | I2: =EOMONTH(H2,1) -> 45838 | J2: =EOMONTH(I2,1) -> 45869 | K2: =EOMONTH(J2,1) -> 45900 | L2: =EOMONTH(K2,1) -> 45930 | ... O2: =EOMONTH(N2,1) -> 46022
A3: RICOP | C3: Ricavi Netti di Vendita | D3: =-SUMIFS(DB_Complessivo!$E:$E,DB_Complessivo!$A:$A,"ACT",DB_Complessivo!$B:$B,D$2,DB_Complessivo!$H:$H,$A3)/1000 -> 390.27999 | E3: =-(SUMIFS(DB_Complessivo!$E:$E,DB_Complessivo!$A:$A,E$1,DB_Complessivo!$B:$B,E$2,DB_Complessivo!$H:$H,$A3)-SUMIFS(DB_Complessivo!$E:$E,DB_Complessivo!$A:$A,E$1,DB_Complessivo!$B:$B,D$2,DB_Complessivo!$H:$H,$A3))/1000 -> 481.76091 | F3: =-(SUMIFS(DB_Complessivo!$E:$E,DB_Complessivo!$A:$A,F$1,DB_Complessivo!$B:$B,F$2,DB_Complessivo!$H:$H,$A3)-SUMIFS(DB_Complessivo!$E:$E,DB_Complessivo!$A:$A,F$1,DB_Complessivo!$B:$B,E$2,DB_Complessivo!$H:$H,$A3))/1000 -> 604.69716 | G3: =-(SUMIFS(DB_Complessivo!$E:$E,DB_Complessivo!$A:$A,G$1,DB_Complessivo!$B:$B,G$2,DB_Complessivo!$H:$H,$A3)-SUMIFS(DB_Complessivo!$E:$E,DB_Complessivo!$A:$A,G$1,DB_Complessivo!$B:$B,F$2,DB_Complessivo!$H:$H,$A3))/1000 -> 713.30061 | H3: =-(SUMIFS(DB_Complessivo!$E:$E,DB_Complessivo!$A:$A,H$1,DB_Complessivo!$B:$B,H$2,DB_Complessivo!$H:$H,$A3)-SUMIFS(DB_Complessivo!$E:$E,DB_Complessivo!$A:$A,H$1,DB_Complessivo!$B:$B,G$2,DB_Complessivo!$H:$H,$A3))/1000 -> 601.76113 | I3: =-(SUMIFS(DB_Complessivo!$E:$E,DB_Complessivo!$A:$A,I$1,DB_Complessivo!$B:$B,I$2,DB_Complessivo!$H:$H,$A3)-SUMIFS(DB_Complessivo!$E:$E,DB_Complessivo!$A:$A,I$1,DB_Complessivo!$B:$B,H$2,DB_Complessivo!$H:$H,$A3))/1000 -> 342.96388 | J3: =-(SUMIFS(DB_Complessivo!$E:$E,DB_Complessivo!$A:$A,J$1,DB_Complessivo!$B:$B,J$2,DB_Complessivo!$H:$H,$A3)-SUMIFS(DB_Complessivo!$E:$E,DB_Complessivo!$A:$A,J$1,DB_Complessivo!$B:$B,I$2,DB_Complessivo!$H:$H,$A3))/1000 -> 355.87977 | K3: =-(SUMIFS(DB_Complessivo!$E:$E,DB_Complessivo!$A:$A,K$1,DB_Complessivo!$B:$B,K$2,DB_Complessivo!$H:$H,$A3)-SUMIFS(DB_Complessivo!$E:$E,DB_Complessivo!$A:$A,K$1,DB_Complessivo!$B:$B,J$2,DB_Complessivo!$H:$H,$A3))/1000 -> 235.87977 | L3: =-(SUMIFS(DB_Complessivo!$E:$E,DB_Complessivo!$A:$A,L$1,DB_Complessivo!$B:$B,L$2,DB_Complessivo!$H:$H,$A3)-SUMIFS(DB_Complessivo!$E:$E,DB_Complessivo!$A:$A,L$1,DB_Complessivo!$B:$B,K$2,DB_Complessivo!$H:$H,$A3))/1000 -> 805.87977 | ... O3: =-(SUMIFS(DB_Complessivo!$E:$E,DB_Complessivo!$A:$A,O$1,DB_Complessivo!$B:$B,O$2,DB_Complessivo!$H:$H,$A3)-SUMIFS(DB_Complessivo!$E:$E,DB_Complessivo!$A:$A,O$1,DB_Complessivo!$B:$B,N$2,DB_Complessivo!$H:$H,$A3))/1000 -> 355.87977
A4: CORR | C4: Corrispettivi | D4: =-SUMIFS(DB_Complessivo!$E:$E,DB_Complessivo!$A:$A,"ACT",DB_Complessivo!$B:$B,D$2,DB_Complessivo!$H:$H,$A4)/1000 -> 38.97781 | E4: =-(SUMIFS(DB_Complessivo!$E:$E,DB_Complessivo!$A:$A,E$1,DB_Complessivo!$B:$B,E$2,DB_Complessivo!$H:$H,$A4)-SUMIFS(DB_Complessivo!$E:$E,DB_Complessivo!$A:$A,E$1,DB_Complessivo!$B:$B,D$2,DB_Complessivo!$H:$H,$A4))/1000 -> 33.54154 | F4: =-(SUMIFS(DB_Complessivo!$E:$E,DB_Complessivo!$A:$A,F$1,DB_Complessivo!$B:$B,F$2,DB_Complessivo!$H:$H,$A4)-SUMIFS(DB_Complessivo!$E:$E,DB_Complessivo!$A:$A,F$1,DB_Complessivo!$B:$B,E$2,DB_Complessivo!$H:$H,$A4))/1000 -> 34.46133 | G4: =-(SUMIFS(DB_Complessivo!$E:$E,DB_Complessivo!$A:$A,G$1,DB_Complessivo!$B:$B,G$2,DB_Complessivo!$H:$H,$A4)-SUMIFS(DB_Complessivo!$E:$E,DB_Complessivo!$A:$A,G$1,DB_Complessivo!$B:$B,F$2,DB_Complessivo!$H:$H,$A4))/1000 -> 12.16945 | H4: =-(SUMIFS(DB_Complessivo!$E:$E,DB_Complessivo!$A:$A,H$1,DB_Complessivo!$B:$B,H$2,DB_Complessivo!$H:$H,$A4)-SUMIFS(DB_Complessivo!$E:$E,DB_Complessivo!$A:$A,H$1,DB_Complessivo!$B:$B,G$2,DB_Complessivo!$H:$H,$A4))/1000 -> 14.21431 | I4: =-(SUMIFS(DB_Complessivo!$E:$E,DB_Complessivo!$A:$A,I$1,DB_Complessivo!$B:$B,I$2,DB_Complessivo!$H:$H,$A4)-SUMIFS(DB_Complessivo!$E:$E,DB_Complessivo!$A:$A,I$1,DB_Complessivo!$B:$B,H$2,DB_Complessivo!$H:$H,$A4))/1000 -> 12.07022 | J4: =-(SUMIFS(DB_Complessivo!$E:$E,DB_Complessivo!$A:$A,J$1,DB_Complessivo!$B:$B,J$2,DB_Complessivo!$H:$H,$A4)-SUMIFS(DB_Complessivo!$E:$E,DB_Complessivo!$A:$A,J$1,DB_Complessivo!$B:$B,I$2,DB_Complessivo!$H:$H,$A4))/1000 -> 15 | K4: =-(SUMIFS(DB_Complessivo!$E:$E,DB_Complessivo!$A:$A,K$1,DB_Complessivo!$B:$B,K$2,DB_Complessivo!$H:$H,$A4)-SUMIFS(DB_Complessivo!$E:$E,DB_Complessivo!$A:$A,K$1,DB_Complessivo!$B:$B,J$2,DB_Complessivo!$H:$H,$A4))/1000 -> 8 | L4: =-(SUMIFS(DB_Complessivo!$E:$E,DB_Complessivo!$A:$A,L$1,DB_Complessivo!$B:$B,L$2,DB_Complessivo!$H:$H,$A4)-SUMIFS(DB_Complessivo!$E:$E,DB_Complessivo!$A:$A,L$1,DB_Complessivo!$B:$B,K$2,DB_Complessivo!$H:$H,$A4))/1000 -> 12 | ... O4: =-(SUMIFS(DB_Complessivo!$E:$E,DB_Complessivo!$A:$A,O$1,DB_Complessivo!$B:$B,O$2,DB_Complessivo!$H:$H,$A4)-SUMIFS(DB_Complessivo!$E:$E,DB_Complessivo!$A:$A,O$1,DB_Complessivo!$B:$B,N$2,DB_Complessivo!$H:$H,$A4))/1000 -> 12
A5: VARPF | C5: Variazione magazzino PF | D5: =-SUMIFS(DB_Complessivo!$E:$E,DB_Complessivo!$A:$A,"ACT",DB_Complessivo!$B:$B,D$2,DB_Complessivo!$H:$H,$A5)/1000 -> 84.21847 | E5: =-(SUMIFS(DB_Complessivo!$E:$E,DB_Complessivo!$A:$A,E$1,DB_Complessivo!$B:$B,E$2,DB_Complessivo!$H:$H,$A5)-SUMIFS(DB_Complessivo!$E:$E,DB_Complessivo!$A:$A,E$1,DB_Complessivo!$B:$B,D$2,DB_Complessivo!$H:$H,$A5))/1000 -> 0 | F5: =-(SUMIFS(DB_Complessivo!$E:$E,DB_Complessivo!$A:$A,F$1,DB_Complessivo!$B:$B,F$2,DB_Complessivo!$H:$H,$A5)-SUMIFS(DB_Complessivo!$E:$E,DB_Complessivo!$A:$A,F$1,DB_Complessivo!$B:$B,E$2,DB_Complessivo!$H:$H,$A5))/1000 -> -47.58835 | G5: =-(SUMIFS(DB_Complessivo!$E:$E,DB_Complessivo!$A:$A,G$1,DB_Complessivo!$B:$B,G$2,DB_Complessivo!$H:$H,$A5)-SUMIFS(DB_Complessivo!$E:$E,DB_Complessivo!$A:$A,G$1,DB_Complessivo!$B:$B,F$2,DB_Complessivo!$H:$H,$A5))/1000 -> -40.86824 | H5: =-(SUMIFS(DB_Complessivo!$E:$E,DB_Complessivo!$A:$A,H$1,DB_Complessivo!$B:$B,H$2,DB_Complessivo!$H:$H,$A5)-SUMIFS(DB_Complessivo!$E:$E,DB_Complessivo!$A:$A,H$1,DB_Complessivo!$B:$B,G$2,DB_Complessivo!$H:$H,$A5))/1000 -> 54.72493 | I5: =-(SUMIFS(DB_Complessivo!$E:$E,DB_Complessivo!$A:$A,I$1,DB_Complessivo!$B:$B,I$2,DB_Complessivo!$H:$H,$A5)-SUMIFS(DB_Complessivo!$E:$E,DB_Complessivo!$A:$A,I$1,DB_Complessivo!$B:$B,H$2,DB_Complessivo!$H:$H,$A5))/1000 -> -81.21015 | J5: =-(SUMIFS(DB_Complessivo!$E:$E,DB_Complessivo!$A:$A,J$1,DB_Complessivo!$B:$B,J$2,DB_Complessivo!$H:$H,$A5)-SUMIFS(DB_Complessivo!$E:$E,DB_Complessivo!$A:$A,J$1,DB_Complessivo!$B:$B,I$2,DB_Complessivo!$H:$H,$A5))/1000 -> 0 | K5: =-(SUMIFS(DB_Complessivo!$E:$E,DB_Complessivo!$A:$A,K$1,DB_Complessivo!$B:$B,K$2,DB_Complessivo!$H:$H,$A5)-SUMIFS(DB_Complessivo!$E:$E,DB_Complessivo!$A:$A,K$1,DB_Complessivo!$B:$B,J$2,DB_Complessivo!$H:$H,$A5))/1000 -> 0 | L5: =-(SUMIFS(DB_Complessivo!$E:$E,DB_Complessivo!$A:$A,L$1,DB_Complessivo!$B:$B,L$2,DB_Complessivo!$H:$H,$A5)-SUMIFS(DB_Complessivo!$E:$E,DB_Complessivo!$A:$A,L$1,DB_Complessivo!$B:$B,K$2,DB_Complessivo!$H:$H,$A5))/1000 -> 0 | ... O5: =-(SUMIFS(DB_Complessivo!$E:$E,DB_Complessivo!$A:$A,O$1,DB_Complessivo!$B:$B,O$2,DB_Complessivo!$H:$H,$A5)-SUMIFS(DB_Complessivo!$E:$E,DB_Complessivo!$A:$A,O$1,DB_Complessivo!$B:$B,N$2,DB_Complessivo!$H:$H,$A5))/1000 -> 0
A6: ALTRI | C6: Altri Ricavi | D6: =-SUMIFS(DB_Complessivo!$E:$E,DB_Complessivo!$A:$A,"ACT",DB_Complessivo!$B:$B,D$2,DB_Complessivo!$H:$H,$A6)/1000 -> 75.82325 | E6: =-(SUMIFS(DB_Complessivo!$E:$E,DB_Complessivo!$A:$A,E$1,DB_Complessivo!$B:$B,E$2,DB_Complessivo!$H:$H,$A6)-SUMIFS(DB_Complessivo!$E:$E,DB_Complessivo!$A:$A,E$1,DB_Complessivo!$B:$B,D$2,DB_Complessivo!$H:$H,$A6))/1000 -> 1.9185 | F6: =-(SUMIFS(DB_Complessivo!$E:$E,DB_Complessivo!$A:$A,F$1,DB_Complessivo!$B:$B,F$2,DB_Complessivo!$H:$H,$A6)-SUMIFS(DB_Complessivo!$E:$E,DB_Complessivo!$A:$A,F$1,DB_Complessivo!$B:$B,E$2,DB_Complessivo!$H:$H,$A6))/1000 -> 41.47551 | G6: =-(SUMIFS(DB_Complessivo!$E:$E,DB_Complessivo!$A:$A,G$1,DB_Complessivo!$B:$B,G$2,DB_Complessivo!$H:$H,$A6)-SUMIFS(DB_Complessivo!$E:$E,DB_Complessivo!$A:$A,G$1,DB_Complessivo!$B:$B,F$2,DB_Complessivo!$H:$H,$A6))/1000 -> 41.57714 | H6: =-(SUMIFS(DB_Complessivo!$E:$E,DB_Complessivo!$A:$A,H$1,DB_Complessivo!$B:$B,H$2,DB_Complessivo!$H:$H,$A6)-SUMIFS(DB_Complessivo!$E:$E,DB_Complessivo!$A:$A,H$1,DB_Complessivo!$B:$B,G$2,DB_Complessivo!$H:$H,$A6))/1000 -> 18.207 | I6: =-(SUMIFS(DB_Complessivo!$E:$E,DB_Complessivo!$A:$A,I$1,DB_Complessivo!$B:$B,I$2,DB_Complessivo!$H:$H,$A6)-SUMIFS(DB_Complessivo!$E:$E,DB_Complessivo!$A:$A,I$1,DB_Complessivo!$B:$B,H$2,DB_Complessivo!$H:$H,$A6))/1000 -> 414.21038 | J6: =-(SUMIFS(DB_Complessivo!$E:$E,DB_Complessivo!$A:$A,J$1,DB_Complessivo!$B:$B,J$2,DB_Complessivo!$H:$H,$A6)-SUMIFS(DB_Complessivo!$E:$E,DB_Complessivo!$A:$A,J$1,DB_Complessivo!$B:$B,I$2,DB_Complessivo!$H:$H,$A6))/1000 -> 111.01306 | K6: =-(SUMIFS(DB_Complessivo!$E:$E,DB_Complessivo!$A:$A,K$1,DB_Complessivo!$B:$B,K$2,DB_Complessivo!$H:$H,$A6)-SUMIFS(DB_Complessivo!$E:$E,DB_Complessivo!$A:$A,K$1,DB_Complessivo!$B:$B,J$2,DB_Complessivo!$H:$H,$A6))/1000 -> 111.01306 | L6: =-(SUMIFS(DB_Complessivo!$E:$E,DB_Complessivo!$A:$A,L$1,DB_Complessivo!$B:$B,L$2,DB_Complessivo!$H:$H,$A6)-SUMIFS(DB_Complessivo!$E:$E,DB_Complessivo!$A:$A,L$1,DB_Complessivo!$B:$B,K$2,DB_Complessivo!$H:$H,$A6))/1000 -> 111.01306 | ... O6: =-(SUMIFS(DB_Complessivo!$E:$E,DB_Complessivo!$A:$A,O$1,DB_Complessivo!$B:$B,O$2,DB_Complessivo!$H:$H,$A6)-SUMIFS(DB_Complessivo!$E:$E,DB_Complessivo!$A:$A,O$1,DB_Complessivo!$B:$B,N$2,DB_Complessivo!$H:$H,$A6))/1000 -> 111.01306
A7: SUBTOTALE | C7: Ricavi | D7: =SUM(D3:D6) -> 589.29952 | E7: =SUM(E3:E6) -> 517.22095 | F7: =SUM(F3:F6) -> 633.04565 | G7: =SUM(G3:G6) -> 726.17896 | H7: =SUM(H3:H6) -> 688.90737 | I7: =SUM(I3:I6) -> 688.03433 | J7: =SUM(J3:J6) -> 481.89283 | K7: =SUM(K3:K6) -> 354.89283 | ... O7: =SUM(O3:O6) -> 478.89283
A8: ACQDI | C8: Acquisti diretti di produzione | D8: =-SUMIFS(DB_Complessivo!$E:$E,DB_Complessivo!$A:$A,"ACT",DB_Complessivo!$B:$B,D$2,DB_Complessivo!$H:$H,$A8)/1000 -> -39.73812 | E8: =-(SUMIFS(DB_Complessivo!$E:$E,DB_Complessivo!$A:$A,E$1,DB_Complessivo!$B:$B,E$2,DB_Complessivo!$H:$H,$A8)-SUMIFS(DB_Complessivo!$E:$E,DB_Complessivo!$A:$A,E$1,DB_Complessivo!$B:$B,D$2,DB_Complessivo!$H:$H,$A8))/1000 -> -38.27117 | F8: =-(SUMIFS(DB_Complessivo!$E:$E,DB_Complessivo!$A:$A,F$1,DB_Complessivo!$B:$B,F$2,DB_Complessivo!$H:$H,$A8)-SUMIFS(DB_Complessivo!$E:$E,DB_Complessivo!$A:$A,F$1,DB_Complessivo!$B:$B,E$2,DB_Complessivo!$H:$H,$A8))/1000 -> -33.32012 | G8: =-(SUMIFS(DB_Complessivo!$E:$E,DB_Complessivo!$A:$A,G$1,DB_Complessivo!$B:$B,G$2,DB_Complessivo!$H:$H,$A8)-SUMIFS(DB_Complessivo!$E:$E,DB_Complessivo!$A:$A,G$1,DB_Complessivo!$B:$B,F$2,DB_Complessivo!$H:$H,$A8))/1000 -> -54.3364 | H8: =-(SUMIFS(DB_Complessivo!$E:$E,DB_Complessivo!$A:$A,H$1,DB_Complessivo!$B:$B,H$2,DB_Complessivo!$H:$H,$A8)-SUMIFS(DB_Complessivo!$E:$E,DB_Complessivo!$A:$A,H$1,DB_Complessivo!$B:$B,G$2,DB_Complessivo!$H:$H,$A8))/1000 -> -65.29559 | I8: =-(SUMIFS(DB_Complessivo!$E:$E,DB_Complessivo!$A:$A,I$1,DB_Complessivo!$B:$B,I$2,DB_Complessivo!$H:$H,$A8)-SUMIFS(DB_Complessivo!$E:$E,DB_Complessivo!$A:$A,I$1,DB_Complessivo!$B:$B,H$2,DB_Complessivo!$H:$H,$A8))/1000 -> -82.87855 | J8: =-(SUMIFS(DB_Complessivo!$E:$E,DB_Complessivo!$A:$A,J$1,DB_Complessivo!$B:$B,J$2,DB_Complessivo!$H:$H,$A8)-SUMIFS(DB_Complessivo!$E:$E,DB_Complessivo!$A:$A,J$1,DB_Complessivo!$B:$B,I$2,DB_Complessivo!$H:$H,$A8))/1000 -> -31.580405 | K8: =-(SUMIFS(DB_Complessivo!$E:$E,DB_Complessivo!$A:$A,K$1,DB_Complessivo!$B:$B,K$2,DB_Complessivo!$H:$H,$A8)-SUMIFS(DB_Complessivo!$E:$E,DB_Complessivo!$A:$A,K$1,DB_Complessivo!$B:$B,J$2,DB_Complessivo!$H:$H,$A8))/1000 -> -21.211801 | L8: =-(SUMIFS(DB_Complessivo!$E:$E,DB_Complessivo!$A:$A,L$1,DB_Complessivo!$B:$B,L$2,DB_Complessivo!$H:$H,$A8)-SUMIFS(DB_Complessivo!$E:$E,DB_Complessivo!$A:$A,L$1,DB_Complessivo!$B:$B,K$2,DB_Complessivo!$H:$H,$A8))/1000 -> -70.462669 | ... O8: =-(SUMIFS(DB_Complessivo!$E:$E,DB_Complessivo!$A:$A,O$1,DB_Complessivo!$B:$B,O$2,DB_Complessivo!$H:$H,$A8)-SUMIFS(DB_Complessivo!$E:$E,DB_Complessivo!$A:$A,O$1,DB_Complessivo!$B:$B,N$2,DB_Complessivo!$H:$H,$A8))/1000 -> -31.580405
A9: VARMP | C9: Variazioni magazzino MP / SL | D9: =-SUMIFS(DB_Complessivo!$E:$E,DB_Complessivo!$A:$A,"ACT",DB_Complessivo!$B:$B,D$2,DB_Complessivo!$H:$H,$A9)/1000 -> 141.30301 | E9: =-(SUMIFS(DB_Complessivo!$E:$E,DB_Complessivo!$A:$A,E$1,DB_Complessivo!$B:$B,E$2,DB_Complessivo!$H:$H,$A9)-SUMIFS(DB_Complessivo!$E:$E,DB_Complessivo!$A:$A,E$1,DB_Complessivo!$B:$B,D$2,DB_Complessivo!$H:$H,$A9))/1000 -> 0 | F9: =-(SUMIFS(DB_Complessivo!$E:$E,DB_Complessivo!$A:$A,F$1,DB_Complessivo!$B:$B,F$2,DB_Complessivo!$H:$H,$A9)-SUMIFS(DB_Complessivo!$E:$E,DB_Complessivo!$A:$A,F$1,DB_Complessivo!$B:$B,E$2,DB_Complessivo!$H:$H,$A9))/1000 -> -143.99539 | G9: =-(SUMIFS(DB_Complessivo!$E:$E,DB_Complessivo!$A:$A,G$1,DB_Complessivo!$B:$B,G$2,DB_Complessivo!$H:$H,$A9)-SUMIFS(DB_Complessivo!$E:$E,DB_Complessivo!$A:$A,G$1,DB_Complessivo!$B:$B,F$2,DB_Complessivo!$H:$H,$A9))/1000 -> 2.72011 | H9: =-(SUMIFS(DB_Complessivo!$E:$E,DB_Complessivo!$A:$A,H$1,DB_Complessivo!$B:$B,H$2,DB_Complessivo!$H:$H,$A9)-SUMIFS(DB_Complessivo!$E:$E,DB_Complessivo!$A:$A,H$1,DB_Complessivo!$B:$B,G$2,DB_Complessivo!$H:$H,$A9))/1000 -> -49.97024 | I9: =-(SUMIFS(DB_Complessivo!$E:$E,DB_Complessivo!$A:$A,I$1,DB_Complessivo!$B:$B,I$2,DB_Complessivo!$H:$H,$A9)-SUMIFS(DB_Complessivo!$E:$E,DB_Complessivo!$A:$A,I$1,DB_Complessivo!$B:$B,H$2,DB_Complessivo!$H:$H,$A9))/1000 -> -1.6508 | J9: =-(SUMIFS(DB_Complessivo!$E:$E,DB_Complessivo!$A:$A,J$1,DB_Complessivo!$B:$B,J$2,DB_Complessivo!$H:$H,$A9)-SUMIFS(DB_Complessivo!$E:$E,DB_Complessivo!$A:$A,J$1,DB_Complessivo!$B:$B,I$2,DB_Complessivo!$H:$H,$A9))/1000 -> 0 | K9: =-(SUMIFS(DB_Complessivo!$E:$E,DB_Complessivo!$A:$A,K$1,DB_Complessivo!$B:$B,K$2,DB_Complessivo!$H:$H,$A9)-SUMIFS(DB_Complessivo!$E:$E,DB_Complessivo!$A:$A,K$1,DB_Complessivo!$B:$B,J$2,DB_Complessivo!$H:$H,$A9))/1000 -> 0 | L9: =-(SUMIFS(DB_Complessivo!$E:$E,DB_Complessivo!$A:$A,L$1,DB_Complessivo!$B:$B,L$2,DB_Complessivo!$H:$H,$A9)-SUMIFS(DB_Complessivo!$E:$E,DB_Complessivo!$A:$A,L$1,DB_Complessivo!$B:$B,K$2,DB_Complessivo!$H:$H,$A9))/1000 -> 0 | ... O9: =-(SUMIFS(DB_Complessivo!$E:$E,DB_Complessivo!$A:$A,O$1,DB_Complessivo!$B:$B,O$2,DB_Complessivo!$H:$H,$A9)-SUMIFS(DB_Complessivo!$E:$E,DB_Complessivo!$A:$A,O$1,DB_Complessivo!$B:$B,N$2,DB_Complessivo!$H:$H,$A9))/1000 -> 0
A10: SERDI | C10: Lavorazioni esterne | D10: =-SUMIFS(DB_Complessivo!$E:$E,DB_Complessivo!$A:$A,"ACT",DB_Complessivo!$B:$B,D$2,DB_Complessivo!$H:$H,$A10)/1000 -> -79.86552 | E10: =-(SUMIFS(DB_Complessivo!$E:$E,DB_Complessivo!$A:$A,E$1,DB_Complessivo!$B:$B,E$2,DB_Complessivo!$H:$H,$A10)-SUMIFS(DB_Complessivo!$E:$E,DB_Complessivo!$A:$A,E$1,DB_Complessivo!$B:$B,D$2,DB_Complessivo!$H:$H,$A10))/1000 -> -59.76614 | F10: =-(SUMIFS(DB_Complessivo!$E:$E,DB_Complessivo!$A:$A,F$1,DB_Complessivo!$B:$B,F$2,DB_Complessivo!$H:$H,$A10)-SUMIFS(DB_Complessivo!$E:$E,DB_Complessivo!$A:$A,F$1,DB_Complessivo!$B:$B,E$2,DB_Complessivo!$H:$H,$A10))/1000 -> -78.6323 | G10: =-(SUMIFS(DB_Complessivo!$E:$E,DB_Complessivo!$A:$A,G$1,DB_Complessivo!$B:$B,G$2,DB_Complessivo!$H:$H,$A10)-SUMIFS(DB_Complessivo!$E:$E,DB_Complessivo!$A:$A,G$1,DB_Complessivo!$B:$B,F$2,DB_Complessivo!$H:$H,$A10))/1000 -> -116.46684 | H10: =-(SUMIFS(DB_Complessivo!$E:$E,DB_Complessivo!$A:$A,H$1,DB_Complessivo!$B:$B,H$2,DB_Complessivo!$H:$H,$A10)-SUMIFS(DB_Complessivo!$E:$E,DB_Complessivo!$A:$A,H$1,DB_Complessivo!$B:$B,G$2,DB_Complessivo!$H:$H,$A10))/1000 -> -125.63973 | I10: =-(SUMIFS(DB_Complessivo!$E:$E,DB_Complessivo!$A:$A,I$1,DB_Complessivo!$B:$B,I$2,DB_Complessivo!$H:$H,$A10)-SUMIFS(DB_Complessivo!$E:$E,DB_Complessivo!$A:$A,I$1,DB_Complessivo!$B:$B,H$2,DB_Complessivo!$H:$H,$A10))/1000 -> -58.85199 | J10: =-(SUMIFS(DB_Complessivo!$E:$E,DB_Complessivo!$A:$A,J$1,DB_Complessivo!$B:$B,J$2,DB_Complessivo!$H:$H,$A10)-SUMIFS(DB_Complessivo!$E:$E,DB_Complessivo!$A:$A,J$1,DB_Complessivo!$B:$B,I$2,DB_Complessivo!$H:$H,$A10))/1000 -> -106.04087 | K10: =-(SUMIFS(DB_Complessivo!$E:$E,DB_Complessivo!$A:$A,K$1,DB_Complessivo!$B:$B,K$2,DB_Complessivo!$H:$H,$A10)-SUMIFS(DB_Complessivo!$E:$E,DB_Complessivo!$A:$A,K$1,DB_Complessivo!$B:$B,J$2,DB_Complessivo!$H:$H,$A10))/1000 -> -53.020435 | L10: =-(SUMIFS(DB_Complessivo!$E:$E,DB_Complessivo!$A:$A,L$1,DB_Complessivo!$B:$B,L$2,DB_Complessivo!$H:$H,$A10)-SUMIFS(DB_Complessivo!$E:$E,DB_Complessivo!$A:$A,L$1,DB_Complessivo!$B:$B,K$2,DB_Complessivo!$H:$H,$A10))/1000 -> -106.04087 | ... O10: =-(SUMIFS(DB_Complessivo!$E:$E,DB_Complessivo!$A:$A,O$1,DB_Complessivo!$B:$B,O$2,DB_Complessivo!$H:$H,$A10)-SUMIFS(DB_Complessivo!$E:$E,DB_Complessivo!$A:$A,O$1,DB_Complessivo!$B:$B,N$2,DB_Complessivo!$H:$H,$A10))/1000 -> -106.04087
A11: PERDI | C11: Manodopera diretta di produzione | D11: =-SUMIFS(DB_Complessivo!$E:$E,DB_Complessivo!$A:$A,"ACT",DB_Complessivo!$B:$B,D$2,DB_Complessivo!$H:$H,$A11)/1000 -> -129.28997 | E11: =-(SUMIFS(DB_Complessivo!$E:$E,DB_Complessivo!$A:$A,E$1,DB_Complessivo!$B:$B,E$2,DB_Complessivo!$H:$H,$A11)-SUMIFS(DB_Complessivo!$E:$E,DB_Complessivo!$A:$A,E$1,DB_Complessivo!$B:$B,D$2,DB_Complessivo!$H:$H,$A11))/1000 -> -129.61934 | F11: =-(SUMIFS(DB_Complessivo!$E:$E,DB_Complessivo!$A:$A,F$1,DB_Complessivo!$B:$B,F$2,DB_Complessivo!$H:$H,$A11)-SUMIFS(DB_Complessivo!$E:$E,DB_Complessivo!$A:$A,F$1,DB_Complessivo!$B:$B,E$2,DB_Complessivo!$H:$H,$A11))/1000 -> -124.96838 | G11: =-(SUMIFS(DB_Complessivo!$E:$E,DB_Complessivo!$A:$A,G$1,DB_Complessivo!$B:$B,G$2,DB_Complessivo!$H:$H,$A11)-SUMIFS(DB_Complessivo!$E:$E,DB_Complessivo!$A:$A,G$1,DB_Complessivo!$B:$B,F$2,DB_Complessivo!$H:$H,$A11))/1000 -> -136.71602 | H11: =-(SUMIFS(DB_Complessivo!$E:$E,DB_Complessivo!$A:$A,H$1,DB_Complessivo!$B:$B,H$2,DB_Complessivo!$H:$H,$A11)-SUMIFS(DB_Complessivo!$E:$E,DB_Complessivo!$A:$A,H$1,DB_Complessivo!$B:$B,G$2,DB_Complessivo!$H:$H,$A11))/1000 -> -136.53407 | I11: =-(SUMIFS(DB_Complessivo!$E:$E,DB_Complessivo!$A:$A,I$1,DB_Complessivo!$B:$B,I$2,DB_Complessivo!$H:$H,$A11)-SUMIFS(DB_Complessivo!$E:$E,DB_Complessivo!$A:$A,I$1,DB_Complessivo!$B:$B,H$2,DB_Complessivo!$H:$H,$A11))/1000 -> -122.89906 | J11: =-(SUMIFS(DB_Complessivo!$E:$E,DB_Complessivo!$A:$A,J$1,DB_Complessivo!$B:$B,J$2,DB_Complessivo!$H:$H,$A11)-SUMIFS(DB_Complessivo!$E:$E,DB_Complessivo!$A:$A,J$1,DB_Complessivo!$B:$B,I$2,DB_Complessivo!$H:$H,$A11))/1000 -> -138.33655 | K11: =-(SUMIFS(DB_Complessivo!$E:$E,DB_Complessivo!$A:$A,K$1,DB_Complessivo!$B:$B,K$2,DB_Complessivo!$H:$H,$A11)-SUMIFS(DB_Complessivo!$E:$E,DB_Complessivo!$A:$A,K$1,DB_Complessivo!$B:$B,J$2,DB_Complessivo!$H:$H,$A11))/1000 -> -103.75241 | L11: =-(SUMIFS(DB_Complessivo!$E:$E,DB_Complessivo!$A:$A,L$1,DB_Complessivo!$B:$B,L$2,DB_Complessivo!$H:$H,$A11)-SUMIFS(DB_Complessivo!$E:$E,DB_Complessivo!$A:$A,L$1,DB_Complessivo!$B:$B,K$2,DB_Complessivo!$H:$H,$A11))/1000 -> -138.33655 | ... O11: =-(SUMIFS(DB_Complessivo!$E:$E,DB_Complessivo!$A:$A,O$1,DB_Complessivo!$B:$B,O$2,DB_Complessivo!$H:$H,$A11)-SUMIFS(DB_Complessivo!$E:$E,DB_Complessivo!$A:$A,O$1,DB_Complessivo!$B:$B,N$2,DB_Complessivo!$H:$H,$A11))/1000 -> -138.33655
A12: SUBTOTALE | C12: Totale costi diretti di produzione | D12: =SUM(D7:D11) -> 481.70892 | E12: =SUM(E7:E11) -> 289.5643 | F12: =SUM(F7:F11) -> 252.12946 | G12: =SUM(G7:G11) -> 421.37981 | H12: =SUM(H7:H11) -> 311.46774 | I12: =SUM(I7:I11) -> 421.75393 | J12: =SUM(J7:J11) -> 205.93501 | K12: =SUM(K7:K11) -> 176.90818 | ... O12: =SUM(O7:O11) -> 202.93501
A13: SUBTOTALE | C13: Margine diretto di produzione | D13: =IFERROR(D12/D$7,"") -> 0.81742629 | E13: =IFERROR(E12/E$7,"") -> 0.55984643 | F13: =IFERROR(F12/F$7,"") -> 0.39828006 | G13: =IFERROR(G12/G$7,"") -> 0.58026992 | H13: =IFERROR(H12/H$7,"") -> 0.45211846 | I13: =IFERROR(I12/I$7,"") -> 0.61298384 | J13: =IFERROR(J12/J$7,"") -> 0.42734608 | K13: =IFERROR(K12/K$7,"") -> 0.4984834 | ... O13: =IFERROR(O12/O$7,"") -> 0.42375871
A14: ACQIN | C14: Acquisti indiretti di fabbrica | D14: =-SUMIFS(DB_Complessivo!$E:$E,DB_Complessivo!$A:$A,"ACT",DB_Complessivo!$B:$B,D$2,DB_Complessivo!$H:$H,$A14)/1000 -> -3.56428 | E14: =-(SUMIFS(DB_Complessivo!$E:$E,DB_Complessivo!$A:$A,E$1,DB_Complessivo!$B:$B,E$2,DB_Complessivo!$H:$H,$A14)-SUMIFS(DB_Complessivo!$E:$E,DB_Complessivo!$A:$A,E$1,DB_Complessivo!$B:$B,D$2,DB_Complessivo!$H:$H,$A14))/1000 -> -0.81304 | F14: =-(SUMIFS(DB_Complessivo!$E:$E,DB_Complessivo!$A:$A,F$1,DB_Complessivo!$B:$B,F$2,DB_Complessivo!$H:$H,$A14)-SUMIFS(DB_Complessivo!$E:$E,DB_Complessivo!$A:$A,F$1,DB_Complessivo!$B:$B,E$2,DB_Complessivo!$H:$H,$A14))/1000 -> -2.23828 | G14: =-(SUMIFS(DB_Complessivo!$E:$E,DB_Complessivo!$A:$A,G$1,DB_Complessivo!$B:$B,G$2,DB_Complessivo!$H:$H,$A14)-SUMIFS(DB_Complessivo!$E:$E,DB_Complessivo!$A:$A,G$1,DB_Complessivo!$B:$B,F$2,DB_Complessivo!$H:$H,$A14))/1000 -> -1.43699 | H14: =-(SUMIFS(DB_Complessivo!$E:$E,DB_Complessivo!$A:$A,H$1,DB_Complessivo!$B:$B,H$2,DB_Complessivo!$H:$H,$A14)-SUMIFS(DB_Complessivo!$E:$E,DB_Complessivo!$A:$A,H$1,DB_Complessivo!$B:$B,G$2,DB_Complessivo!$H:$H,$A14))/1000 -> -0.03172 | I14: =-(SUMIFS(DB_Complessivo!$E:$E,DB_Complessivo!$A:$A,I$1,DB_Complessivo!$B:$B,I$2,DB_Complessivo!$H:$H,$A14)-SUMIFS(DB_Complessivo!$E:$E,DB_Complessivo!$A:$A,I$1,DB_Complessivo!$B:$B,H$2,DB_Complessivo!$H:$H,$A14))/1000 -> -1.74704 | J14: =-(SUMIFS(DB_Complessivo!$E:$E,DB_Complessivo!$A:$A,J$1,DB_Complessivo!$B:$B,J$2,DB_Complessivo!$H:$H,$A14)-SUMIFS(DB_Complessivo!$E:$E,DB_Complessivo!$A:$A,J$1,DB_Complessivo!$B:$B,I$2,DB_Complessivo!$H:$H,$A14))/1000 -> -0.87677 | K14: =-(SUMIFS(DB_Complessivo!$E:$E,DB_Complessivo!$A:$A,K$1,DB_Complessivo!$B:$B,K$2,DB_Complessivo!$H:$H,$A14)-SUMIFS(DB_Complessivo!$E:$E,DB_Complessivo!$A:$A,K$1,DB_Complessivo!$B:$B,J$2,DB_Complessivo!$H:$H,$A14))/1000 -> -1.057348 | L14: =-(SUMIFS(DB_Complessivo!$E:$E,DB_Complessivo!$A:$A,L$1,DB_Complessivo!$B:$B,L$2,DB_Complessivo!$H:$H,$A14)-SUMIFS(DB_Complessivo!$E:$E,DB_Complessivo!$A:$A,L$1,DB_Complessivo!$B:$B,K$2,DB_Complessivo!$H:$H,$A14))/1000 -> -0.819216 | ... O14: =-(SUMIFS(DB_Complessivo!$E:$E,DB_Complessivo!$A:$A,O$1,DB_Complessivo!$B:$B,O$2,DB_Complessivo!$H:$H,$A14)-SUMIFS(DB_Complessivo!$E:$E,DB_Complessivo!$A:$A,O$1,DB_Complessivo!$B:$B,N$2,DB_Complessivo!$H:$H,$A14))/1000 -> -0.763486
A15: PERIM | C15: Costi del personale diretto improduttivo | D15: =-SUMIFS(DB_Complessivo!$E:$E,DB_Complessivo!$A:$A,"ACT",DB_Complessivo!$B:$B,D$2,DB_Complessivo!$H:$H,$A15)/1000 -> -55.409988 | E15: =-(SUMIFS(DB_Complessivo!$E:$E,DB_Complessivo!$A:$A,E$1,DB_Complessivo!$B:$B,E$2,DB_Complessivo!$H:$H,$A15)-SUMIFS(DB_Complessivo!$E:$E,DB_Complessivo!$A:$A,E$1,DB_Complessivo!$B:$B,D$2,DB_Complessivo!$H:$H,$A15))/1000 -> -55.551145 | F15: =-(SUMIFS(DB_Complessivo!$E:$E,DB_Complessivo!$A:$A,F$1,DB_Complessivo!$B:$B,F$2,DB_Complessivo!$H:$H,$A15)-SUMIFS(DB_Complessivo!$E:$E,DB_Complessivo!$A:$A,F$1,DB_Complessivo!$B:$B,E$2,DB_Complessivo!$H:$H,$A15))/1000 -> -53.557877 | G15: =-(SUMIFS(DB_Complessivo!$E:$E,DB_Complessivo!$A:$A,G$1,DB_Complessivo!$B:$B,G$2,DB_Complessivo!$H:$H,$A15)-SUMIFS(DB_Complessivo!$E:$E,DB_Complessivo!$A:$A,G$1,DB_Complessivo!$B:$B,F$2,DB_Complessivo!$H:$H,$A15))/1000 -> -58.59258 | H15: =-(SUMIFS(DB_Complessivo!$E:$E,DB_Complessivo!$A:$A,H$1,DB_Complessivo!$B:$B,H$2,DB_Complessivo!$H:$H,$A15)-SUMIFS(DB_Complessivo!$E:$E,DB_Complessivo!$A:$A,H$1,DB_Complessivo!$B:$B,G$2,DB_Complessivo!$H:$H,$A15))/1000 -> -58.514603 | I15: =-(SUMIFS(DB_Complessivo!$E:$E,DB_Complessivo!$A:$A,I$1,DB_Complessivo!$B:$B,I$2,DB_Complessivo!$H:$H,$A15)-SUMIFS(DB_Complessivo!$E:$E,DB_Complessivo!$A:$A,I$1,DB_Complessivo!$B:$B,H$2,DB_Complessivo!$H:$H,$A15))/1000 -> -52.671026 | J15: =-(SUMIFS(DB_Complessivo!$E:$E,DB_Complessivo!$A:$A,J$1,DB_Complessivo!$B:$B,J$2,DB_Complessivo!$H:$H,$A15)-SUMIFS(DB_Complessivo!$E:$E,DB_Complessivo!$A:$A,J$1,DB_Complessivo!$B:$B,I$2,DB_Complessivo!$H:$H,$A15))/1000 -> -59.287091 | K15: =-(SUMIFS(DB_Complessivo!$E:$E,DB_Complessivo!$A:$A,K$1,DB_Complessivo!$B:$B,K$2,DB_Complessivo!$H:$H,$A15)-SUMIFS(DB_Complessivo!$E:$E,DB_Complessivo!$A:$A,K$1,DB_Complessivo!$B:$B,J$2,DB_Complessivo!$H:$H,$A15))/1000 -> -44.465318 | L15: =-(SUMIFS(DB_Complessivo!$E:$E,DB_Complessivo!$A:$A,L$1,DB_Complessivo!$B:$B,L$2,DB_Complessivo!$H:$H,$A15)-SUMIFS(DB_Complessivo!$E:$E,DB_Complessivo!$A:$A,L$1,DB_Complessivo!$B:$B,K$2,DB_Complessivo!$H:$H,$A15))/1000 -> -59.287091 | ... O15: =-(SUMIFS(DB_Complessivo!$E:$E,DB_Complessivo!$A:$A,O$1,DB_Complessivo!$B:$B,O$2,DB_Complessivo!$H:$H,$A15)-SUMIFS(DB_Complessivo!$E:$E,DB_Complessivo!$A:$A,O$1,DB_Complessivo!$B:$B,N$2,DB_Complessivo!$H:$H,$A15))/1000 -> -59.287091
A16: PERIN | C16: Costi del Personale indiretto di fabbrica | D16: =-SUMIFS(DB_Complessivo!$E:$E,DB_Complessivo!$A:$A,"ACT",DB_Complessivo!$B:$B,D$2,DB_Complessivo!$H:$H,$A16)/1000 -> -59.855184 | E16: =-(SUMIFS(DB_Complessivo!$E:$E,DB_Complessivo!$A:$A,E$1,DB_Complessivo!$B:$B,E$2,DB_Complessivo!$H:$H,$A16)-SUMIFS(DB_Complessivo!$E:$E,DB_Complessivo!$A:$A,E$1,DB_Complessivo!$B:$B,D$2,DB_Complessivo!$H:$H,$A16))/1000 -> -58.432939 | F16: =-(SUMIFS(DB_Complessivo!$E:$E,DB_Complessivo!$A:$A,F$1,DB_Complessivo!$B:$B,F$2,DB_Complessivo!$H:$H,$A16)-SUMIFS(DB_Complessivo!$E:$E,DB_Complessivo!$A:$A,F$1,DB_Complessivo!$B:$B,E$2,DB_Complessivo!$H:$H,$A16))/1000 -> -91.718601 | G16: =-(SUMIFS(DB_Complessivo!$E:$E,DB_Complessivo!$A:$A,G$1,DB_Complessivo!$B:$B,G$2,DB_Complessivo!$H:$H,$A16)-SUMIFS(DB_Complessivo!$E:$E,DB_Complessivo!$A:$A,G$1,DB_Complessivo!$B:$B,F$2,DB_Complessivo!$H:$H,$A16))/1000 -> -213.59886 | H16: =-(SUMIFS(DB_Complessivo!$E:$E,DB_Complessivo!$A:$A,H$1,DB_Complessivo!$B:$B,H$2,DB_Complessivo!$H:$H,$A16)-SUMIFS(DB_Complessivo!$E:$E,DB_Complessivo!$A:$A,H$1,DB_Complessivo!$B:$B,G$2,DB_Complessivo!$H:$H,$A16))/1000 -> 80.724233 | I16: =-(SUMIFS(DB_Complessivo!$E:$E,DB_Complessivo!$A:$A,I$1,DB_Complessivo!$B:$B,I$2,DB_Complessivo!$H:$H,$A16)-SUMIFS(DB_Complessivo!$E:$E,DB_Complessivo!$A:$A,I$1,DB_Complessivo!$B:$B,H$2,DB_Complessivo!$H:$H,$A16))/1000 -> -63.692227 | J16: =-(SUMIFS(DB_Complessivo!$E:$E,DB_Complessivo!$A:$A,J$1,DB_Complessivo!$B:$B,J$2,DB_Complessivo!$H:$H,$A16)-SUMIFS(DB_Complessivo!$E:$E,DB_Complessivo!$A:$A,J$1,DB_Complessivo!$B:$B,I$2,DB_Complessivo!$H:$H,$A16))/1000 -> -68.559125 | K16: =-(SUMIFS(DB_Complessivo!$E:$E,DB_Complessivo!$A:$A,K$1,DB_Complessivo!$B:$B,K$2,DB_Complessivo!$H:$H,$A16)-SUMIFS(DB_Complessivo!$E:$E,DB_Complessivo!$A:$A,K$1,DB_Complessivo!$B:$B,J$2,DB_Complessivo!$H:$H,$A16))/1000 -> -48.25709 | L16: =-(SUMIFS(DB_Complessivo!$E:$E,DB_Complessivo!$A:$A,L$1,DB_Complessivo!$B:$B,L$2,DB_Complessivo!$H:$H,$A16)-SUMIFS(DB_Complessivo!$E:$E,DB_Complessivo!$A:$A,L$1,DB_Complessivo!$B:$B,K$2,DB_Complessivo!$H:$H,$A16))/1000 -> -64.342787 | ... O16: =-(SUMIFS(DB_Complessivo!$E:$E,DB_Complessivo!$A:$A,O$1,DB_Complessivo!$B:$B,O$2,DB_Complessivo!$H:$H,$A16)-SUMIFS(DB_Complessivo!$E:$E,DB_Complessivo!$A:$A,O$1,DB_Complessivo!$B:$B,N$2,DB_Complessivo!$H:$H,$A16))/1000 -> -66.342787
A17: SERIN | C17: Servizi indiretti di fabbrica | D17: =-SUMIFS(DB_Complessivo!$E:$E,DB_Complessivo!$A:$A,"ACT",DB_Complessivo!$B:$B,D$2,DB_Complessivo!$H:$H,$A17)/1000 -> -12.6146 | E17: =-(SUMIFS(DB_Complessivo!$E:$E,DB_Complessivo!$A:$A,E$1,DB_Complessivo!$B:$B,E$2,DB_Complessivo!$H:$H,$A17)-SUMIFS(DB_Complessivo!$E:$E,DB_Complessivo!$A:$A,E$1,DB_Complessivo!$B:$B,D$2,DB_Complessivo!$H:$H,$A17))/1000 -> -15.81967 | F17: =-(SUMIFS(DB_Complessivo!$E:$E,DB_Complessivo!$A:$A,F$1,DB_Complessivo!$B:$B,F$2,DB_Complessivo!$H:$H,$A17)-SUMIFS(DB_Complessivo!$E:$E,DB_Complessivo!$A:$A,F$1,DB_Complessivo!$B:$B,E$2,DB_Complessivo!$H:$H,$A17))/1000 -> -8.80182 | G17: =-(SUMIFS(DB_Complessivo!$E:$E,DB_Complessivo!$A:$A,G$1,DB_Complessivo!$B:$B,G$2,DB_Complessivo!$H:$H,$A17)-SUMIFS(DB_Complessivo!$E:$E,DB_Complessivo!$A:$A,G$1,DB_Complessivo!$B:$B,F$2,DB_Complessivo!$H:$H,$A17))/1000 -> -11.1116 | H17: =-(SUMIFS(DB_Complessivo!$E:$E,DB_Complessivo!$A:$A,H$1,DB_Complessivo!$B:$B,H$2,DB_Complessivo!$H:$H,$A17)-SUMIFS(DB_Complessivo!$E:$E,DB_Complessivo!$A:$A,H$1,DB_Complessivo!$B:$B,G$2,DB_Complessivo!$H:$H,$A17))/1000 -> -22.69203 | I17: =-(SUMIFS(DB_Complessivo!$E:$E,DB_Complessivo!$A:$A,I$1,DB_Complessivo!$B:$B,I$2,DB_Complessivo!$H:$H,$A17)-SUMIFS(DB_Complessivo!$E:$E,DB_Complessivo!$A:$A,I$1,DB_Complessivo!$B:$B,H$2,DB_Complessivo!$H:$H,$A17))/1000 -> -25.72489 | J17: =-(SUMIFS(DB_Complessivo!$E:$E,DB_Complessivo!$A:$A,J$1,DB_Complessivo!$B:$B,J$2,DB_Complessivo!$H:$H,$A17)-SUMIFS(DB_Complessivo!$E:$E,DB_Complessivo!$A:$A,J$1,DB_Complessivo!$B:$B,I$2,DB_Complessivo!$H:$H,$A17))/1000 -> -20.997513 | K17: =-(SUMIFS(DB_Complessivo!$E:$E,DB_Complessivo!$A:$A,K$1,DB_Complessivo!$B:$B,K$2,DB_Complessivo!$H:$H,$A17)-SUMIFS(DB_Complessivo!$E:$E,DB_Complessivo!$A:$A,K$1,DB_Complessivo!$B:$B,J$2,DB_Complessivo!$H:$H,$A17))/1000 -> -20.997513 | L17: =-(SUMIFS(DB_Complessivo!$E:$E,DB_Complessivo!$A:$A,L$1,DB_Complessivo!$B:$B,L$2,DB_Complessivo!$H:$H,$A17)-SUMIFS(DB_Complessivo!$E:$E,DB_Complessivo!$A:$A,L$1,DB_Complessivo!$B:$B,K$2,DB_Complessivo!$H:$H,$A17))/1000 -> -20.997513 | ... O17: =-(SUMIFS(DB_Complessivo!$E:$E,DB_Complessivo!$A:$A,O$1,DB_Complessivo!$B:$B,O$2,DB_Complessivo!$H:$H,$A17)-SUMIFS(DB_Complessivo!$E:$E,DB_Complessivo!$A:$A,O$1,DB_Complessivo!$B:$B,N$2,DB_Complessivo!$H:$H,$A17))/1000 -> -20.997513
